Workbook

Sheet Annotations
A1: File | B1: Assigned_to | C1: Status | D1: Correct answer | E1: Explanation 1 | F1: Explanation 2 | G1: Explanation 3 | H1: Literal_Description | I1: Humor Style | J1: Humor style secondary | K1: Contextual Knowledge | L1: Contextual Knowledge secondary | M1: Duplicate check
A2: 13ibrc1 | B2: Sabrina | C2: Done | D2: Let’s start with the comic. The two shallow and wide glasses hold the same amount of liquid. The next panels you see the transfer of the liquid to the taller thin glass. The volume and quantity of the liquid remains the same. The third panel the child points to the taller glass. This whole set up is a standard test for the developmental level of a child. The goal is to tell which glass holds the most liquid. It’s commonly for young children to look at the glass and see that it’s taller and say that has the most liquid, simply because they lack the understanding to consider the width of the glass. This occurs even if you pour it right in front of them. So the comment from Lara Trump follows a similar logic. The red portion of the map outlines Republican districts, the blue outlines Democratic districts. She is implying that because the red covers the majority of the map, most of the country is Republican and therefor would be unable to impeach them. The comic is pointing out that although the red map covers more land than blue, it does not accurately convey the number of voters, because the blue districts hold the same or more of the population due to population density. | E2: A Reddit screenshot shows a tweet with a red-and-blue map of the United States and the text “Try to impeach this.” Under it, another user replies with a three-panel image of a child pouring liquid between containers. | F2: Trump’s daughter appears to be trolling people online by posting a map that makes it look like far more people voted for her dad. It comes across as a deliberately provocative post meant to annoy or bait people on X. | G2: She seems to have edited or presented the voting map in a way that makes it look much redder than it actually is. The image gives the impression that the results are being manipulated visually to support her point. | H2: A Reddit screenshot shows a tweet with a red-and-blue map of the United States and the text “Try to impeach this.” Under it, another user replies with a three-panel image of a child pouring liquid between containers. | I2: Comparison | J2: Sarcasm/Irony | K2: Logical | L2: politics | M2: =IF(COUNTIF($A$2:A2, A2)>1, "Dublet", "OK") -> OK
A3: 14ys2z4 | B3: Naomi | C3: Done | D3: Centrists or people that dont participate in politics are often viewed as grillers, they just want to take a load off and not worry about the chaos. Daughter is saying the boyfriend doesnt have to worry about her dad taking a stand to them because he doesnt stand for anything basically | E3: A four-panel illustrated comic. The first panel shows a teenage couple about to kiss on a bed; the boy nervously asks, "W-wait... isn't your dad home?" The second panel shows the girl reassuring him, "It's okay. He won't do anything. Never does." The third panel shows a bald, hollow-eyed dad at a flaming grill with the caption "My dad's a griller." The fourth panel is a close-up of the same gaunt, exhausted-looking father holding a beer can under a starry night sky. | F3: The "griller" subspecies in the wild — beer in hand, soul somewhere else. | G3: Dad has transcended fatherhood and entered his charcoal-priest era. | H3: A four-panel illustrated comic. The first panel shows a teenage couple about to kiss on a bed; the boy nervously asks, "W-wait... isn't your dad home?" The second panel shows the girl reassuring him, "It's okay. He won't do anything. Never does." The third panel shows a bald, hollow-eyed dad at a flaming grill with the caption "My dad's a griller." The fourth panel is a close-up of the same gaunt, exhausted-looking father holding a beer can under a starry night sky. | I3: Wordplay | J3: Situational | K3: politics | L3: Logical | M3: =IF(COUNTIF($A$2:A3, A3)>1, "Dublet", "OK") -> OK
A4: 1587f2g | B4: Naomi | C4: Done | D4: I saw an explanation for this a while ago, you have to know hair to get this one. The haircut on the right is mid-hairdress, and the one on the left is the finished look. So while the one on the right looks more artificial and the one on the left looks more natural, the one on the left is actually the complete look. It's essentially saying that you put more effort into yourself than the chick your bf is banging, and he doesn't appreciate that. | E4: Its hilarious because the two are exactly identical. | F4: The image shows a side-by-side comparison of two blonde hairstyles: soft, brushed-out waves on the left and tight, unbrushed ringlets on the right. The text at the top reads "you vs. the girl he cheats with," while a social media comment at the bottom states that the user enjoys the idea of men not understanding the post. | G4: Its because the two images show the hair curling in opposite dorections in the image making the joke that men are never satisifed and are destined to cheat. | H4: The image shows a side-by-side comparison of two blonde hairstyles: soft, brushed-out waves on the left and tight, unbrushed ringlets on the right. The text at the top reads "you vs. the girl he cheats with," while a social media comment at the bottom states that the user enjoys the idea of men not understanding the post. | I4: Exaggeration | J4: Comparison | K4: Technical | L4: Social conventions | M4: =IF(COUNTIF($A$2:A4, A4)>1, "Dublet", "OK") -> OK
A5: 15a2flm | B5: Naomi | C5: Done | D5: With a new job, you can get days off by saying your grandparent died. You're new at the company so no one knows that they're already dead. Use up to 4 times. | E5: Day one of a new job and grandma is suddenly alive, dying, and Catholic again. | F5: A screenshot of a tweet from "stoned cold fox" (@roastmalone_) reading: "the best part of starting a new job is all 4 of your grandparents are alive again." | G5: PTO loophole that resurrects your entire family tree on demand. | H5: A screenshot of a tweet from "stoned cold fox" (@roastmalone_) reading: "the best part of starting a new job is all 4 of your grandparents are alive again." | I5: Dark Humor | J5: Situational | K5: General knowledge | L5: Social conventions | M5: =IF(COUNTIF($A$2:A5, A5)>1, "Dublet", "OK") -> OK
A6: 15gdv3c | B6: Naomi | C6: Done | D6: Morning after pill | E6: A meme captioned "When you're on deployment and your wife spends $50 at CVS at 8:21am" with a close-up photo of a soldier in a helmet with a single tear running down his cheek. | F6: The exact timestamp where a deployment check-in becomes a Maury episode. | G6: Pre-9 AM pharmacy receipt that delivers a paternity verdict before breakfast. | H6: A meme captioned "When you're on deployment and your wife spends $50 at CVS at 8:21am" with a close-up photo of a soldier in a helmet with a single tear running down his cheek. | I6: Dark Humor | J6: Sarcasm/Irony | K6: General knowledge | L6: Logical | M6: =IF(COUNTIF($A$2:A6, A6)>1, "Dublet", "OK") -> OK
A7: 15h4szq | B7: Naomi | C7: Done | D7: In Platos republic, Plato argues that the best society is one in which a astiorcratic elite who have spent their whole lives training and learning the art of statecraft should be the rulers. The idea is that if someone has been trained in the art of statecraft and philosophy from birth they will be the idea ruler or "philosopher king" who seeks council from other who are skilled in their professions. Super simplified, in an ideal world, people would fulfil a specific role and be happy about it. In Barbie, each of the Barbies holds a specific role they were created for, their ruler rules and does so well, because they were created to rule. The Barbies are happy about it. You could argue it looks like Platos ideal republic | E7: This is because Plato is one of the first people to come up with an idea of society and barbie is a modern version of it. | F7: A two-panel meme that humorously labels the 2023 Barbie movie poster as "the anime" and the cover of Plato's The Republic as "the manga," satirizing the common gatekeeping trope that one cannot appreciate an adaptation without reading its "source material." | G7: It is incongruous which makes it funny since Plato is an important philosopher and he ahs nothing in common with childrens toy brand. | H7: A two-panel meme that humorously labels the 2023 Barbie movie poster as "the anime" and the cover of Plato's The Republic as "the manga," satirizing the common gatekeeping trope that one cannot appreciate an adaptation without reading its "source material." | I7: Comparison | J7: Situational | K7: History/Mythology | L7: Pop culture | M7: =IF(COUNTIF($A$2:A7, A7)>1, "Dublet", "OK") -> OK
A8: 15oof8t | B8: Naomi | C8: Done | D8: The joke is that young girls keep asking their bfs stupid shit like would you still love me if I were a worm?" A bunch of weird things can be slotted in there, but worm seems to be the most popular one. The bouncer is crying because of the intense love he knows the man must feel for his "girlfriend" since they're still together despite her being now a worm." | E8: Door policy bent for the most heartfelt parasitic relationship at the club. | F8: A three-panel comic by @beetlemoses. The first panel shows a bald, bearded bouncer stopping a man saying "Whoa, pal. No entry without a girl." The second panel reveals the man's huge muscular chest with a tapeworm peeking out as he says "But sir—I'm with my girlfriend." The third panel shows the bouncer tearfully waving the velvet rope aside while the man walks past, giving a thumbs-up. | G8: A bouncer reduced to tears by an unconventional plus-one situation. | H8: A three-panel comic by @beetlemoses. The first panel shows a bald, bearded bouncer stopping a man saying "Whoa, pal. No entry without a girl." The second panel reveals the man's huge muscular chest with a tapeworm peeking out as he says "But sir—I'm with my girlfriend." The third panel shows the bouncer tearfully waving the velvet rope aside while the man walks past, giving a thumbs-up. | I8: Incongruity | J8: Surprise | K8: meme | L8: Pop culture | M8: =IF(COUNTIF($A$2:A8, A8)>1, "Dublet", "OK") -> OK
A9: 15upbjf | B9: Naomi | C9: Done | D9: Those are RCA cables. The yellow one is for video, white and red are audio. Van Gogh cut off a piece of his left ear, so he’s missing one of the audio cables. Beethoven was deaf, so he’s missing both audio cables. Stevie Wonder is blind, so he’s missing the video. | E9: The pre-HDMI cable hierarchy, narrated entirely through famous artists. | F9: Three historical figures matched with the AV cables that bypass their respective disabilities. | G9: A meme captioned "HDMI kids won't understand" showing three rows: Vincent van Gogh's self-portrait paired with yellow and red RCA cables, a portrait of Beethoven paired with a single yellow RCA cable, and a photo of Stevie Wonder paired with red and white RCA cables. | H9: A meme captioned "HDMI kids won't understand" showing three rows: Vincent van Gogh's self-portrait paired with yellow and red RCA cables, a portrait of Beethoven paired with a single yellow RCA cable, and a photo of Stevie Wonder paired with red and white RCA cables. | I9: Wordplay | J9: Comparison | K9: Technical | L9: History/Mythology | M9: =IF(COUNTIF($A$2:A9, A9)>1, "Dublet", "OK") -> OK
A10: 15vbd1p | B10: Sabrina | C10: Done | D10: At first I thought this was her being pregnant but I'm pretty sure it's actually another dude hiding in the closet cuz she's cheating. The heartbeats would be closer if she was pregnant. | E10: He starts crying because the heartbeat sensor he made actually works. In that moment, he is probably imagining all the people it could help, and it hits him that his invention might genuinely matter. | F10: He is crying because there is a bomb next to his girlfriend, and he has no idea how to tell her. She looks so calm and happy, which makes the situation feel even worse. | G10: A comic shows a woman lying on a bed while someone uses a heartbeat sensor nearby. In the next panel, a young man holding the device is crying with an emotional expression. | H10: A comic shows a woman lying on a bed while someone uses a heartbeat sensor nearby. In the next panel, a young man holding the device is crying with an emotional expression. | I10: Dark Humor | J10: Incongruity | K10: Logical | L10: Social conventions | M10: =IF(COUNTIF($A$2:A10, A10)>1, "Dublet", "OK") -> OK
A11: 15yqaf6 | B11: Naomi | C11: Done | D11: the double slit experiment, particles behave differently when they are observed. | E11: It humorously depicts paranoia and how you can feel things when your not looking. | F11: This meme depicts object permemanence. | G11: A two-panel meme featuring the "Monkey Puppet" character looking away and then forward, paired with diagrams | H11: A two-panel meme featuring the "Monkey Puppet" character looking away and then forward, paired with diagrams | I11: Incongruity | J11: Comparison | K11: Technical | L11: General knowledge | M11: =IF(COUNTIF($A$2:A11, A11)>1, "Dublet", "OK") -> OK
A12: 15aafk0 | B12: Naomi | C12: Done | D12: Everyone whose ages 12+ and older knows that the Harry Potter series deals with magic and eugenics. When the series first came out, it was vilified by fundamentalist Christians, mostly right wingers, for glorifying and promoting witchcraft. Naturally, the kids and the alternative crowd who had left wing views thought the world of Harry Potter was a safe space for their fascination with wand waving and British people, both of which are pretty gay. However, that all changed when J.K Rowling, the creator of the series made a controversial tweet ( Or Xeet \*Point and wink\*) about her feelings on trans people. The fandom quickly fell apart after this, resulting in most of the fandom in canceling Rowling by giving her the avada kedavra treatment. Ironically, the same right wingers who once called for her books to be banned and burned are now Rowling's biggest supports. Kind of like when the racists left the Democratic party after LBJ thought black people were cool. The joke here is that Harry Potter went from being loved by witchy girls to far right extremists after one tweet (Or Xeet \*Point and Wink\*). Now if you'll excuse me, I've just been sorted into Slytherin house and feel the urge to make fun of some mudbloods. ROADHOUSE! | E12: The Harry Potter box set quietly switching political affiliations in the night. | F12: A Facebook post from "The Brian Nichols Show" reading "Left wing literature, 2013 / Right wing literature, 2023" with two side-by-side images of the same Harry Potter complete book box set, the post having 42K reactions, 4.1K comments, and 5.3K shares. | G12: Same boxed set, two decades, opposite team jerseys. | H12: A Facebook post from "The Brian Nichols Show" reading "Left wing literature, 2013 / Right wing literature, 2023" with two side-by-side images of the same Harry Potter complete book box set, the post having 42K reactions, 4.1K comments, and 5.3K shares. | I12: Sarcasm/Irony | J12: Comparison | K12: Pop culture | L12: politics | M12: =IF(COUNTIF($A$2:A12, A12)>1, "Dublet", "OK") -> OK
A13: 164v3oo | B13: Naomi | C13: Done | D13: If you squint it looks like the painting girl with a pearl earring" The shirt of the girl on the left is the face." | E13: A meme captioned "Hold your phone as far from you as you can and squint your eyes" with two flushed-face emojis, above a black-and-white photo of two young girls in matching sweaters sitting together in a grassy field, smiling at each other. | F13: Optical illusion gag delivered via blurred sweater geometry. | G13: When pareidolia and a low-resolution sweater conspire to trick the viewer. | H13: A meme captioned "Hold your phone as far from you as you can and squint your eyes" with two flushed-face emojis, above a black-and-white photo of two young girls in matching sweaters sitting together in a grassy field, smiling at each other. | I13: Surprise | J13: Situational | K13: Logical | L13: General knowledge | M13: =IF(COUNTIF($A$2:A13, A13)>1, "Dublet", "OK") -> OK
... A39: 198awkk | B39: Naomi | C39: Done | D39: This is a popular riddle set up where one person tells the truth and the other always lies. You ask them one question to see which one is which. In this case, the setup asks the question, “do you understand the rules?” The guards both say “yes.” Since one always lies and one always tells the truth, it means that one of the guards is lying and doesn’t understand the rules | E39: Three "yes" answers and zero ways to tell which guard is lying. | F39: A three-panel comic by The Jenkins Comic. The first panel shows a top-hatted character explaining to a person in a red shirt: "...so one guard always tells the truth, and one always lies. But you don't know who's who." The second panel shows him concluding "And that's pretty much all the rules of the puzzle. Understand?" The third panel shows the person in red and both armored guards all saying "Yes" in unison. | G39: The classic logic puzzle, ruined by group consensus. | H39: A three-panel comic by The Jenkins Comic. The first panel shows a top-hatted character explaining to a person in a red shirt: "...so one guard always tells the truth, and one always lies. But you don't know who's who." The second panel shows him concluding "And that's pretty much all the rules of the puzzle. Understand?" The third panel shows the person in red and both armored guards all saying "Yes" in unison. | I39: Wordplay | J39: Sarcasm/Irony | K39: General knowledge | L39: Logical | M39: =IF(COUNTIF($A$2:A39, A39)>1, "Dublet", "OK") -> OK
A40: 19994ey | B40: Sabrina | C40: Done | D40: I'm assuming the idea that someone would think it's a gunshot in that neighborhood is absurd. Edit: I think the idea is absurd *to OP*. I'm not making a judgement one way or another. | E40: It is a cannibalism joke implying that they always get “chicken” after the dad has killed someone. | F40: Pizza had not been invented yet, which is why the situation does not really make sense historically. | G40: A four-panel comic shows a man in a helmet and formal clothing on a battlefield. He returns home holding a cooked chicken and tells his children that he brought dinner. The children complain that they are having chicken again and ask why he does not bring pizza next time, while the man looks upset. | H40: A four-panel comic shows a man in a helmet and formal clothing on a battlefield. He returns home holding a cooked chicken and tells his children that he brought dinner. The children complain that they are having chicken again and ask why he does not bring pizza next time, while the man looks upset. | I40: Exaggeration | J40: Dark Humor | K40: politics | L40: General knowledge
A41: 19bj5k2 | B41: Naomi | C41: Done | D41: Explaining 15 is 3 more than 12. It’s implying that the generations are getting dumber and dumber. | E41: A meme captioned "We're not gonna make it, are we?" with a photo of a Coca-Cola 15-pack box prominently labeled "3 MORE CANS THAN 12 PACK" with a green arrow pointing to the claim. | F41: Marketing math broken down into pre-kindergarten subtraction. | G41: Packaging copy written for an audience the manufacturer has clearly given up on. | H41: A meme captioned "We're not gonna make it, are we?" with a photo of a Coca-Cola 15-pack box prominently labeled "3 MORE CANS THAN 12 PACK" with a green arrow pointing to the claim. | I41: Sarcasm/Irony | J41: Exaggeration | K41: General knowledge | L41: Pop culture | M41: =IF(COUNTIF($A$2:A41, A41)>1, "Dublet", "OK") -> OK
A42: 19dbf08 | B42: Naomi | C42: Done | D42: It’s a zen expression. Before enlightenment, chop wood, carry water. After enlightenment, chop wood, carry water. Here’s a good explanation from the internet: Before Enlightenment, you hate your life. You chop wood and carry water, but secretly wish to get out of it all. You bear with these activities through habit and out of hopelessness, but you really wish you could do something else. In a way, you are a victim, a slave - the wood chops you and the water carries you, and there is no way to escape. This could go for eternity, it is like living in eternal hell. After Enlightenment, you are in harmony with the universe. You realized the emptiness of it all, so you see that there is nothing more important than chopping wood and carrying water. All activities are equalized, there is no preference, no discrimination. Because there is no "you", no ego, no personality, no being, no separate individuality - there is no conflict. No need to escape. No other bank to be reached, no Nirvana to seek. But also, because you have mastered your mind, you are not chopped by the wood and carried by the water anymore. You can flip your perspective at will. It is your choice to chop wood and carry water, and you live it in complete suchness and spontaneity. You are beyond the beyond. And even beyond "beyond the beyond". | E42: Chop wood, carry water — the only thing that changed was the beard. | F42: A two-panel meme labeled "Before Enlightenment" and "After Enlightenment." Both panels contain the same thought bubble showing an illustration of a man chopping wood and a photo of a man carrying water buckets on a shoulder pole. The top panel shows a crying, distressed wojak in the shower; the bottom panel shows a calm, bearded wojak in the shower. | G42: No matter what you do life is still is the same. | H42: A two-panel meme labeled "Before Enlightenment" and "After Enlightenment." Both panels contain the same thought bubble showing an illustration of a man chopping wood and a photo of a man carrying water buckets on a shoulder pole. The top panel shows a crying, distressed wojak in the shower; the bottom panel shows a calm, bearded wojak in the shower. | I42: Situational | J42: Comparison | K42: History/Mythology | L42: General knowledge | M42: =IF(COUNTIF($A$2:A42, A42)>1, "Dublet", "OK") -> OK
A43: 19egkxy | B43: Naomi | C43: Done | D43: There’s a first half to this comic, where the man goes to space and thinks that people would be nicer to each other if they could only see earth from that view. It’s a play on the idea that astronauts who see earth from space are given a better sense of perspective about how small the planet is and how our divides are artificially made. The man, however, immediately counteracts his own point by taking an elitist stance, thinking he’s morally enlightened and better than other people who haven’t seen earth from space. He had the revelation, but didn’t actually internalize its message. The comic then continues to show that people can be kind and loving to one another without ever seeing earth from space, showing that being kind is a choice you make. There’s nothing you have to do or see to make you be nicer to others, you just have to do it. People can see earth from space and not internalize kindness, people can never see earth from space and still be kind. | E43: The most insufferable bar question, answered with the gentlest possible white lie. | F43: Astronaut quietly choosing caregiving over flexing her resume at a party. | G43: A four-panel comic by Extra Fabulous Comics. In the first panel, a man at a bar asks a woman, "Have you ever seen Earth from space?" She replies "No," and he taunts "Ha! Loser!" The next panels show the woman driving home, arriving at a modest house, paying a babysitter, and finally sitting beside an elderly bedridden relative whom she tends to with a bowl of food, beside a framed photo on the wall depicting her as an astronaut. | H43: A four-panel comic by Extra Fabulous Comics. In the first panel, a man at a bar asks a woman, "Have you ever seen Earth from space?" She replies "No," and he taunts "Ha! Loser!" The next panels show the woman driving home, arriving at a modest house, paying a babysitter, and finally sitting beside an elderly bedridden relative whom she tends to with a bowl of food, beside a framed photo on the wall depicting her as an astronaut. | I43: Comparison | J43: Sarcasm/Irony | K43: Logical | L43: Social conventions | M43: =IF(COUNTIF($A$2:A43, A43)>1, "Dublet", "OK") -> OK
A44: 19eokbq | B44: Naomi | C44: Done | D44: In police interrogations they will get you food to reward you for cooperating and keep you talking, normally it's just McDonald's or a vending machine item. The fact that there are multiple KFC boxes and name brand drink for one person implies they're very happy with this person's cooperation level. | E44: Since he hasnt seen his friend in a long time they are cathing up and eating food. | F44: A child is being rewarded by their mom for telling on his siblings. | G44: A screenshot of a television playing the crime documentary show showing a blurred suspect in an interrogation room with a large spread of KFC fast food on the table, captioned "bro told on EVERYBODY" | H44: A screenshot of a television playing the crime documentary show showing a blurred suspect in an interrogation room with a large spread of KFC fast food on the table, captioned "bro told on EVERYBODY" | I44: Situational | J44: Dark Humor | K44: General knowledge | L44: politics | M44: =IF(COUNTIF($A$2:A44, A44)>1, "Dublet", "OK") -> OK
A45: 1actpx8 | B45: Sabrina | C45: Done | D45: the meme refers to cloudy and a chance of meatballs (movie): the main character is a scientist and sprayed on shoes when he was a kid, which he could never remove | E45: its exaggeration, as the meme presents an obviously unnecessary warning against using Flex Seal as footwear, thereby highlighting the absurdity of the situation. | F45: using Flex Seal as footwear is portrayed as undesirable, humorously justified by the unlikely scenario of falling meatballs from the sky. | G45: a snapchat picture showing a person holding a can of Flex Seal and their foot covered in a black substance, with the text ‘Flex seal shoe’ with the text underneath: "did the tales of falling meatballs not weigh on thine conscious". | H45: a snapchat picture showing a person holding a can of Flex Seal and their foot covered in a black substance, with the text ‘Flex seal shoe’ with the text underneath: "did the tales of falling meatballs not weigh on thine conscious". | I45: Sarcasm/Irony | J45: Surprise | K45: Hobby | L45: Pop culture | M45: =IF(COUNTIF($A$2:A45, A45)>1, "Dublet", "OK") -> OK
A46: 1aekqdo | B46: Naomi | C46: Done | D46: The Colt 1911 is a handgun that first entered service in… you guessed it! 1911. It saw service in both WW1 and WW2. It’s still a decent handgun even by todays standards, but it’s gained a cult following over the years, especially among boomers. When anyone brings up its shortcomings such as low magazine capacity, its weight, or that modern designs are typically more reliable, they say something along the lines of “muh two world wars!” Because it was on the winning side of both world wars. In the event of a third world war, it’s likely that the 1911 will see combat yet again. | E46: Nic Cage reads the news, Pedro Pascal reads the spec sheet. | F46: A two-panel meme using stills from The Unbearable Weight of Massive Talent. The top panel shows Nicolas Cage looking concerned with the caption "Seeing the world is on the brink of WW3," and the bottom panel shows Pedro Pascal grinning widely with the caption "The 1911." | G46: One man fears the apocalypse, the other already picked his sidearm. | H46: A two-panel meme using stills from The Unbearable Weight of Massive Talent. The top panel shows Nicolas Cage looking concerned with the caption "Seeing the world is on the brink of WW3," and the bottom panel shows Pedro Pascal grinning widely with the caption "The 1911." | I46: Sarcasm/Irony | J46: Comparison | K46: History/Mythology | L46: politics | M46: =IF(COUNTIF($A$2:A46, A46)>1, "Dublet", "OK") -> OK
A47: 1aexlbt | B47: Naomi | C47: Done | D47: It’s a fork bomb: Here’s a breakdown of what the command does: 1. () This defines a function named : (colon). 2. {} This indicates the start and end of the function’s body. 3. : (colon) inside the function: This is a no-op (no operation) placeholder. It doesn’t do anything but is necessary syntax for defining a function in Bash. 4. | This pipes the output of the function (which is nothing) to another instance of the function. 5. & This sends the command preceding it (another instance of the function) to run in the background. 6. ; This terminates the definition of the function. 7. : (colon) after the semicolon: This executes the function once. So, when you run this command, it defines a function that spawns a new instance of itself in an infinite loop, quickly exhausting system resources and causing the system to become unresponsive. The final : after the semicolon executes the function once to start the process. | E47: The cat is innocent; the bash fork bomb hiding in its collar is not. | F47: A house pet whose name is also a textbook denial-of-service attack. | G47: A meme with the caption "This cat's name is :(){ :|:& };: you should type his name on your linux's terminal" above a close-up photo of a black cat with bright yellow-green eyes staring straight at the camera. | H47: A meme with the caption "This cat's name is :(){ :|:& };: you should type his name on your linux's terminal" above a close-up photo of a black cat with bright yellow-green eyes staring straight at the camera. | I47: Wordplay | J47: Situational | K47: Technical | L47: Hobby | M47: =IF(COUNTIF($A$2:A47, A47)>1, "Dublet", "OK") -> OK
A48: 1af8odu | B48: Sabrina | C48: Done | D48: A teller is a person who works at the front desk of a bank. Teller is also a person's name; that person is one half of the magician duo Penn & Teller. On stage, Teller doesn't speak. Penn is the one who explains everything/talks to the crowd. The joke is that you expect the robber to be speaking to a bank teller. But he's actually speaking to the magician Teller who doesn't talk. That's why Penn comes in at the end to explain what's going on. | E48: Penn’s comment makes the scene funny because he already understands why the “teller” never answers. The silence is treated as typical behavior, not as fear or confusion | F48: A tweet-style image shows a fictional dialogue where a bank robber repeatedly asks a teller where the safe is. The teller gives no visible response, and the robber becomes confused. The final line says, “PENN: He always does this,” implying the teller is the magician Teller, who is known for staying silent. | G48: The robber is absurdly expecting a machine to respond like a person, which makes his frustration seem misplaced and cartoon-like. | H48: A tweet-style image shows a fictional dialogue where a bank robber repeatedly asks a teller where the safe is. The teller gives no visible response, and the robber becomes confused. The final line says, “PENN: He always does this,” implying the teller is the magician Teller, who is known for staying silent. | I48: Wordplay | J48: Sarcasm/Irony | K48: Pop culture | L48: Social conventions | M48: =IF(COUNTIF($A$2:A48, A48)>1, "Dublet", "OK") -> OK
A49: 1agsl73 | B49: Sabrina | C49: Done | D49: “One must imagine Sisyphus happy.” - Albert Camus | E49: It works because the phrase sounds like a rhyme, almost like “men are happy being crappy.” The wording makes it feel like a dumb little slogan, which is why it lands. | F49: It shows this contrast between old-school masculine men and the softer side of them writing poems for their lovers. They look tough, but they are still being romantic in a very dramatic way. | G49: The meme shows the text “Roses are red, Poems are sappy” above an image of a muscular figure pushing a large boulder up a rocky hill. | H49: The meme shows the text “Roses are red, Poems are sappy” above an image of a muscular figure pushing a large boulder up a rocky hill. | I49: Wordplay | J49: Surprise | K49: History/Mythology | L49: Logical | M49: =IF(COUNTIF($A$2:A49, A49)>1, "Dublet", "OK") -> OK
A50: 1ajx3sn | B50: Naomi | C50: Done | D50: It's a rickroll. Never gonna give you up, never gonna let you down | E50: A category so specific the answer reveals itself before any letter does. | F50: Toto's "Africa" auto-filling into every empty grid by default. | G50: A screenshot of an r/Funnymemes post captioned "Too easy" with a meme reading "Friend: You can't possibly guess a wheel of fortune puzzle with no letters / Me:" above a Wheel of Fortune board showing only blank tiles with no letters revealed, under the category "80's SONG LYRICS." | H50: A screenshot of an r/Funnymemes post captioned "Too easy" with a meme reading "Friend: You can't possibly guess a wheel of fortune puzzle with no letters / Me:" above a Wheel of Fortune board showing only blank tiles with no letters revealed, under the category "80's SONG LYRICS." | I50: Wordplay | J50: Comparison | K50: Pop culture | L50: Hobby | M50: =IF(COUNTIF($A$2:A50, A50)>1, "Dublet", "OK") -> OK
A51: 1ajzxfm | B51: Sabrina | C51: Done | D51: It’s kind of a weird joke that doesn’t make perfect sense, but here’s the intended meaning: 1. Many people might see something like 50/50 odds leading to 20 successes in a row and think the next one is more likely to be a failed surgery. Like how many people could flip a coin and get heads twice in a row, and be more likely to guess the next coinflip would be tails. Hence the nervous face. 2. A statistician would know that the success rate of each surgery is independent of all the other ones, so they wouldn’t be especially nervous theirs would go wrong. 3. A scientist might see 20 successes in a row for a surgery with a 50% survival rate and think “wow, this doctor must be really good at doing surgeries” | E51: The meme explains that normal people would choose this doctor because he has 50% success rate, where as mathematicians would be more sceptical and scientists would refrain from getting a surgery from this doctor. | F51: The meme is funny because it illustrates how different fields of process thoughts, it is funny because although most people would take the surgery, mathmaticians and scientists wouldn't because they have the knowledge to know that the probability of the surgery failing is very small despite the given numbers. | G51: A meme with text describing a doctor stating that a surgery has a 50% survival rate and that the last 20 patients survived. Below the text are three panels labeled ‘Normal people’, ‘Mathematician’, and ‘Scientist’, each showing a different face reacting to the statement. | H51: A meme with text describing a doctor stating that a surgery has a 50% survival rate and that the last 20 patients survived. Below the text are three panels labeled ‘Normal people’, ‘Mathematician’, and ‘Scientist’, each showing a different face reacting to the statement. | I51: Comparison | J51: Exaggeration | K51: Logical | L51: General knowledge | M51: =IF(COUNTIF($A$2:A51, A51)>1, "Dublet", "OK") -> OK
A52: 1amtoff | B52: Sabrina | C52: Done | D52: Amazon does not hire 12 year olds, and 12 year olds cannot drive. The potential panic this may cause whomever at Amazon, is hilarious. | E52: The humor arises from the unexpected implication that a well-known company such as Amazon employs a 12-year-old, which contradicts established social and legal norms, thereby creating a surprising and absurd scenario. | F52: A screenshot of a social media thread where a user says that Amazon hired their 12-year-old son, followed by a response from an Amazon customer service account asking for clarification, and a subsequent reply stating that the son is one of their drivers | G52: The humor stems from the company’s apparent unawareness of having employed an underage individual, leading to the implicit consequence that they would need to locate and terminate the employment, which highlights the absurdity of the situation. | H52: A screenshot of a social media thread where a user says that Amazon hired their 12-year-old son, followed by a response from an Amazon customer service account asking for clarification, and a subsequent reply stating that the son is one of their drivers | I52: Incongruity | J52: Sarcasm/Irony | K52: General knowledge | L52: politics | M52: =IF(COUNTIF($A$2:A52, A52)>1, "Dublet", "OK") -> OK
... A175: 1fl51f0 | B175: Naomi | C175: Done | D175: "It signals that the car is driven by a gay couple looking for a big, hairy threesome partner" | E175: Its generally a bad idea to have custom made license plates | F175: The lady driving in from of OP, is presumably bad at driving and has caused an accident | G175: Its funny because its hard to read the license plate | H175: The lady driving in from of OP, is presumably bad at driving and has caused an accident | I175: Wordplay | J175: Situational | K175: Social conventions | L175: Logical | M175: =IF(COUNTIF($A$2:A175, A175)>1, "Dublet", "OK") -> OK
A176: 1flb4nk | B176: Sabrina | C176: Done | D176: The show being referenced is the mockumentary Cunk on Earth, where the titular narrator humorously misinterprets history. The Romans left a lot from their history, including pottery fragments (which broke due to the long time period), which Cunk humorously says is caused by their clumsiness. | E176: A social media post shows a woman standing in front of ancient ruins. Below it, another post says that based on the amount of pottery fragments, the Roman Empire may have been the clumsiest empire in history. | F176: Materials have changed a lot since ancient times, so pottery today can last much longer than pottery from the Roman Empire. | G176: Someone probably broke the pottery on purpose just to mess with the Roman Empire. | H176: A social media post shows a woman standing in front of ancient ruins. Below it, another post says that based on the amount of pottery fragments, the Roman Empire may have been the clumsiest empire in history. | I176: Surprise | J176: Exaggeration | K176: History/Mythology | L176: Logical | M176: =IF(COUNTIF($A$2:A206, A176)>1, "Dublet", "OK") -> OK
A177: 1fm0tjo | B177: Sabrina | C177: Done | D177: Someone feels old because they remembered Y2K was a thing. | E177: Obviously no one can live for 3000 years. | F177: Back then people thought not turning off the PC would break it. | G177: A meme showing a sticker reading “REMEMBER Turn your computer off before midnight on 12/31/99” above an image of a man with the caption “I was there. 3,000 years ago…” | H177: A meme showing a sticker reading “REMEMBER Turn your computer off before midnight on 12/31/99” above an image of a man with the caption “I was there. 3,000 years ago…” | I177: Exaggeration | J177: Situational | K177: Logical | L177: Social conventions | M177: =IF(COUNTIF($A$2:A177, A177)>1, "Dublet", "OK") -> OK
A178: 1fo91u1 | B178: Sabrina | C178: Done | D178: The Logo designer normally charges 350$ But the person asking for the logo has a budget of 800$ 800$ is more dollars than the 350$, this is an important fact which can be easily overlooked. So just about as the logo desinger was to send their message they see this. And after doing a bit of math and self refelection they think to themselves. "hmm, I could also charge 800$ as that is more than 350$" Which will allow the logo desinger to buy more peanuts. Peanuts are tasty. Also shrek is there for the 'hold on a moment' thing and obviously for the sex appeal. | E178: It’s funny because the offer is much lower than the original price. | F178: It’s funny because the buyer sent the message to the wrong person. | G178: A screenshot of a chat where a person asks for a logo price, states a budget of $800, and a reply is typed “Logo design price is $350,” followed by an image of Shrek smiling. | H178: A screenshot of a chat where a person asks for a logo price, states a budget of $800, and a reply is typed “Logo design price is $350,” followed by an image of Shrek smiling. | I178: Situational | J178: Sarcasm/Irony | K178: Logical | L178: Social conventions | M178: =IF(COUNTIF($A$2:A178, A178)>1, "Dublet", "OK") -> OK
A179: 1fq1qb9 | B179: Naomi | C179: Done | D179: The pain of regret cuts deeper than the pain of discipline. | E179: A motivational-style illustration titled "PAIN" showing two cartoon kitchen knives side by side. The left knife, labeled "DISCIPLINE," has a mostly clean blade with a small amount of red at the base. The right knife, labeled "REGRET," is fully coated in red across the entire blade. | F179: Inspirational graphic that accidentally moonlights as crime-scene evidence. | G179: A motivational poster taking the metaphor too literally, with cutlery. | H179: A motivational-style illustration titled "PAIN" showing two cartoon kitchen knives side by side. The left knife, labeled "DISCIPLINE," has a mostly clean blade with a small amount of red at the base. The right knife, labeled "REGRET," is fully coated in red across the entire blade. | I179: Wordplay | J179: Comparison | K179: Logical | L179: General knowledge | M179: =IF(COUNTIF($A$2:A179, A179)>1, "Dublet", "OK") -> OK
A180: 1fs6ndo | B180: Sabrina | C180: Done | D180: Tyranids avoid two things , demon and necron. Tbf thé latter are probably a better news than the nids | E180: Something bad is happening, yet the soldier is still smiling. | F180: At first it seems like bad news, but then he realizes it’s actually good. | G180: A three-panel meme showing a soldier in armor with text: “A Tyranid fleet is approaching the system,” followed by two panels both stating “It ignores your planet,” with the soldier’s facial expression changing. | H180: A three-panel meme showing a soldier in armor with text: “A Tyranid fleet is approaching the system,” followed by two panels both stating “It ignores your planet,” with the soldier’s facial expression changing. | I180: Comparison | J180: Dark Humor | K180: Hobby | L180: Logical | M180: =IF(COUNTIF($A$2:A180, A180)>1, "Dublet", "OK") -> OK
A181: 1fs7uqa | B181: Sabrina | C181: Done | D181: News anchor Wolf Blitzer tweeted a photo of himself out having drinks on a Sunday, July 21st. That happened to be the same Sunday that Biden made the historic decision to drop out of the presidential race, about an hour or so later, and so Blitzer seemingly was asked to come in to work again for this breaking news story. Other people are joking that if he hadn't checked his email, he would have been able to continue enjoying his day off instead of having it interrupted and having to go in to work. | E181: One moment he is happily enjoying beers with his friends on his day off, and the next he finds out through his work email that he has been fired. If he had just ignored the email, he could have delayed knowing and kept enjoying the day a little longer. | F181: He was just having drinks on his day off, and then somehow ended up on the news for being reckless. So honestly, maybe he should have checked his work email, because the firing notice would have given him a heads-up that things were already going downhill. | G181: A meme says, “Never check your work email on a day off.” It shows one photo of an older man smiling with a drink and another photo of the same man looking serious on a news broadcast. | H181: A meme says, “Never check your work email on a day off.” It shows one photo of an older man smiling with a drink and another photo of the same man looking serious on a news broadcast. | I181: Surprise | J181: Exaggeration | K181: politics | L181: Social conventions | M181: =IF(COUNTIF($A$2:A181, A181)>1, "Dublet", "OK") -> OK
A182: 1fssuxj | B182: Naomi | C182: Done | D182: There is no I in nothing or again. He made the letter I not exist anymore. | E182: Its a play on percieved reality and meta that you can never be sure if anything is ever real. | F182: Its implying that we no longer exost since when you read you are I. | G182: In this four-panel comic, a character tells a genie, "I wish I didn't exist," to which the genie responds, "Granted." After a "POOF!" the character observes that "Nothng Changed," and the genie tells them to "Look Agan," revealing that the letter "i" has been removed from the dialogue.' | H182: In this four-panel comic, a character tells a genie, "I wish I didn't exist," to which the genie responds, "Granted." After a "POOF!" the character observes that "Nothng Changed," and the genie tells them to "Look Agan," revealing that the letter "i" has been removed from the dialogue. | I182: Wordplay | J182: Sarcasm/Irony | K182: Logical | L182: General knowledge | M182: =IF(COUNTIF($A$2:A182, A182)>1, "Dublet", "OK") -> OK
A183: 1fst6nb | B183: Sabrina | C183: Done | D183: Yeah its a political joke, the neighbours have taken a part of the other person's garden just like Russia has taken parts of Ukraine. Hopefully that helps. | E183: It plays on the stereotype that Russians tend to be reserved rather than overly talkative. | F183: There’s an implicit absurdity in someone openly identifying as Russian to their neighbors in an American setting, where that isn’t particularly common. | G183: Drawing of a man standing by a fence talking to two neighbors inside a yard; a speech bubble says: “No, we’ve never had Russian neighbours. You are the first.” | H183: Drawing of a man standing by a fence talking to two neighbors inside a yard; a speech bubble says: “No, we’ve never had Russian neighbours. You are the first.” | I183: Comparison | J183: Sarcasm/Irony | K183: politics | L183: Logical | M183: =IF(COUNTIF($A$2:A183, A183)>1, "Dublet", "OK") -> OK
A184: 1ftatdh | B184: Naomi | C184: Done | D184: Can’t be 100% sure, but I think that’s meant to be Joseph Smith, founder of Mormonism. In Mormonism, America is the true Promised Land, not Israel. Or something like that, I’m not religious. Edit: Great thanks to everyone who’s provided corrections and specifics! Everyone should upvote them | E184: Joseph Smith showing up in the comments like "way ahead of you." | F184: A screenshot of a tweet from "Enhanced Interrogated Poet" quote-tweeting a post from "frye" (@__frye) reading "they should invent a Holy Land that's not in the middle east." The quoted image is a portrait painting of Joseph Smith, founder of the Latter-day Saint movement, with a blank speech bubble pointing at him. | G184: 19th-century pre-emptive response to a 2024 take. | H184: A screenshot of a tweet from "Enhanced Interrogated Poet" quote-tweeting a post from "frye" (@__frye) reading "they should invent a Holy Land that's not in the middle east." The quoted image is a portrait painting of Joseph Smith, founder of the Latter-day Saint movement, with a blank speech bubble pointing at him. | I184: Exaggeration | J184: Comparison | K184: History/Mythology | L184: General knowledge | M184: =IF(COUNTIF($A$2:A184, A184)>1, "Dublet", "OK") -> OK
A185: 1ftdy3c | B185: Sabrina | C185: Done | D185: "It's missing the punchline. The other muffin screams 'Oh my god, a talking muffin!'" | E185: The muffin is screaming because theyre in a hot oven | F185: Theyre screamin in the oven because theyre coming alive | G185: A photo shows a person holding a wrapped object or package with printed text on it. The visible text says, “Two muffins were sitting in an oven. One says ‘Geez, it’s hot in here.’ The other screams.” Above the photo, there is a caption that says, “what kind of joke is this.” | H185: A photo shows a person holding a wrapped object or package with printed text on it. The visible text says, “Two muffins were sitting in an oven. One says ‘Geez, it’s hot in here.’ The other screams.” Above the photo, there is a caption that says, “what kind of joke is this.” | I185: Surprise | J185: Sarcasm/Irony | K185: Logical | L185: Social conventions | M185: =IF(COUNTIF($A$2:A185, A185)>1, "Dublet", "OK") -> OK
A186: 1fu3pp1 | B186: Sabrina | C186: Done | D186: that is way too good for a school computer. it's clearly for gaming | E186: The humor comes from a child demonstrating unexpectedly advanced knowledge. | F186: The phrasing appears not making sense, which creates the comedic effect. | G186: Four-panel meme: top text shows a mother asking for a PC for school and a son listing high-end specs; bottom panels show Shrek smiling. | H186: Four-panel meme: top text shows a mother asking for a PC for school and a son listing high-end specs; bottom panels show Shrek smiling. | I186: Incongruity | J186: Situational | K186: Technical | L186: Hobby | M186: =IF(COUNTIF($A$2:A186, A186)>1, "Dublet", "OK") -> OK
A187: 1fuxrbx | B187: Sabrina | C187: Done | D187: The numbers when pressed will correlate to different letters. For example, pressing 2 will give you A, but pressing 22 will give you B, 222 giving you C, and so on. This pattern of numbers spells, "It was me Dio!" Which is a reference to the anime Jojo's Bizarre Adventure. The line is said by the main antagonist, named Dio Brando. | E187: The joke lies in how it presents itself as completely ordinary, even though it’s framed as something unusual. | F187: That old Nokia triggers nostalgia, which is what makes it amusing. | G187: Image of an old mobile phone keypad with numbers and letters; below it is the sequence: “4448 927777 633 3444666”. | H187: Image of an old mobile phone keypad with numbers and letters; below it is the sequence: “4448 927777 633 3444666”. | I187: Wordplay | J187: Surprise | K187: Hobby | L187: Pop culture | M187: =IF(COUNTIF($A$2:A187, A187)>1, "Dublet", "OK") -> OK
A188: 1fvg71d | B188: Naomi | C188: Done | D188: "First image is Villa Savoye built in 1931 in Poissy, France. A modern style building using that all the rage material reinforced concrete. Second image is Palais Garnier, an opera house built in 1875 in Paris France at the behest of Emperor Napoleon III the style is literally called Napoleon III. OOP likes the older style better and feels that newer buildings are appreciated for their advanced construction but are unable to capture the beauty of early styles." | E188: The image shows that ancient people literally invented modern buildings first, and todayï¿½s architects are stealing their exact designs and claiming them as new. | F188: The humor comes from a generational disagreement where older people simply dislike modern styles out of nostalgia, regardless of whether new designs are actually better. | G188: The Joke is that the old house was actually build first | H188: The image shows that ancient people literally invented modern buildings first, and todayï¿½s architects are stealing their exact designs and claiming them as new. | I188: Comparison | J188: Sarcasm/Irony | K188: History/Mythology | L188: General knowledge | M188: =IF(COUNTIF($A$2:A188, A188)>1, "Dublet", "OK") -> OK
... A267: 1ic88xs | B267: Naomi | C267: Done | D267: She doesn’t use deodorant cause if she did she would’ve saw the money and would have grabbed it | E267: A Facebook post from Craig Clark reading "Buddy sent me this picture. Put 80 bucks on his girls deodorant and she ain't touched it for 8 days. Genius." with a photo of a blue stick of deodorant sitting on a granite bathroom counter, wrapped with a rubber band securing four $20 bills around it. | F267: Cash bait sits undisturbed exactly where it was always least likely to be found. | G267: An accidental experimental study on the half-life of teenage hygiene. | H267: A Facebook post from Craig Clark reading "Buddy sent me this picture. Put 80 bucks on his girls deodorant and she ain't touched it for 8 days. Genius." with a photo of a blue stick of deodorant sitting on a granite bathroom counter, wrapped with a rubber band securing four $20 bills around it. | I267: Surprise | J267: Situational | K267: Logical | L267: General knowledge | M267: =IF(COUNTIF($A$2:A267, A267)>1, "Dublet", "OK") -> OK
A268: 1ieb7j3 | B268: Naomi | C268: Done | D268: "That is the title character from the film Amelie, and she's also the mascot of FitGirl Repacks, a site to get pirated PC games." | E268: The image shows a woman holding a spoon to demonstrate that PC gamers eat cheaply. | F268: The meme suggests PC users enjoy games less seriously, so prices matter less to them. | G268: The humor comes from implication and insider knowledge: the sly expression suggests PC users often pirate games or use deep discounts, so they donï¿½t complain about prices because they rarely pay full price. | H268: The image shows a woman holding a spoon to demonstrate that PC gamers eat cheaply. | I268: Surprise | J268: Dark Humor | K268: meme | L268: Hobby | M268: =IF(COUNTIF($A$2:A268, A268)>1, "Dublet", "OK") -> OK | N268: Det er herfra Fridas billeder slutter
A269: 1if88s3 | B269: Sabrina | C269: Done | D269: Binary code? 1 1= 3 IIrc | E269: The two fingers are meant as a signal to the bartender that he wants another round of drinks. It is the kind of gesture that makes sense in a bar setting, even without saying much out loud. | F269: A cartoon shows three men walking into a bar. One of them holds up two fingers while saying “Three beers” to the bartender, who is holding a glass. | G269: He says three beers while only holding up two fingers, which makes the whole moment confusing. The mismatch between what he says and what he signals is what throws everything off. | H269: A cartoon shows three men walking into a bar. One of them holds up two fingers while saying “Three beers” to the bartender, who is holding a glass. | I269: Wordplay | J269: Situational | K269: Technical | L269: Social conventions | M269: =IF(COUNTIF($A$2:A269, A269)>1, "Dublet", "OK") -> OK
A270: 1ig7lnf | B270: Sabrina | C270: Done | D270: Your brain on drugs | E270: The humor comes from the confusion of the person, who misidentifies the object even though it is clearly an egg. | F270: The humor arises from the fact that commercials often use fake or altered food, which the meme highlights. | G270: Text at the top: “If you watched TV in the 80s you know this isn’t an egg”; below is a frying pan with a fried egg being cooked on a stove. | H270: Text at the top: “If you watched TV in the 80s you know this isn’t an egg”; below is a frying pan with a fried egg being cooked on a stove. | I270: Incongruity | J270: Sarcasm/Irony | K270: meme | L270: Pop culture | M270: =IF(COUNTIF($A$2:A270, A270)>1, "Dublet", "OK") -> OK
A271: 1ih9bat | B271: Sabrina | C271: Done | D271: His daughter is a pilot, he wished she were a doctor so now she is, but no longer knows how to fly the plane. | E271: The joke builds on the stereotype that brown parents are only truly proud of your degree if you become a doctor. | F271: It is funny because she is technically already a doctor, but it is as if the genie suddenly made her remember it, like waking her from a dream. | G271: A four-panel comic shows a man speaking to a genie who grants him one wish. The man says he wants his daughter to become a doctor. The genie begins to object because she already appears to be a doctor or pilot, and the final panel shows an airplane saying “umm,” implying that the wish may have changed her profession incorrectly. | H271: A four-panel comic shows a man speaking to a genie who grants him one wish. The man says he wants his daughter to become a doctor. The genie begins to object because she already appears to be a doctor or pilot, and the final panel shows an airplane saying “umm,” implying that the wish may have changed her profession incorrectly. | I271: Sarcasm/Irony | J271: Situational | K271: Logical | L271: Social conventions | M271: =IF(COUNTIF($A$2:A271, A271)>1, "Dublet", "OK") -> OK
A272: 1ii3g3t | B272: Naomi | C272: Done | D272: It's the way how it was found. Basically, during WWII (correct me if I'm wrong) Japanese were making atrocious experiments on people. One of those experiments was to put a live human in an oven, that removes all liquid from a thing that was put into it. So, they weighed a person before the experiment and weighed the remains after. The mass loss was about 70%. Thats how we know human body is 70% water | E272: The photo is in black in white for why we discovered it because only balck and white photos existed when it was discovered. | F272: It is a reference to a scene in the incredibles movie when Mr.Incredible and iceman fight. | G272: A two-panel meme with the text "The human body is 70% water" above two images of Mr. Incredible: a normal cartoon version labeled "Those who know" and a dark, distressed version labeled "Those who know why we know." | H272: A two-panel meme with the text "The human body is 70% water" above two images of Mr. Incredible: a normal cartoon version labeled "Those who know" and a dark, distressed version labeled "Those who know why we know." | I272: Dark Humor | J272: Situational | K272: History/Mythology | L272: General knowledge | M272: =IF(COUNTIF($A$2:A272, A272)>1, "Dublet", "OK") -> OK
A273: 1iizrp4 | B273: Sabrina | C273: Done | D273: "Washington's farewell address said that political parties would destroy the nation." | E273: Jefferson and Adams were known to throw crazy parties. The pun here is Washington acting like their dad | F273: The comic depicts Washington saying goodbye to Jefferson and Adams | G273: A comic shows George Washington telling Jefferson and Adams that he is leaving and saying “No parties.” In the final panel, Jefferson and Adams are shown smiling at each other, implying that they ignore his instruction. Below the comic, a comment says it is one of the best puns the commenter has seen. | H273: A comic shows George Washington telling Jefferson and Adams that he is leaving and saying “No parties.” In the final panel, Jefferson and Adams are shown smiling at each other, implying that they ignore his instruction. Below the comic, a comment says it is one of the best puns the commenter has seen. | I273: Wordplay | J273: Sarcasm/Irony | K273: politics | L273: History/Mythology | M273: =IF(COUNTIF($A$2:A273, A273)>1, "Dublet", "OK") -> OK
A274: 1ijlh5e | B274: Sabrina | C274: Done | D274: What crazy is Christians burned her books when she was writing them as a Christian. | E274: The joke refers to the historical idea that Christians used to burn witches, which has also been heavily popularized in modern culture. | F274: It is ironic that feminists would want a picture with Trump. | G274: A screenshot of a tweet discusses women’s and girls’ rights and includes a photo of a political figure seated at a desk surrounded by women and girls. A reply underneath comments that the person has become an inspiration to people who burned their books years earlier. | H274: A screenshot of a tweet discusses women’s and girls’ rights and includes a photo of a political figure seated at a desk surrounded by women and girls. A reply underneath comments that the person has become an inspiration to people who burned their books years earlier. | I274: Situational | J274: Sarcasm/Irony | K274: politics | L274: Pop culture | M274: =IF(COUNTIF($A$2:A274, A274)>1, "Dublet", "OK") -> OK
A275: 1ijv4xn | B275: Naomi | C275: Done | D275: Beaver sees water Beaver hates the sound of running water Beaver says oh, absolutely not" with the rage of a thousand suns burning in his soul Beaver goes to build dam to stop the running water" | E275: A two-panel comic by @AbelBryanMedia titled "A Beaver's Instinct." The first panel shows a beaver looking at a flowing stream with a question mark above its head. The second panel zooms in on the beaver's face as it firmly declares, "Oh, absolutely not." | F275: Nature's busiest engineer rejecting a project before it has begun. | G275: A beaver consulting its blueprint and deciding the river fails inspection. | H275: A two-panel comic by @AbelBryanMedia titled "A Beaver's Instinct." The first panel shows a beaver looking at a flowing stream with a question mark above its head. The second panel zooms in on the beaver's face as it firmly declares, "Oh, absolutely not." | I275: Wordplay | J275: Situational | K275: General knowledge | L275: meme | M275: =IF(COUNTIF($A$2:A275, A275)>1, "Dublet", "OK") -> OK
A276: 1ikp7ob | B276: Sabrina | C276: Done | D276: He’s lying. The joke is that they’re actually brothers and he is lying to make a joke. | E276: A screenshot shows two young men being interviewed. The interviewer asks whether they are twins in real life. One of the men answers that it is a weird story, and the final caption says they met at the audition. | F276: Even though they aren't siblings they are related because they're cousins lmao | G276: It shows how good the casting director was, since they look like twins | H276: A screenshot shows two young men being interviewed. The interviewer asks whether they are twins in real life. One of the men answers that it is a weird story, and the final caption says they met at the audition. | I276: Sarcasm/Irony | J276: Incongruity | K276: Social conventions | L276: Pop culture | M276: =IF(COUNTIF($A$2:A276, A276)>1, "Dublet", "OK") -> OK
A277: 1il72ww | B277: Naomi | C277: Done | D277: This is the finance bro uniform. Slacks/jeans, button down blue shirt, Patagonia vest, expensive shoes The Excel spread sheet part is in reference to a large part of their jobs involve using excel to perform various financial analysis. They usually consider themselves to be excel wizards and many compete" in speed tests using shortcuts only and no mouse to format and build visuals in excel." | E277: It is funny because the stripes on their shirts make them look like excel spreadhseets. | F277: It is because the are in a line like a column like a spreadhseet column. | G277: An image captioned "It's a bad day to be an excel spreadsheet" showing three men walking down a city sidewalk, all viewed from behind, wearing matching outfits of dark quilted vests, blue button-up shirts, and jeans. | H277: An image captioned "It's a bad day to be an excel spreadsheet" showing three men walking down a city sidewalk, all viewed from behind, wearing matching outfits of dark quilted vests, blue button-up shirts, and jeans. | I277: Sarcasm/Irony | J277: Situational | K277: Social conventions | L277: General knowledge | M277: =IF(COUNTIF($A$2:A277, A277)>1, "Dublet", "OK") -> OK
A278: 1inxmb2 | B278: Sabrina | C278: Done | D278: picture of a guy, top text, bottom text. therefore, meme | E278: The humor comes from the fact that the dollar is frequently used in memes, leading the younger brother to confuse the real object with its online representation. | F278: Screenshot of a tweet: “little brother told me ‘money is the oldest meme’ and proceeded to describe this image”; below is a one-dollar bill labeled “FEDERAL RESERVE NOTE ONE DOLLAR”. | G278: The humor lies in the misinterpretation of a physical dollar bill as a meme, highlighting the child’s lack of real-world understanding. | H278: Screenshot of a tweet: “little brother told me ‘money is the oldest meme’ and proceeded to describe this image”; below is a one-dollar bill labeled “FEDERAL RESERVE NOTE ONE DOLLAR”. | I278: Comparison | J278: Sarcasm/Irony | K278: meme | L278: Logical | M278: =IF(COUNTIF($A$2:A278, A278)>1, "Dublet", "OK") -> OK
A279: 1ip0ht2 | B279: Naomi | C279: Done | D279: Looks like the Third Impact from Evangelion to me. One of the portrayals of the Third Impact is a lot of light crosses sticking out of the ground. Also, consider that the tweet is by a Japanese user. | E279: A screenshot of a tweet from @ZeroSuitCamus reading "OH SHIT OH FUCK ITS HAPPENING" quote-tweeting a Japanese post by うけ (@VhxM9IVTAy3cQRp) reading "すっごい光の護封剣" with a photo of vivid, colorful light pillars rising vertically into the night sky over a snowy town. | F279: Atmospheric light pillars mistaken for a Yu-Gi-Oh trap card finally activating in real life. | G279: Swords of Revealing Light deployed worldwide — duelist confirms via Twitter. | H279: A screenshot of a tweet from @ZeroSuitCamus reading "OH SHIT OH FUCK ITS HAPPENING" quote-tweeting a Japanese post by うけ (@VhxM9IVTAy3cQRp) reading "すっごい光の護封剣" with a photo of vivid, colorful light pillars rising vertically into the night sky over a snowy town. | I279: Exaggeration | J279: Comparison | K279: Hobby | L279: meme | M279: =IF(COUNTIF($A$2:A279, A279)>1, "Dublet", "OK") -> OK
A280: 1ipozgr | B280: Naomi | C280: Done | D280: For who made the meme,the air fryer is considered more important than anything else the thiefs are stealing. | E280: An air fryer is extremely expensive making i think most valubale item and therfore worst thing to get stolen. | F280: The image is a high-contrast, black-and-white close-up photograph of a man with a mustache. He is looking directly at the camera with a serious, intense expression. The lighting highlights his facial features while casting deep shadows across his face. Above the photograph, there is text that reads: When im getting robbed and they start going for my air fryer. | G280: People ususlaly hide embarrasing secrets in their air fryer making them vulnerable. | H280: The image is a high-contrast, black-and-white close-up photograph of a man with a mustache. He is looking directly at the camera with a serious, intense expression. The lighting highlights his facial features while casting deep shadows across his face. Above the photograph, there is text that reads: When im getting robbed and they start going for my air fryer. | I280: Situational | J280: Exaggeration | K280: General knowledge | L280: Social conventions | M280: =IF(COUNTIF($A$2:A280, A280)>1, "Dublet", "OK") -> OK
... A502: 1naurrn | B502: Sabrina | C502: Done | D502: She has a point. And probably synaesthesia | E502: She seems to be choosing purely based on the vibes that the colors and days give her, as if each combination has its own mood or energy. The humor comes from how confidently she treats those feelings as a real system | F502: A young woman with curly hair looks at the camera. Text explains she associates numbers, colors, days, and seasons as the same | G502: She believes in numerology and probably has a collection of crystals or stones she touches before deciding what kind of day she is going to have | H502: A young woman with curly hair looks at the camera. Text explains she associates numbers, colors, days, and seasons as the same. | I502: Comparison | J502: Incongruity | K502: Technical | L502: General knowledge | M502: =IF(COUNTIF($A$2:A502, A502)>1, "Dublet", "OK") -> OK

Sheet PAnnotations
A1: File | B1: Assigned_to | C1: Status | D1: Correct answer | E1: Literal_Description | F1: Humor Style | G1: Humor style secondary | H1: Contextual Knowledge | I1: Contextual Knowledge secondary | J1: Partner name | K1: Status | L1: Partner: Humor Style | M1: Partner: Humor style secondary | N1: Partner: Contextual Knowledge | O1: Partner: Contextual Knowledge secondary | P1: Humor primary match | Q1: Humor full label-set overlap | R1: Context primary match | S1: Context full label-set overlap | T1: Humor partial overlap | U1: Context partial overlap
A2: 1actpx8 | B2: Sabrina | C2: Done | D2: the meme refers to cloudy and a chance of meatballs (movie): the main character is a scientist and sprayed on shoes when he was a kid, which he could never remove | E2: a snapchat picture showing a person holding a can of Flex Seal and their foot covered in a black substance, with the text ‘Flex seal shoe’ with the text underneath: "did the tales of falling meatballs not weigh on thine conscious". | F2: Sarcasm/Irony | G2: Surprise | H2: Hobby | I2: Pop culture | J2: Naomi | K2: Done | L2: Sarcasm/Irony | M2: Situational | N2: Hobby | O2: Pop culture | P2: =IF(F2=L2,1,0) -> 1 | Q2: =IF(OR(AND(F2=L2,G2=M2),AND(F2=M2,G2=L2)),1,0) -> 0 | R2: =IF(H2=N2,1,0) -> 1 | S2: =IF(OR(AND(H2=N2,I2=O2),AND(H2=O2,I2=N2)),1,0) -> 1 | T2: =IF(OR(F2=L2,F2=M2,G2=L2,G2=M2),1,0) -> 1 | U2: =IF(OR(H2=N2,H2=O2,I2=N2,I2=O2),1,0) -> 1
A3: 1amtoff | B3: Sabrina | C3: Done | D3: Amazon does not hire 12 year olds, and 12 year olds cannot drive. The potential panic this may cause whomever at Amazon, is hilarious. | E3: A screenshot of a social media thread where a user says that Amazon hired their 12-year-old son, followed by a response from an Amazon customer service account asking for clarification, and a subsequent reply stating that the son is one of their drivers | F3: Incongruity | G3: Sarcasm/Irony | H3: General knowledge | I3: politics | J3: Naomi | K3: Done | L3: Incongruity | M3: Sarcasm/Irony | N3: General knowledge | O3: politics | P3: =IF(F3=L3,1,0) -> 1 | Q3: =IF(OR(AND(F3=L3,G3=M3),AND(F3=M3,G3=L3)),1,0) -> 1 | R3: =IF(H3=N3,1,0) -> 1 | S3: =IF(OR(AND(H3=N3,I3=O3),AND(H3=O3,I3=N3)),1,0) -> 1 | T3: =IF(OR(F3=L3,F3=M3,G3=L3,G3=M3),1,0) -> 1 | U3: =IF(OR(H3=N3,H3=O3,I3=N3,I3=O3),1,0) -> 1
A4: 1b7unh0 | B4: Sabrina | C4: Done | D4: He would probably also be confused why they had built a second Memphis | E4: A meme divided into two sections labeled “Women with a time machine” and “Men with a time machine.” The top shows a woman pointing a gun at Henry Ford. The bottom shows a man speaking to an ancient Egyptian figure in front of a pyramid, with text about a modern glass pyramid in Memphis containing a Bass Pro Shop. | F4: Comparison | G4: Exaggeration | H4: History/Mythology | I4: Logical | J4: Naomi | K4: Done | L4: Comparison | M4: Exaggeration | N4: History/Mythology | O4: Logical | P4: =IF(F4=L4,1,0) -> 1 | Q4: =IF(OR(AND(F4=L4,G4=M4),AND(F4=M4,G4=L4)),1,0) -> 1 | R4: =IF(H4=N4,1,0) -> 1 | S4: =IF(OR(AND(H4=N4,I4=O4),AND(H4=O4,I4=N4)),1,0) -> 1 | T4: =IF(OR(F4=L4,F4=M4,G4=L4,G4=M4),1,0) -> 1 | U4: =IF(OR(H4=N4,H4=O4,I4=N4,I4=O4),1,0) -> 1
A5: 1bikyy1 | B5: Sabrina | C5: Done | D5: The math is a little off, but the gist of it is that the grand canyon took a long *long* time to get to its current state, but, at some point in the very distant past, it would've started out as a small stream, as depicted in the meme. So, the joke is that the Flintstones were around a long time ago when the Grand Canyon was still just a little stream. | E5: A meme with the text “So that's the Grand Canyon, huh?” followed by “– The Flintstones,” showing a cartoon scene of characters standing near a narrow canyon with a small stream running through it. | F5: Incongruity | G5: Surprise | H5: History/Mythology | I5: General knowledge | J5: Naomi | K5: Done | L5: Incongruity | M5: Surprise | N5: Hobby | O5: Technical | P5: =IF(F5=L5,1,0) -> 1 | Q5: =IF(OR(AND(F5=L5,G5=M5),AND(F5=M5,G5=L5)),1,0) -> 1 | R5: =IF(H5=N5,1,0) -> 0 | S5: =IF(OR(AND(H5=N5,I5=O5),AND(H5=O5,I5=N5)),1,0) -> 0 | T5: =IF(OR(F5=L5,F5=M5,G5=L5,G5=M5),1,0) -> 1 | U5: =IF(OR(H5=N5,H5=O5,I5=N5,I5=O5),1,0) -> 0
A6: 1bmtc5u | B6: Sabrina | C6: Done | D6: He likes big butts and he cannot lie. | E6: A black-and-white cartoon of a courtroom scene where a judge asks a witness to swear to tell the truth. The witness, a woman standing at the stand, responds that it will not be necessary. Several people are seated in the courtroom observing the exchange. | F6: Incongruity | G6: Exaggeration | H6: Social conventions | I6: Pop culture | J6: Naomi | K6: Done | L6: Situational | M6: Incongruity | N6: Social conventions | O6: Pop culture | P6: =IF(F6=L6,1,0) -> 0 | Q6: =IF(OR(AND(F6=L6,G6=M6),AND(F6=M6,G6=L6)),1,0) -> 0 | R6: =IF(H6=N6,1,0) -> 1 | S6: =IF(OR(AND(H6=N6,I6=O6),AND(H6=O6,I6=N6)),1,0) -> 1 | T6: =IF(OR(F6=L6,F6=M6,G6=L6,G6=M6),1,0) -> 1 | U6: =IF(OR(H6=N6,H6=O6,I6=N6,I6=O6),1,0) -> 1
A7: 1c6zoan | B7: Sabrina | C7: Done | D7: That's a (slightly edited) picture of Todd Howard, the director, executive producer, and public spokesperson for Bethesda Games. He lead development on all the Elder Scrolls games (Skyrim), Starfield, and Fallout 3, 4, and 76. Recently the Fallout TV series was released and it featured an event that happened in one of the endings of "Fallout New Vegas," a game published but *not developed* by Bethesda. But the event in question happens in different years in each of New Vegas and the TV show. Because of this Todd was asked recently whether New Vegas or the TV show is canon to the series at large, and if New Vegas is, which ending. His response was "all of Fallout is canon." Which doesn't really answer any questions or make sense. | E7: A screenshot of a social media post showing a dialogue about inconsistencies in a fictional storyline, mentioning “Todd” and “New Vegas,” followed by a repeated response stating “All of it.” Below the text is an image of Todd. | F7: Incongruity | G7: Sarcasm/Irony | H7: Pop culture | I7: Hobby | J7: Naomi | K7: Done | L7: Incongruity | M7: Sarcasm/Irony | N7: Pop culture | O7: Hobby | P7: =IF(F7=L7,1,0) -> 1 | Q7: =IF(OR(AND(F7=L7,G7=M7),AND(F7=M7,G7=L7)),1,0) -> 1 | R7: =IF(H7=N7,1,0) -> 1 | S7: =IF(OR(AND(H7=N7,I7=O7),AND(H7=O7,I7=N7)),1,0) -> 1 | T7: =IF(OR(F7=L7,F7=M7,G7=L7,G7=M7),1,0) -> 1 | U7: =IF(OR(H7=N7,H7=O7,I7=N7,I7=O7),1,0) -> 1
A8: 1cehmmt | B8: Naomi | C8: Done | D8: He looks very much like Hugh Laurie. | E8: It is a screeshot of an internet article with the title of "Russian Plumber Doesn't Know Why People Stare At Him On The Street" the phot below the caption shows a middle aged caucasian male with a tired expression. | F8: Situational | G8: Comparison | H8: Pop culture | I8: Hobby | J8: Sabrina | K8: Done | L8: Comparison | M8: Surprise | N8: Pop culture | O8: Hobby | P8: =IF(F8=L8,1,0) -> 0 | Q8: =IF(OR(AND(F8=L8,G8=M8),AND(F8=M8,G8=L8)),1,0) -> 0 | R8: =IF(H8=N8,1,0) -> 1 | S8: =IF(OR(AND(H8=N8,I8=O8),AND(H8=O8,I8=N8)),1,0) -> 1 | T8: =IF(OR(F8=L8,F8=M8,G8=L8,G8=M8),1,0) -> 1 | U8: =IF(OR(H8=N8,H8=O8,I8=N8,I8=O8),1,0) -> 1
A9: 1cgcw31 | B9: Naomi | C9: Done | D9: Its a reference to a trend on TikTok where people will ask women if they would feel safer being alone in the woods with a bear or a random man and they almost always choose the bear. Basically the idea is that the bear will be pretty much harmless if you leave it alone vs a man could have nefarious intent with no provocation. | E9: It shows a man speaking with the caption "if you don't understand why women are choosing the bear... you are probably part of the reason they are choosing the bear"and the llama reacting with a gaping sigh. | F9: Exaggeration | G9: Sarcasm/Irony | H9: Pop culture | I9: meme | J9: Sabrina | K9: Done | L9: Exaggeration | M9: Sarcasm/Irony | N9: Pop culture | O9: meme | P9: =IF(F9=L9,1,0) -> 1 | Q9: =IF(OR(AND(F9=L9,G9=M9),AND(F9=M9,G9=L9)),1,0) -> 1 | R9: =IF(H9=N9,1,0) -> 1 | S9: =IF(OR(AND(H9=N9,I9=O9),AND(H9=O9,I9=N9)),1,0) -> 1 | T9: =IF(OR(F9=L9,F9=M9,G9=L9,G9=M9),1,0) -> 1 | U9: =IF(OR(H9=N9,H9=O9,I9=N9,I9=O9),1,0) -> 1
A10: 1eae89f | B10: Naomi | C10: Done | D10: In one possible ending of Bloodborne, the protagonist becomes an eldritch squid creature. | E10: It shows a line of somber men walking in a single file line into a an upside cover of the game Bloodborne and leaving the other side of the cover is a line of squids. | F10: Exaggeration | G10: Comparison | H10: Hobby | I10: Logical | J10: Sabrina | K10: Done | L10: Exaggeration | M10: Comparison | N10: Hobby | O10: Logical | P10: =IF(F10=L10,1,0) -> 1 | Q10: =IF(OR(AND(F10=L10,G10=M10),AND(F10=M10,G10=L10)),1,0) -> 1 | R10: =IF(H10=N10,1,0) -> 1 | S10: =IF(OR(AND(H10=N10,I10=O10),AND(H10=O10,I10=N10)),1,0) -> 1 | T10: =IF(OR(F10=L10,F10=M10,G10=L10,G10=M10),1,0) -> 1 | U10: =IF(OR(H10=N10,H10=O10,I10=N10,I10=O10),1,0) -> 1
A11: 1iw42ka | B11: Naomi | C11: Done | D11: Grimes met Elon Musk at Met gala 2018 , leading to their relationship . Many people believe things would have been better if Grimes and Musk had never met . | E11: It is a screeenshot of a tweet showing a meme with the top portion titled "Boys with the time Machine" and one male face saying "im your grandson" and he other one replies "wow" the lower portion of the meme is titled "Girls with the time machine" and a group of females speaking to a photo of Grimes with the caption "do not go to the 2018 Met Gala" | F11: Exaggeration | G11: Comparison | H11: Pop culture | I11: politics | J11: Sabrina | K11: Done | L11: Exaggeration | M11: Comparison | N11: Pop culture | O11: Social conventions | P11: =IF(F11=L11,1,0) -> 1 | Q11: =IF(OR(AND(F11=L11,G11=M11),AND(F11=M11,G11=L11)),1,0) -> 1 | R11: =IF(H11=N11,1,0) -> 1 | S11: =IF(OR(AND(H11=N11,I11=O11),AND(H11=O11,I11=N11)),1,0) -> 0 | T11: =IF(OR(F11=L11,F11=M11,G11=L11,G11=M11),1,0) -> 1 | U11: =IF(OR(H11=N11,H11=O11,I11=N11,I11=O11),1,0) -> 1
A12: 1k4fjdr | B12: Naomi | C12: Done | D12: Wish #1 is to wish the genie does the opposite of what he asks in wish #2 Wish #2 is to not grant wish #3 (which since Wish #1 was do the opposite, it means the genie must grant wish #2 as 'do grant wish #3). Wish #3 is cancel wish #1, which is to do the opposite of wish #2, which as established is to make the genie grant wish #3, which causes wish #2 to not be opposite, which means that genie can't grant wish #3, which means wish #1 can't be cancelled, which means, genie needs to do the opposite of "don't do wish #3", which means, the genie must cancel wish #1, which means wish #2 becomes "don't grant wish #3", thus stopping "cancel wish #1" from happening, which means wish #2 won't grant wish #3, which means wish #1 gets cancelled, which means, wish #2 must cancel wish #3, which means wish #1 doesn't get cancelled... | E12: A four-panel comic followed by an image of a mushroom cloud, depicting a man using his three wishes from a genie to create a logical paradox by asking for the opposite of the second wish, the denial of the third wish, and the cancellation of the first. | F12: Wordplay | G12: Situational | H12: Logical | I12: Hobby | J12: Sabrina | K12: Done | L12: Wordplay | M12: Situational | N12: Logical | O12: Hobby | P12: =IF(F12=L12,1,0) -> 1 | Q12: =IF(OR(AND(F12=L12,G12=M12),AND(F12=M12,G12=L12)),1,0) -> 1 | R12: =IF(H12=N12,1,0) -> 1 | S12: =IF(OR(AND(H12=N12,I12=O12),AND(H12=O12,I12=N12)),1,0) -> 1 | T12: =IF(OR(F12=L12,F12=M12,G12=L12,G12=M12),1,0) -> 1 | U12: =IF(OR(H12=N12,H12=O12,I12=N12,I12=O12),1,0) -> 1
A13: 1k70gfk | B13: Naomi | C13: Done | D13: White supremacists, in the US at least, have yet to decide if they fully believe Italians are white or not | E13: A meme featuring text about Italians watching a "race war" with the intent of joining whoever wins, paired with an image of Thanos sitting on his throne. | F13: Sarcasm/Irony | G13: Dark Humor | H13: politics | I13: General knowledge | J13: Sabrina | K13: Done | L13: Exaggeration | M13: Dark Humor | N13: politics | O13: General knowledge | P13: =IF(F13=L13,1,0) -> 0 | Q13: =IF(OR(AND(F13=L13,G13=M13),AND(F13=M13,G13=L13)),1,0) -> 0 | R13: =IF(H13=N13,1,0) -> 1 | S13: =IF(OR(AND(H13=N13,I13=O13),AND(H13=O13,I13=N13)),1,0) -> 1 | T13: =IF(OR(F13=L13,F13=M13,G13=L13,G13=M13),1,0) -> 1 | U13: =IF(OR(H13=N13,H13=O13,I13=N13,I13=O13),1,0) -> 1
... A51: 1czson4 | B51: Sabrina | C51: Done | D51: It's a joke about different numbering systems. Think of binary, which is a base 2 system, wherein you only have the numbers 0 and 1. Comparing to our system (which we call base 10 btw), 0 in binary equals 0, 1 in binary equals 1, 10 in binary equals 2, 11 in binary equals 3, etc. But for an alien, 10 is 10. The point being that from an objective perspective, any numbering system (base 2, base 4, base 8, etc) would call itself "base 10" because 10 is still the reset number (base 4 might look like this: 1, 2, 3, 10, 11, 12, 13, 20, etc). I suppose the joke is mocking an overly solipsistic perspective and reminding the reader to consider the universe from different points of view. Edit for clarity: base 10 means there are 10 single digit numbers, so what we call base 10 has the numbers 0, 1, 2, 3, 4, 5, 6, 7, 8, 9. Base 4 means there are 4 single digits, 0, 1, 2, 3. But in both cases, the reset number will be 10, so the same, regardless of the fact that 10 represents different amounts in the different systems. | E51: A comic shows an astronaut speaking to a small alien next to a group of rocks. The astronaut says that there are ten rocks and assumes the alien is using base 4. The alien replies that it uses base 10 and asks what base 4 is. The caption states, “Every base is base 10.” | F51: Sarcasm/Irony | G51: Comparison | H51: Technical | I51: Logical | J51: Naomi | K51: Done | L51: Sarcasm/Irony | M51: Comparison | N51: Technical | O51: Logical | P51: =IF(F51=L51,1,0) -> 1 | Q51: =IF(OR(AND(F51=L51,G51=M51),AND(F51=M51,G51=L51)),1,0) -> 1 | R51: =IF(H51=N51,1,0) -> 1 | S51: =IF(OR(AND(H51=N51,I51=O51),AND(H51=O51,I51=N51)),1,0) -> 1 | T51: =IF(OR(F51=L51,F51=M51,G51=L51,G51=M51),1,0) -> 1 | U51: =IF(OR(H51=N51,H51=O51,I51=N51,I51=O51),1,0) -> 1
A52: Gennemsnit | P52: =COUNTIF(P2:P51,1)/COUNTA(P2:P51) -> 0.88 | Q52: =COUNTIF(Q2:Q51,1)/COUNTA(Q2:Q51) -> 0.76 | R52: =COUNTIF(R2:R51,1)/COUNTA(R2:R51) -> 0.88 | S52: =COUNTIF(S2:S51,1)/COUNTA(S2:S51) -> 0.82 | T52: =COUNTIF(T2:T51,1)/COUNTA(T2:T51) -> 1 | U52: =COUNTIF(U2:U51,1)/COUNTA(U2:U51) -> 0.96
P53: =P52*100 -> 88 | Q53: =Q52*100 -> 76 | R53: =R52*100 -> 88 | S53: =S52*100 -> 82 | T53: =T52*100 -> 100 | U53: =U52*100 -> 96

Sheet Lists
A1: Assigned | B1: Status | D1: Humor (Primary) | E1: Count Humor | F1: Mangler | G1: Mål | I1: Context (Primary) | J1: Count context | K1: Mangler | L1: Mål | N1: farvekode | O1: Antal billeder for style | P1: Antal billeder for context | R1: Picture annotations | S1: Name | T1: status | U1: Progress | V1: Mål | X1: Count Humor primary (PA) | Y1: Humor primary + secondary count (PA) | Z1: Context primary count (PA) | AA1: Context primary + secondary count
A2: Sabrina | B2: Not started | D2: Wordplay | E2: =COUNTIFS(Annotations!I:I,D2,Annotations!C:C,"Done") -> 65 | F2: =MAX(0,$G2-E2) -> 0 | G2: 63 | I2: Pop culture | J2: =COUNTIFS(Annotations!K:K,I2,Annotations!C:C,"Done") -> 62 | K2: =MAX(0,$L2-J2) -> 0 | L2: 56 | N2: 0-30% | O2: 0-21 | P2: 0-16 | S2: Sabrina | T2: Done | U2: =COUNTIFS(Annotations!B:B,A2,Annotations!C:C,"Done") -> 250 | V2: 250 | X2: =COUNTIF(PAnnotations!F:F,$D$2) -> 7 | Y2: =COUNTIF(PAnnotations!F:F,$D$2)+COUNTIF(PAnnotations!G:G,$D$2) -> 7 | Z2: =COUNTIF(PAnnotations!H:H,I2) -> 8 | AA2: =COUNTIF(PAnnotations!H:H,$I$2)+COUNTIF(PAnnotations!I:I,$I$2) -> 12
A3: Naomi | B3: In progress | D3: Situational | E3: =COUNTIFS(Annotations!I:I,D3,Annotations!C:C,"Done") -> 63 | F3: =MAX(0,$G3-E3) -> 0 | G3: 63 | I3: meme | J3: =COUNTIFS(Annotations!K:K,I3,Annotations!C:C,"Done") -> 41 | K3: =MAX(0,$L3-J3) -> 15 | L3: 56 | N3: 31-74% | O3: 22-53 | P3: 17-40 | S3: Naomi | T3: Done | U3: =COUNTIFS(Annotations!B:B,A3,Annotations!C:C,"Done") -> 251 | V3: 250 | X3: =COUNTIF(PAnnotations!F:F,$D$3) -> 6 | Y3: =COUNTIF(PAnnotations!F:F,$D$3)+COUNTIF(PAnnotations!G:G,$D$3) -> 19 | Z3: =COUNTIF(PAnnotations!H:H,I3) -> 3 | AA3: =COUNTIF(PAnnotations!H:H,$I$3)+COUNTIF(PAnnotations!I:I,$I$3) -> 5
B4: Done | D4: Comparison | E4: =COUNTIFS(Annotations!I:I,D4,Annotations!C:C,"Done") -> 65 | F4: =MAX(0,$G4-E4) -> 0 | G4: 63 | I4: Social conventions | J4: =COUNTIFS(Annotations!K:K,I4,Annotations!C:C,"Done") -> 64 | K4: =MAX(0,$L4-J4) -> 0 | L4: 56 | N4: 75%-100% | O4: 54-72 | P4: 41-56 | X4: =COUNTIF(PAnnotations!F:F,$D$4) -> 5 | Y4: =COUNTIF(PAnnotations!F:F,D4)+COUNTIF(PAnnotations!G:G,D4) -> 19 | Z4: =COUNTIF(PAnnotations!H:H,I4) -> 4 | AA4: =COUNTIF(PAnnotations!H:H,$I$4)+COUNTIF(PAnnotations!I:I,$I$4) -> 10
D5: Exaggeration | E5: =COUNTIFS(Annotations!I:I,D5,Annotations!C:C,"Done") -> 61 | F5: =MAX(0,$G5-E5) -> 2 | G5: 63 | I5: Technical | J5: =COUNTIFS(Annotations!K:K,I5,Annotations!C:C,"Done") -> 56 | K5: =MAX(0,$L5-J5) -> 0 | L5: 56 | R5: Partner Annotations | S5: Name | T5: status | U5: Progress | V5: Mål | X5: =COUNTIF(PAnnotations!F:F,$D$5) -> 7 | Y5: =COUNTIF(PAnnotations!F:F,$D$5)+COUNTIF(PAnnotations!G:G,$D$5) -> 13 | Z5: =COUNTIF(PAnnotations!H:H,I5) -> 4 | AA5: =COUNTIF(PAnnotations!H:H,$I$5)+COUNTIF(PAnnotations!I:I,$I$5) -> 6
D6: Sarcasm/Irony | E6: =COUNTIFS(Annotations!I:I,D6,Annotations!C:C,"Done") -> 61 | F6: =MAX(0,$G6-E6) -> 2 | G6: 63 | I6: Hobby | J6: =COUNTIFS(Annotations!K:K,I6,Annotations!C:C,"Done") -> 61 | K6: =MAX(0,$L6-J6) -> 0 | L6: 56 | S6: Sabrina | T6: Done | U6: =COUNTIFS(PAnnotations!J:J,A2,PAnnotations!K:K,"Done") -> 25 | V6: 25 | X6: =COUNTIF(PAnnotations!F:F,$D$6) -> 8 | Y6: =COUNTIF(PAnnotations!F:F,$D$6)+COUNTIF(PAnnotations!G:G,$D$6) -> 14 | Z6: =COUNTIF(PAnnotations!H:H,I6) -> 5 | AA6: =COUNTIF(PAnnotations!H:H,$I$6)+COUNTIF(PAnnotations!I:I,$I$6) -> 13
D7: Surprise | E7: =COUNTIFS(Annotations!I:I,D7,Annotations!C:C,"Done") -> 54 | F7: =MAX(0,$G7-E7) -> 9 | G7: 63 | I7: Logical | J7: =COUNTIFS(Annotations!K:K,I7,Annotations!C:C,"Done") -> 50 | K7: =MAX(0,$L7-J7) -> 6 | L7: 56 | S7: Naomi | T7: Done | U7: =COUNTIFS(PAnnotations!J:J,A3,PAnnotations!K:K,"Done") -> 25 | V7: 25 | X7: =COUNTIF(PAnnotations!F:F,$D$7) -> 5 | Y7: =COUNTIF(PAnnotations!F:F,$D$7)+COUNTIF(PAnnotations!G:G,$D$7) -> 9 | Z7: =COUNTIF(PAnnotations!H:H,I7) -> 8 | AA7: =COUNTIF(PAnnotations!H:H,$I$7)+COUNTIF(PAnnotations!I:I,$I$7) -> 17
D8: Incongruity | E8: =COUNTIFS(Annotations!I:I,D8,Annotations!C:C,"Done") -> 62 | F8: =MAX(0,$G8-E8) -> 1 | G8: 63 | I8: General knowledge | J8: =COUNTIFS(Annotations!K:K,I8,Annotations!C:C,"Done") -> 55 | K8: =MAX(0,$L8-J8) -> 1 | L8: 56 | X8: =COUNTIF(PAnnotations!F:F,$D$8) -> 8 | Y8: =COUNTIF(PAnnotations!F:F,$D$8)+COUNTIF(PAnnotations!G:G,$D$8) -> 9 | Z8: =COUNTIF(PAnnotations!H:H,I8) -> 5 | AA8: =COUNTIF(PAnnotations!H:H,$I$8)+COUNTIF(PAnnotations!I:I,$I$8) -> 18
D9: Dark Humor | E9: =COUNTIFS(Annotations!I:I,D9,Annotations!C:C,"Done") -> 70 | F9: =MAX(0,$G9-E9) -> 0 | G9: 63 | I9: politics | J9: =COUNTIFS(Annotations!K:K,I9,Annotations!C:C,"Done") -> 57 | K9: =MAX(0,$L9-J9) -> 0 | L9: 56 | R9: Secondary tags | S9: Name | T9: status | U9: Progress | V9: Mål | X9: =COUNTIF(PAnnotations!F:F,$D$9) -> 4 | Y9: =COUNTIF(PAnnotations!F:F,$D$9)+COUNTIF(PAnnotations!G:G,$D$9) -> 10 | Z9: =COUNTIF(PAnnotations!H:H,I9) -> 5 | AA9: =COUNTIF(PAnnotations!H:H,$I$9)+COUNTIF(PAnnotations!I:I,$I$9) -> 10
I10: History/Mythology | J10: =COUNTIFS(Annotations!K:K,I10,Annotations!C:C,"Done") -> 55 | K10: =MAX(0,$L10-J10) -> 1 | L10: 56 | S10: Sabrina | T10: Done | U10: =COUNTIFS(Annotations!$B$2:$B$504,"Sabrina",Annotations!$J$2:$J$504,"<>",Annotations!$L$2:$L$504,"<>") -> 250 | V10: 250 | Z10: =COUNTIF(PAnnotations!H:H,I10) -> 8 | AA10: =COUNTIF(PAnnotations!H:H,$I$10)+COUNTIF(PAnnotations!I:I,$I$10) -> 9
D11: I alt | E11: =SUM(E2:E9) -> 501 | F11: =504-E11 -> 3 | G11: =SUM(G2:G9) -> 504 | I11: I alt | J11: =SUM(J2:J10) -> 501 | K11: =504-J11 -> 3 | L11: =SUM(L2:L10) -> 504 | S11: Naomi | T11: Done | U11: =COUNTIFS(Annotations!$B$2:$B$504,"Naomi",Annotations!$J$2:$J$504,"<>",Annotations!$L$2:$L$504,"<>") -> 251 | V11: 250
X13: Secondary humor count | Y13: Humor primary + secondary count (PA) | Z13: secondary context count | AA13: Context primary + secondary count
C14: Fokusområde: | H14: Fokusområde: | X14: =COUNTIF(Annotations!J:J,$D$2) -> 5 | Y14: =COUNTIF(Annotations!I:I,$D$2)+COUNTIF(Annotations!J:J,$D$2) -> 70 | Z14: =COUNTIF(Annotations!L:L,$I$2) -> 60 | AA14: =COUNTIF(Annotations!K:K,$I$2)+COUNTIF(Annotations!L:L,$I$2) -> 122
C15: Wordplay, Sarcasm and Dark humor | H15: meme, politics, historie og hobby | X15: =COUNTIF(Annotations!J:J,$D$3) -> 113 | Y15: =COUNTIF(Annotations!I:I,$D$3)+COUNTIF(Annotations!J:J,$D$3) -> 176 | Z15: =COUNTIF(Annotations!L:L,$I$3) -> 25 | AA15: =COUNTIF(Annotations!K:K,$I$3)+COUNTIF(Annotations!L:L,$I$3) -> 66
X16: =COUNTIF(Annotations!J:J,$D$4) -> 121 | Y16: =COUNTIF(Annotations!I:I,D4)+COUNTIF(Annotations!J:J,D4) -> 186 | Z16: =COUNTIF(Annotations!L:L,$I$4) -> 89 | AA16: =COUNTIF(Annotations!K:K,$I$4)+COUNTIF(Annotations!L:L,$I$4) -> 153
X17: =COUNTIF(Annotations!J:J,$D$5) -> 75 | Y17: =COUNTIF(Annotations!I:I,$D$5)+COUNTIF(Annotations!J:J,$D$5) -> 136 | Z17: =COUNTIF(Annotations!L:L,$I$5) -> 18 | AA17: =COUNTIF(Annotations!K:K,$I$5)+COUNTIF(Annotations!L:L,$I$5) -> 74
X18: =COUNTIF(Annotations!J:J,$D$6) -> 76 | Y18: =COUNTIF(Annotations!I:I,$D$6)+COUNTIF(Annotations!J:J,$D$6) -> 137 | Z18: =COUNTIF(Annotations!L:L,$I$6) -> 50 | AA18: =COUNTIF(Annotations!K:K,$I$6)+COUNTIF(Annotations!L:L,$I$6) -> 111
X19: =COUNTIF(Annotations!J:J,$D$7) -> 34 | Y19: =COUNTIF(Annotations!I:I,$D$7)+COUNTIF(Annotations!J:J,$D$7) -> 88 | Z19: =COUNTIF(Annotations!L:L,$I$7) -> 70 | AA19: =COUNTIF(Annotations!K:K,$I$7)+COUNTIF(Annotations!L:L,$I$7) -> 120
X20: =COUNTIF(Annotations!J:J,$D$8) -> 34 | Y20: =COUNTIF(Annotations!I:I,$D$8)+COUNTIF(Annotations!J:J,$D$8) -> 96 | Z20: =COUNTIF(Annotations!L:L,$I$8) -> 146 | AA20: =COUNTIF(Annotations!K:K,$I$8)+COUNTIF(Annotations!L:L,$I$8) -> 201
X21: =COUNTIF(Annotations!J:J,$D$9) -> 43 | Y21: =COUNTIF(Annotations!I:I,$D$9)+COUNTIF(Annotations!J:J,$D$9) -> 113 | Z21: =COUNTIF(Annotations!L:L,$I$9) -> 26 | AA21: =COUNTIF(Annotations!K:K,$I$9)+COUNTIF(Annotations!L:L,$I$9) -> 83
Z22: =COUNTIF(Annotations!L:L,$I$10) -> 17 | AA22: =COUNTIF(Annotations!K:K,$I$10)+COUNTIF(Annotations!L:L,$I$10) -> 72

Sheet Notes
A1: AI to use: look for performace gap i disse modeller | B1: Duplicates: slettet fra vores annotation ark | C1: inden vi analysere med AI | D1: Lektie til næste gang | E1: Spørgsmål | F1: Inddrag i rapport
A2: GPT5 | B2: 1jfy6ms | C2: Når vi har ramt 500 billeder skal vi sørge for alt teksten er ensartet, dvs. enten punktum på alle eller ingen, fjerne indrykning, fjerne citationstegn, stort bogstav for alle sætninger etc. | D2: Find akademiske kilder 3-4 hver, kilderne skal være nuanceret (artikler, bøger m.m.) | E2: skal vi lave en komparativ analyse? Dvs. Skal vi sammenligne Fridas resultater med vores? Fx om vi kan sige om accuracy m.m. | F2: til sammenligning med frida er vores muligheder med flere ord, vores literal er meget mere beskrivende
A3: Claude 4.6 | B3: 1gz2i0o | C3: når man omdanner cvs til excel bliver nogle tegn underlige, det skal rettes | D3: Lav en kode som gør teksten ren i annotations
A4: Gemini 3 | B4: 1d6ho4f | C4: vi skal randomisere rækkefølgen af svarmulighederne | D4: En kode der randomisere svarene
A5: Open weight models | B5: 1gqh1c5 | C5: for literal: hvis det er none of the above så lav en ny og ellers så tag den der tættest på | D5: Have en klar outline
A6: Gemma 4 E4B | B6: 1mfr9vy | D6: Skrive analyse delen
A7: Qwen 3.5 4B | B7: 1j983b2
A8: 2 other models: mixture (More training capacity) | C8: Lav en sekundær tag til billederne | D8: Naomi: finish csv file and adjust frida code to run experiment
A9: gemma 4 26B A4B | C9: hav styr på hvad en transformer language model er | D9: Outline: Naomi (2 related work) Sabrina (3 data)
A10: qwen 3.5 35B A3B | C10: Hvordan de trænes (modellerne) | D10: Lav 25 partner annotations til hinandens random
A11: - Gemma E4B - Qwen 3.5 -4B - Gemma 4 -26B -A4B -it - Qwen 3.5- 35B A3B | C11: Open ai key | D11: Skriv til desmond
A12: Use | C12: 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 | D12: Sabrina: Lav secondary tags til billederne
D13: Sabrina: Lav progress for partner annotation
A14: openrouter.ai | D14: do both (with the correct answer)
A15: Google collab | D15: correlation precentages
C16: openrouter.ai key | D16: variance and standard deviation
C17: 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
A38: Result times:
A39: Claude: 32 mins
A40: Gemini: 51 min
A41: OpenAI GPT : 1 hr 37 min | C41: gemma-4-26b-a4b-it: returning invalid beacuse it is choosing none instead of letters a,b,c,d
A42: qwen3-vl-30b-a3b-thinking: 19 mins
A43: qwen3.5-9b: 386 min
A44: gemma-4-26b-a4b-it: 175 mins
A45: gemma-3-4b-it: 1m
C51: 1hevxkv | D51: errors out on google/gemma-4-26b-a4b-it

Sheet Definitions
A1: Context definitions | B1: How to use them correctly | C1: Examples | D1: Humor style definitions | E1: How to use them correctly | F1: Examples
A2: popculture | B2: Requires knowledge of widely known media, celebrities, movies, music, or mainstream entertainment. | C2: This is me waiting like Harry Potter for my letter
A3: Meme | B3: Requires familiarity with a specific internet meme format or template. | C3: “This is fine.” (dog sitting in a burning room)
A4: Social conventions | B4: Requires understanding of social norms, roles, or expected behavior between people. | C4: Saying ‘you too’ to the waiter when they say enjoy your meal.
A5: Technical | B5: Requires specialized or domain-specific knowledge (e.g. programming, science, psychology). | C5: Fixing a bug by commenting out the code.
A6: Hobby | B6: Requires insider knowledge of a niche interest or community (e.g. Warhammer, fishing). | C6: Only Warhammer players know this pain…
A7: Logical | B7: Requires understanding of reasoning, logic, or a flawed/absurd conclusion. | C7: If tomatoes are fruit, then ketchup is a smoothie.
A8: General knowledge | B8: Requires broad, common knowledge about the world that most people are expected to know. | C8: Nokia phones never break
A9: Politics | B9: Requires knowledge of political systems, conflicts, ideologies, or current affairs. | C9: Russia taking land like my neighbor taking my parking spot.
A10: History/Mythology | B10: Requires knowledge of historical events, figures, or mythological stories. | C10: Medusa turning men to stone
A13: sarcasm/Irony
A14: Wordplay/rhymes
A15: Social/Cultural Norms.
