Workbook

Sheet Annotations
A1: File | B1: Assigned_to | C1: Status | D1: Correct answer | E1: Explanation 1 | F1: Explanation 2 | G1: Explanation 3 | H1: Literal_Description | I1: Humor Style | J1: Humor style secondary | K1: Contextual Knowledge | L1: Contextual Knowledge secondary | M1: Duplicate check
A2: 1actpx8 | B2: Sabrina | C2: Done | D2: the meme refers to cloudy and a chance of meatballs (movie): the main character is a scientist and sprayed on shoes when he was a kid, which he could never remove | E2: its exaggeration, as the meme presents an obviously unnecessary warning against using Flex Seal as footwear, thereby highlighting the absurdity of the situation. | F2: using Flex Seal as footwear is portrayed as undesirable, humorously justified by the unlikely scenario of falling meatballs from the sky. | G2: a snapchat picture showing a person holding a can of Flex Seal and their foot covered in a black substance, with the text ‘Flex seal shoe’ with the text underneath: "did the tales of falling meatballs not weigh on thine conscious". | H2: a snapchat picture showing a person holding a can of Flex Seal and their foot covered in a black substance, with the text ‘Flex seal shoe’ with the text underneath: "did the tales of falling meatballs not weigh on thine conscious". | I2: Sarcasm/Irony | J2: Surprise | K2: Hobby | L2: Logical | M2: =IF(COUNTIF($A$2:A2, A2)>1, "Dublet", "OK") -> OK
A3: 1af8odu | B3: Sabrina | C3: Done | D3: A teller is a person who works at the front desk of a bank. Teller is also a person's name; that person is one half of the magician duo Penn & Teller. On stage, Teller doesn't speak. Penn is the one who explains everything/talks to the crowd. The joke is that you expect the robber to be speaking to a bank teller. But he's actually speaking to the magician Teller who doesn't talk. That's why Penn comes in at the end to explain what's going on. | E3: Penn’s comment makes the scene funny because he already understands why the “teller” never answers. The silence is treated as typical behavior, not as fear or confusion | F3: A tweet-style image shows a fictional dialogue where a bank robber repeatedly asks a teller where the safe is. The teller gives no visible response, and the robber becomes confused. The final line says, “PENN: He always does this,” implying the teller is the magician Teller, who is known for staying silent. | G3: The robber is absurdly expecting a machine to respond like a person, which makes his frustration seem misplaced and cartoon-like. | H3: A tweet-style image shows a fictional dialogue where a bank robber repeatedly asks a teller where the safe is. The teller gives no visible response, and the robber becomes confused. The final line says, “PENN: He always does this,” implying the teller is the magician Teller, who is known for staying silent. | I3: Wordplay | J3: Sarcasm/Irony | K3: Pop culture | L3: Social conventions | M3: =IF(COUNTIF($A$2:A3, A3)>1, "Dublet", "OK") -> OK
A4: 1ajzxfm | B4: Sabrina | C4: Done | D4: It’s kind of a weird joke that doesn’t make perfect sense, but here’s the intended meaning: 1. Many people might see something like 50/50 odds leading to 20 successes in a row and think the next one is more likely to be a failed surgery. Like how many people could flip a coin and get heads twice in a row, and be more likely to guess the next coinflip would be tails. Hence the nervous face. 2. A statistician would know that the success rate of each surgery is independent of all the other ones, so they wouldn’t be especially nervous theirs would go wrong. 3. A scientist might see 20 successes in a row for a surgery with a 50% survival rate and think “wow, this doctor must be really good at doing surgeries” | E4: The meme explains that normal people would choose this doctor because he has 50% success rate, where as mathematicians would be more sceptical and scientists would refrain from getting a surgery from this doctor. | F4: The meme is funny because it illustrates how different fields of process thoughts, it is funny because although most people would take the surgery, mathmaticians and scientists wouldn't because they have the knowledge to know that the probability of the surgery failing is very small despite the given numbers. | G4: A meme with text describing a doctor stating that a surgery has a 50% survival rate and that the last 20 patients survived. Below the text are three panels labeled ‘Normal people’, ‘Mathematician’, and ‘Scientist’, each showing a different face reacting to the statement. | H4: A meme with text describing a doctor stating that a surgery has a 50% survival rate and that the last 20 patients survived. Below the text are three panels labeled ‘Normal people’, ‘Mathematician’, and ‘Scientist’, each showing a different face reacting to the statement. | I4: Comparison | J4: Exaggeration | K4: Logical | L4: General knowledge | M4: =IF(COUNTIF($A$2:A4, A4)>1, "Dublet", "OK") -> OK
A5: 1amtoff | B5: Sabrina | C5: Done | D5: Amazon does not hire 12 year olds, and 12 year olds cannot drive. The potential panic this may cause whomever at Amazon, is hilarious. | E5: The humor arises from the unexpected implication that a well-known company such as Amazon employs a 12-year-old, which contradicts established social and legal norms, thereby creating a surprising and absurd scenario. | F5: A screenshot of a social media thread where a user says that Amazon hired their 12-year-old son, followed by a response from an Amazon customer service account asking for clarification, and a subsequent reply stating that the son is one of their drivers | G5: The humor stems from the company’s apparent unawareness of having employed an underage individual, leading to the implicit consequence that they would need to locate and terminate the employment, which highlights the absurdity of the situation. | H5: A screenshot of a social media thread where a user says that Amazon hired their 12-year-old son, followed by a response from an Amazon customer service account asking for clarification, and a subsequent reply stating that the son is one of their drivers | I5: Incongruity | J5: Sarcasm/Irony | K5: General knowledge | L5: Social conventions | M5: =IF(COUNTIF($A$2:A5, A5)>1, "Dublet", "OK") -> OK
A6: 1aoxsw3 | B6: Sabrina | C6: Done | D6: Deer run in circles as a defense mechanism against predators ants run in circles because an ant has to turn around & left a pheromone trail in a circle, so the ants will die. it’s very sad. | E6: The humor arises from a contrast in perception, where similar circular movement is framed as unsettling in deer but appealing in ants. | F6: The humor stems from anthropomorphic framing, as deer and ants are depicted as exhibiting human-like reactions when observing animals moving in circles. | G6: “A meme with the caption ‘Animals running in circles is so cool’ at the top, followed by two images of animals arranged in circular formations. Below the images are two panels with illustrated faces, labeled ‘Deers’ on the left and ‘Ants’ on the right, each showing a different facial expression.” | H6: “A meme with the caption ‘Animals running in circles is so cool’ at the top, followed by two images of animals arranged in circular formations. Below the images are two panels with illustrated faces, labeled ‘Deers’ on the left and ‘Ants’ on the right, each showing a different facial expression.” | I6: Comparison | J6: Situational | K6: Technical | L6: General knowledge | M6: =IF(COUNTIF($A$2:A6, A6)>1, "Dublet", "OK") -> OK
A7: 1asrnb3 | B7: Sabrina | C7: Done | D7: The black car is the Impala (aka “Metallicar”/“Baby”) from *Supernatural*, a show about two brothers who hunt down paranormal phenomena like ghosts, demons, etc. The Mystery Machine, of course, is Scooby Doo and the Scooby Gang, who hunt down ghosts and other various monsters. If they’re both in the same place, some haunted stuff is going down. | E7: Incongruity between the claim that the location is haunted and the absence of any visible supernatural elements, resulting in a confusing and unexpected situation. | F7: The humor stems from a cultural association between the presence of suspicious-looking vehicles and the suggestion of unusual activity, which contrasts with the otherwise ordinary setting. | G7: A meme with the text “oh this place is HAUNTED haunted” at the top, showing a black car parked in front of a colorful van resembling the Scooby-Doo “Mystery Machine” in a parking lot. | H7: A meme with the text “oh this place is HAUNTED haunted” at the top, showing a black car parked in front of a colorful van resembling the Scooby-Doo “Mystery Machine” in a parking lot. | I7: Exaggeration | J7: Comparison | K7: Pop culture | L7: Hobby | M7: =IF(COUNTIF($A$2:A7, A7)>1, "Dublet", "OK") -> OK
A8: 1aya611 | B8: Sabrina | C8: Done | D8: Alabama ruled that frozen embryos count as live children, so this couple is claiming their 3 live children and 5 frozen embryos as 8 total children for tax purposes | E8: The humor arises from the unexpected implication that the parents to the children are experimenting on them in a lab they have at home | F8: The couple tries to claim more children for tax benefits, but claiming 'children in the lab' creates absurdity which makes the situation funny | G8: A meme showing a couple sitting in an office labeled “Tax Services,” speaking to a man behind a desk. One person says “We’re claiming 8 kids…” and the other adds “3 at home and 5 in the lab.” | H8: A meme showing a couple sitting in an office labeled “Tax Services,” speaking to a man behind a desk. One person says “We’re claiming 8 kids…” and the other adds “3 at home and 5 in the lab.” | I8: Sarcasm/Irony | J8: Exaggeration | K8: Social conventions | L8: Logical | M8: =IF(COUNTIF($A$2:A8, A8)>1, "Dublet", "OK") -> OK
A9: 1b03bqv | B9: Sabrina | C9: Done | D9: we's making up states to mess em up badly | E9: The state is relatively small and is therefore often overlooked or difficult to recall. | F9: the stereotype that many Americans are unable to identify all U.S. states, implying that they would fail the task presented. | G9: A map of the United States showing state borders, with one state highlighted in yellow and a caption asking viewers to identify it. | H9: A map of the United States showing state borders, with one state highlighted in yellow and a caption asking viewers to identify it. | I9: Incongruity | J9: Sarcasm/Irony | K9: politics | L9: General knowledge | M9: =IF(COUNTIF($A$2:A9, A9)>1, "Dublet", "OK") -> OK
A10: 1b7unh0 | B10: Sabrina | C10: Done | D10: He would probably also be confused why they had built a second Memphis | E10: The humor arises from a stereotypical contrast suggesting that men would use time travel to carry out significant historical interventions, whereas women are portrayed as being motivated by the desire to see Cleopatra in person. | F10: The humor stems from a reversed stereotypical framing in which women are depicted as pursuing significant historical interventions, while men are portrayed as being motivated by the desire to see Cleopatra in person. | G10: A meme divided into two sections labeled “Women with a time machine” and “Men with a time machine.” The top shows a woman pointing a gun at Henry Ford. The bottom shows a man speaking to an ancient Egyptian figure in front of a pyramid, with text about a modern glass pyramid in Memphis containing a Bass Pro Shop. | H10: A meme divided into two sections labeled “Women with a time machine” and “Men with a time machine.” The top shows a woman pointing a gun at Henry Ford. The bottom shows a man speaking to an ancient Egyptian figure in front of a pyramid, with text about a modern glass pyramid in Memphis containing a Bass Pro Shop. | I10: Comparison | J10: Dark Humor | K10: History/Mythology | L10: Logical | M10: =IF(COUNTIF($A$2:A10, A10)>1, "Dublet", "OK") -> OK
A11: 1be8p2s | B11: Sabrina | C11: Done | D11: It's a football thing Hosted in Brazil, best international team historically and huge favourites to win, they crashed out the tournament to Germany with a 7-1 loss. One of the most shocking results in football. Brazilian fans did not take the loss well. | E11: The humor arises from a reference to the widely recognized “6–7” event, which gives the expression an additional, non-mathematical meaning. | F11: The humor stems from the strong cultural association of the “6–7” reference in Brazil, where repeated exposure to the event evokes an emotional response. | G11: A meme with text at the top reading “Teacher: what is 7-1? Me: 6 My Brazilian classmates:” followed by an image of people wearing yellow shirts reacting emotionally in what appears to be a stadium setting. | H11: A meme with text at the top reading “Teacher: what is 7-1? Me: 6 My Brazilian classmates:” followed by an image of people wearing yellow shirts reacting emotionally in what appears to be a stadium setting. | I11: Incongruity | J11: Situational | K11: Pop culture | L11: General knowledge | M11: =IF(COUNTIF($A$2:A11, A11)>1, "Dublet", "OK") -> OK
A12: 1bikyy1 | B12: Sabrina | C12: Done | D12: The math is a little off, but the gist of it is that the grand canyon took a long *long* time to get to its current state, but, at some point in the very distant past, it would've started out as a small stream, as depicted in the meme. So, the joke is that the Flintstones were around a long time ago when the Grand Canyon was still just a little stream. | E12: The humor arises from an incongruity in scale, where the Grand Canyon is depicted as disproportionately small relative to the characters, implying that people in the past were significantly larger than in reality. This contrast highlights the absurdity of the scene. | F12: The humor stems from an implicit exaggeration of the Grand Canyon’s size, reflecting the tendency to describe it as exceptionally vast in comparison to its representation in the image. | G12: A meme with the text “So that's the Grand Canyon, huh?” followed by “– The Flintstones,” showing a cartoon scene of characters standing near a narrow canyon with a small stream running through it. | H12: A meme with the text “So that's the Grand Canyon, huh?” followed by “– The Flintstones,” showing a cartoon scene of characters standing near a narrow canyon with a small stream running through it. | I12: Sarcasm/Irony | J12: Incongruity | K12: History/Mythology | L12: General knowledge | M12: =IF(COUNTIF($A$2:A12, A12)>1, "Dublet", "OK") -> OK
A13: 1bl3eve | B13: Sabrina | C13: Done | D13: Been a while since I read the books but basically, phones attract monsters for some reason, so Demigods don’t carry them around. | E13: The humor arises from the implausibility of using an iPod as a means of confronting Medusa, highlighting the absurdity of the situation. | F13: The humor stems from the anachronistic coexistence of Medusa and Percy Jackson, combining mythological elements with a modern setting. | G13: A screenshot of a social media post referencing Percy Jackson using an iPod to fight Medusa, accompanied by two images: one of a character holding a device and another showing Medusa’s reflection in the device. Below, a reply comments that it is funny because they did not have phones. | H13: A screenshot of a social media post referencing Percy Jackson using an iPod to fight Medusa, accompanied by two images: one of a character holding a device and another showing Medusa’s reflection in the device. Below, a reply comments that it is funny because they did not have phones. | I13: Incongruity | J13: Sarcasm/Irony | K13: Hobby | L13: Logical | M13: =IF(COUNTIF($A$2:A13, A13)>1, "Dublet", "OK") -> OK
... A165: 1mluk7a | B165: Naomi | C165: Done | D165: After WW2 countless people had to plant trees to restock wood with mostly monoculture forests, as ressource for rebuilding the mostly destroyed country. During the war way more wood was taken off the land then replanted. | E165: Its a joke because of their differing climates amking it an impossible comaprison. | F165: Text over a leafy background discusses Germany being "green" compared to Spain. Below the text, a man in a black sweater touches his nose while looking to the side. | G165: Because the the vastly different land per capita comparison | H165: Text over a leafy background discusses Germany being "green" compared to Spain. Below the text, a man in a black sweater touches his nose while looking to the side. | I165: Dark Humor | J165: Comparison | K165: History/Mythology | L165: politics | M165: =IF(COUNTIF($A$2:A165, A165)>1, "Dublet", "OK") -> OK
A166: 1mpg380 | B166: Naomi | C166: Done | D166: Frustration's attack power depends on how low your friendship is. If Frustration is dealing some big damage, you've got a shitty trainer on your hands Edit: Also it's a Sylveon, which requires the OPPOSITE of what Frustration demands, so yeah that other trainer has done things to harm this poor creature so much they might have to get banned in-universe Edit 2: Sylveon evolves from Affection in Gen 6 and 7, IDK why that got nixed in Gen 8 onwards | E166: This image shows a digital menu for the Pokémon Sylveon with the moves Frustration, Dazzling Gleam, Hyper Beam, and Focus Energy selected. Below the menu is a two-panel meme featuring Mr. Incredible, with a colorful version labeled "THOSE WHO DON'T KNOW" on the left and a dark, distorted version labeled "THOSE WHO KNOW" on the right. | F166: On the surface it seems like a cute pink creature but when you read closer frustration is one of its key traits. | G166: This is a famously difficult game if your loadut is incorrect and this is one of them. | H166: This image shows a digital menu for the Pokémon Sylveon with the moves Frustration, Dazzling Gleam, Hyper Beam, and Focus Energy selected. Below the menu is a two-panel meme featuring Mr. Incredible, with a colorful version labeled "THOSE WHO DON'T KNOW" on the left and a dark, distorted version labeled "THOSE WHO KNOW" on the right. | I166: Situational | K166: Hobby | M166: =IF(COUNTIF($A$2:A166, A166)>1, "Dublet", "OK") -> OK
A167: 1eexgq9 | B167: Naomi | C167: Done | D167: Argentina is where a lot of nazi refugees fled from Germany as the outcome of WW2 was becoming more certain to avoid capture by the allies. As a result, many of their descendants still live there, so you end up with some Argentinians with suspiciously German last names and lineage. | E167: It is a joke because Argntianians have famously "less latiny names" | F167: It is funny bercause German last names are some of the most common throughut the whole world. | G167: The image features the header "Argentinians be like:" above two photos labeled "First Name" and "Last Name." Under "First Name," a man is shown in a traditional matador outfit with a cape, and under "Last Name," a man is wearing a black Nazi SS military uniform with a swastika armband. | H167: The image features the header "Argentinians be like:" above two photos labeled "First Name" and "Last Name." Under "First Name," a man is shown in a traditional matador outfit with a cape, and under "Last Name," a man is wearing a black Nazi SS military uniform with a swastika armband. | I167: Dark Humor | K167: History/Mythology | M167: =IF(COUNTIF($A$2:A167, A167)>1, "Dublet", "OK") -> OK
A168: 1cs870m | B168: Naomi | C168: Done | D168: Nada means nothing but also swim, he asked what's up | E168: It is funny because penguins dont talk. | F168: It is funny because penguins dont speak spanish. | G168: The image contains a social media post with the text, "i'm literally so bored i just realized that 'no' is 'on' backwards." Below the text is a reaction photo of a man with a shocked, wide-eyed expression. | H168: The image contains a social media post with the text, "i'm literally so bored i just realized that 'no' is 'on' backwards." Below the text is a reaction photo of a man with a shocked, wide-eyed expression. | I168: Wordplay | K168: General knowledge | M168: =IF(COUNTIF($A$2:A168, A168)>1, "Dublet", "OK") -> OK
A169: 1g1cv45 | B169: Naomi | C169: Done | D169: He is putting water into the empty bottle, to shake it up and make soapy water, to get an extra wash out of the bottle before throwing it away. | E169: It funny because the animal is sad and it is asumed that one would be happy having fufillled thier childhood goals. | F169: It is funny because animals dont shower themselves ad wouldnt know to put water in the bottle of soap to get an extra use. | G169: He is putting water into the empty bottle, to shake it up and make soapy water, to get an extra wash out of the bottle before throwing it away. | H169: He is putting water into the empty bottle, to shake it up and make soapy water, to get an extra wash out of the bottle before throwing it away. | I169: Comparison | K169: meme | M169: =IF(COUNTIF($A$2:A169, A169)>1, "Dublet", "OK") -> OK
A170: 1g2ofgo | B170: Naomi | C170: Done | D170: Traditional ways of observing Yom Kippur include abstaining from food, washing, and sex, so it's not really normal to wish a happy" Yom Kippur to anyone" | E170: That is not traditionally how you greet someone on yom kippur. | F170: It is funny because on Yom Kippur jews usually dont use phones as technology is forbidden to keep kosher lifestyle. | G170: A 4 panel meme with screenshots from the terminator with him wishing th woman on the phone "Happy Yom Kipur" her returning the greeting and then the man telling the child his parents are dead. | H170: A 4 panel meme with screenshots from the terminator with him wishing th woman on the phone "Happy Yom Kipur" her returning the greeting and then the man telling the child his parents are dead. | I170: Situational | K170: History/Mythology | M170: =IF(COUNTIF($A$2:A170, A170)>1, "Dublet", "OK") -> OK
A171: 1jzu8un | B171: Naomi | C171: Done | D171: What's wrong with McAfee?What's wrong with McAfee? That question is a different topic, anyway the joke is that even if you uninstall it somehow it'll find its way back to your PC or just won't let you do it at all. | E171: A man labeled "Me" physically ejects another man labeled "McAfee" from a building. After the first man turns around to dust off his hands, the second man immediately reappears directly behind him inside the room. | F171: It is a joke refering to the common trope that there is always one friend you cant get rid of. | G171: It isa reference to the character macafee in the Netflix show "the Politician" | H171: A man labeled "Me" physically ejects another man labeled "McAfee" from a building. After the first man turns around to dust off his hands, the second man immediately reappears directly behind him inside the room. | I171: Surprise | K171: Technical | M171: =IF(COUNTIF($A$2:A171, A171)>1, "Dublet", "OK") -> OK
A172: 1gvvhs3 | B172: Naomi | C172: Done | D172: Tea" is slang for gossip" | E172: It is incongruous because a flight attendant would never divuldge this kind of information ti a passenger. | F172: It is funny because the woamn who asked for the tea is the wife. | G172: A flight attendant offers a passenger a choice between coffee or tea, to which the passenger selects tea. The flight attendant then leans in and shares a secret about the captain having a second family while his wife is on the same plane. | H172: A flight attendant offers a passenger a choice between coffee or tea, to which the passenger selects tea. The flight attendant then leans in and shares a secret about the captain having a second family while his wife is on the same plane. | I172: Wordplay | K172: Social conventions | M172: =IF(COUNTIF($A$2:A172, A172)>1, "Dublet", "OK") -> OK
A173: 1l22d3q | B173: Naomi | C173: Done | D173: It’s a pretty significant plot point to do with Yellowjackets, which she is a major character in. let’s just say, to avoid spoilers, wearing the heart necklace in that show is indicative of bad things to follow. also you should watch Yellowjackets | E173: It is a compliment to the woman in the photo saying she is so beautiful she is worth going to war for. | F173: A social media post features two photos of actress Ella Purnell, with a caption comparing her facial expression to a portrait one would carry in a heart locket during wartime. A comment below the photos suggests that she has already seen enough heart necklaces. | G173: The poster assumed that since she is beautiful she has already been gifted lots of jewlery. | H173: A social media post features two photos of actress Ella Purnell, with a caption comparing her facial expression to a portrait one would carry in a heart locket during wartime. A comment below the photos suggests that she has already seen enough heart necklaces. | I173: Sarcasm/Irony | K173: Pop culture | M173: =IF(COUNTIF($A$2:A173, A173)>1, "Dublet", "OK") -> OK
A174: 1j289je | B174: Naomi | C174: Done | D174: Penguins are a brand of individually wrapped biscuits | E174: It is a joke about platic toys and how two animals who would never coexist in nature are able to in plastic form. | F174: Elephants have famously thick and wrinkly skin. | G174: A person holds a small slip of paper featuring a joke about elephants and penguins. The text asks why elephants do not like penguins, followed by the answer: "They can't get the wrappers off." | H174: A person holds a small slip of paper featuring a joke about elephants and penguins. The text asks why elephants do not like penguins, followed by the answer: "They can't get the wrappers off." | I174: Incongruity | K174: General knowledge | M174: =IF(COUNTIF($A$2:A174, A174)>1, "Dublet", "OK") -> OK
A175: 1ga3uxo | B175: Naomi | C175: Done | D175: It prints out the 8th letter of the Sinhala alphabet, which is the official language of Sri Lanka. The alphabet looks like this: ඞ Amogus. | E175: It is a script that deletes your entire computer. | F175: It is a script that installs a virus that sends all your passwords and usernames to hackers. | G175: An image shows Peter Griffin from Family Guy running through a field while being chased by a plane. Overlaying the scene is a line of Python code and a warning to not print it, calling it the "worst mistake of my life." | H175: An image shows Peter Griffin from Family Guy running through a field while being chased by a plane. Overlaying the scene is a line of Python code and a warning to not print it, calling it the "worst mistake of my life." | I175: Surprise | K175: Technical | M175: =IF(COUNTIF($A$2:A175, A175)>1, "Dublet", "OK") -> OK
A176: 1l99mtp | B176: Naomi | C176: Done | D176: The answer is: horse legs don't bend that way. | E176: The busha upon frst glance looks like the head of a person. | F176: There are no such places in Auburn California. | G176: A framed sketch of a white horse is displayed on a wall above a wooden cabinet in a hotel foyer. A small, round topiary plant on the cabinet is positioned directly in front of the bottom of the painting, overlapping the horse's underside. | H176: A framed sketch of a white horse is displayed on a wall above a wooden cabinet in a hotel foyer. A small, round topiary plant on the cabinet is positioned directly in front of the bottom of the painting, overlapping the horse's underside. | I176: Situational | K176: Technical | M176: =IF(COUNTIF($A$2:A176, A176)>1, "Dublet", "OK") -> OK
A177: 1hjwowy | B177: Naomi | C177: Done | D177: It was posted by someone who identifies as GenX. That’s all there is to it. | E177: Gen X is uusally not as mentioned when discussing generational differences. | F177: A four-panel meme characterizes different generations through various emotional reactions: Millennials and Boomers are shown shouting and pointing, while Gen Z is shown crying into a headset. In the final panel, Gen X is depicted looking on calmly while holding a drink. | G177: It shws people depicted by their age. | H177: A four-panel meme characterizes different generations through various emotional reactions: Millennials and Boomers are shown shouting and pointing, while Gen Z is shown crying into a headset. In the final panel, Gen X is depicted looking on calmly while holding a drink. | I177: Exaggeration | K177: Social conventions | M177: =IF(COUNTIF($A$2:A177, A177)>1, "Dublet", "OK") -> OK
... A187: 1it3ezt | B187: Naomi | C187: Done | D187: As for a bee, he refers to an F-22 stealth fighter, whose radar-cross section is comparable to a bee. SO the radar says that there's a bee flying at mach 2 | E187: An image captioned "POV: You're in a Su-57 and a bee is approaching you at mach 2" showing a close-up of a gray and orange calico cat staring directly at the camera with a wide-eyed, worried expression. | F187: It is because the bee would most definetly be killed instantly by the object going mach 2. | G187: Its funny becaue a cat coukd never be a pilot. | H187: An image captioned "POV: You're in a Su-57 and a bee is approaching you at mach 2" showing a close-up of a gray and orange calico cat staring directly at the camera with a wide-eyed, worried expression. | I187: Wordplay | K187: Technical | M187: =IF(COUNTIF($A$2:A187, A187)>1, "Dublet", "OK") -> OK
A188: 1ceuuuh | B188: Sabrina | C188: Done | D188: They're all pregnant. Can't deploy pregnant people | E188: They are wearing longer jackets as a way of respecting Iran’s expectations around modest clothing. It looks like they are trying to adapt to the country’s rules and avoid standing out too much. | F188: The woman looks kind of dull and uninterested, like she is not exactly excited to be there. Her expression makes it seem as if the whole trip or situation is not really her vibe. | G188: At the top, the meme says, “Single female Soldiers when they hear they might deploy to Iran.” Under the text, a pregnant female soldier is shown from three different angles while wearing a military uniform. | H188: At the top, the meme says, “Single female Soldiers when they hear they might deploy to Iran.” Under the text, a pregnant female soldier is shown from three different angles while wearing a military uniform. | I188: Sarcasm/Irony | J188: Situational | K188: politics | L188: Logical | M188: =IF(COUNTIF($A$2:A188, A188)>1, "Dublet", "OK") -> OK
A189: 1bk5jkq | B189: Sabrina | C189: Done | D189: Noone's sure why saturn has a hexagon There's hypotheses, but noone's completely sure that's what the meme is referring to | E189: It is not actually a hexagon, which is basically the whole troll part of the meme. The image acts like it is showing something obvious or scientific, but the shape does not even match what it claims. | F189: Saturn’s hexagon is a real cloud pattern around the planet’s north pole, which is why the reference works. The meme depends on recognizing that Saturn is known for having this strange, almost hexagonal storm-like formation. | G189: This four-panel meme focuses on Saturn’s hexagon-shaped pole. It starts with a simple image of Saturn, then moves into darker and more dramatic edits where different meme faces react to the hexagon. | H189: This four-panel meme focuses on Saturn’s hexagon-shaped pole. It starts with a simple image of Saturn, then moves into darker and more dramatic edits where different meme faces react to the hexagon. | I189: Surprise | J189: Situational | K189: Technical | L189: Hobby | M189: =IF(COUNTIF($A$2:A189, A189)>1, "Dublet", "OK") -> OK
A190: 1az5r39 | B190: Sabrina | C190: Done | D190: Food prices in Canada are very high | E190: In America people have the whole American Dream thing where everyone is told they can work hard and maybe become rich one day. | F190: Bugs Bunny appears in two separate panels with different flags behind him. In the first panel, the American flag is shown with the words “work or starve,” while the second panel uses the Canadian flag and changes the phrase to “work and starve.” | G190: In Canada it feels more like people get a decent amount and the whole society is supposed to be a bit more equal. | H190: Bugs Bunny appears in two separate panels with different flags behind him. In the first panel, the American flag is shown with the words “work or starve,” while the second panel uses the Canadian flag and changes the phrase to “work and starve.” | I190: Comparison | J190: Exaggeration | K190: politics | L190: General knowledge | M190: =IF(COUNTIF($A$2:A190, A190)>1, "Dublet", "OK") -> OK
A191: 1hauo6q | B191: Sabrina | C191: Done | D191: A McDonald's employee collected the prize bag on identifying the UnitedHealth CEO assassin. | E191: A “Marked Safe” style post is shown with a small blue flag icon above the text. The message says that the person is marked safe from being the most hated McDonald’s employee in the country today. | F191: No matter how hated you think you are there is always someone people hate even more lol. | G191: Working at McDonald’s already makes some people judge you because of all the boycotts and politics around it. | H191: A “Marked Safe” style post is shown with a small blue flag icon above the text. The message says that the person is marked safe from being the most hated McDonald’s employee in the country today. | I191: Dark Humor | J191: Exaggeration | K191: politics | L191: Pop culture | M191: =IF(COUNTIF($A$2:A191, A191)>1, "Dublet", "OK") -> OK
A192: 1jtym4e | B192: Sabrina | C192: Done | D192: That scar looks like the one left by the BCG (Bacille Calmette-Guérin) vaccine. It prevents tuberculosis. Many immigrants are seen with this scar. | E192: The meme begins with ICE asking, “are you Mexican,” followed by the reply “No.” Beneath that, the image compares a mark on someone’s skin with a suspicious facial expression labeled as ICE. | F192: ICE is shown as thinking someone is illegal just because they are Mexican which makes the whole thing feel racist and unfair. | G192: ICE does not only go after Mexicans. They target immigrants in general so it is bigger than just one group. | H192: The meme begins with ICE asking, “are you Mexican,” followed by the reply “No.” Beneath that, the image compares a mark on someone’s skin with a suspicious facial expression labeled as ICE. | I192: Dark Humor | J192: Exaggeration | K192: politics | L192: Social conventions | M192: =IF(COUNTIF($A$2:A192, A192)>1, "Dublet", "OK") -> OK
A193: 1l4x3e6 | B193: Sabrina | C193: Done | D193: They are implying a relationship between trumps youngest son, Baron, and elons daughter, Vivian, would end the petty squabbles and reunite the 2 fathers. | E193: If Putin’s daughter and Trump’s son got together, it would basically mean world peace. | F193: A tweet says there is a long-standing way to resolve current political tension and that the user should not have to spell it out. Below the text are two photos placed side by side, one of a young blonde woman and one of a young man in a suit. | G193: Trump’s son having a model girlfriend would make him happier and probably less awkward overall. | H193: A tweet says there is a long-standing way to resolve current political tension and that the user should not have to spell it out. Below the text are two photos placed side by side, one of a young blonde woman and one of a young man in a suit. | I193: Surprise | J193: Exaggeration | K193: politics | L193: Logical | M193: =IF(COUNTIF($A$2:A193, A193)>1, "Dublet", "OK") -> OK
A194: 1mahcad | B194: Sabrina | C194: Done | D194: penguin also happens to be the name of a chocolate bar p-p-pick up a penguin | E194: Penguins are tough animals, so eating one would obviously not be easy. | F194: Getting the wrapper off a Penguin bar is already hard for humans, so an elephant would have no chance. | G194: A small paper joke card is lying on a wooden table. The card asks, “Why don’t elephants like penguins?” and answers, “They can’t get the wrappers off.” | H194: A small paper joke card is lying on a wooden table. The card asks, “Why don’t elephants like penguins?” and answers, “They can’t get the wrappers off.” | I194: Wordplay | J194: Situational | K194: General knowledge | L194: meme | M194: =IF(COUNTIF($A$2:A194, A194)>1, "Dublet", "OK") -> OK
A195: 1j0n4gg | B195: Sabrina | C195: Done | D195: Loss of US support for zelenski and Ukraine means Russia and its allies will have a considerable advantage, this image depicts them revelling in this information. | E195: Men love gossip just as much as women do, they just pretend they do not. | F195: A four-panel phone-call meme shows three political leaders holding phones. The captions suggest that one leader asks if another is seeing something, then a third joins the call with a loud phone sound. | G195: When the tea is good enough, even men are calling their homeboys immediately. | H195: A four-panel phone-call meme shows three political leaders holding phones. The captions suggest that one leader asks if another is seeing something, then a third joins the call with a loud phone sound. | I195: Surprise | J195: Sarcasm/Irony | K195: politics | L195: meme | M195: =IF(COUNTIF($A$2:A195, A195)>1, "Dublet", "OK") -> OK
A196: 1hbogj4 | B196: Sabrina | C196: Done | D196: The United Health Care CEO shooter was recently apprehended in Pennsylvania in a McDonald’s after a tip was called in by another customer, contrary to the current belief that it was an employee. The meme is implying that the McDonald’s worker would also snitch on Anne Frank, who was hiding in an attic from the Nazis, because of the belief a McDonald’s employee snitched | E196: Comparing Anne Frank hiding from the Nazis to someone being murdered by a civilian from a major company makes no sense. Those two situations are nowhere near the same level. | F196: Anne Frank’s hiding place has become such a tourist spot now that there is even a McDonald’s nearby where people can ask for directions. | G196: A fast-food worker is shown smiling while holding a kitchen utensil. The text above her says, “Anne Frank? Yeah, she’s in the attic.” | H196: A fast-food worker is shown smiling while holding a kitchen utensil. The text above her says, “Anne Frank? Yeah, she’s in the attic.” | I196: Dark Humor | J196: Sarcasm/Irony | K196: politics | L196: Pop culture | M196: =IF(COUNTIF($A$2:A196, A196)>1, "Dublet", "OK") -> OK
A197: 1flb4nk | B197: Sabrina | C197: Done | D197: The show being referenced is the mockumentary Cunk on Earth, where the titular narrator humorously misinterprets history. The Romans left a lot from their history, including pottery fragments (which broke due to the long time period), which Cunk humorously says is caused by their clumsiness. | E197: A social media post shows a woman standing in front of ancient ruins. Below it, another post says that based on the amount of pottery fragments, the Roman Empire may have been the clumsiest empire in history. | F197: Materials have changed a lot since ancient times, so pottery today can last much longer than pottery from the Roman Empire. | G197: Someone probably broke the pottery on purpose just to mess with the Roman Empire. | H197: A social media post shows a woman standing in front of ancient ruins. Below it, another post says that based on the amount of pottery fragments, the Roman Empire may have been the clumsiest empire in history. | I197: Surprise | J197: Sarcasm/Irony | K197: History/Mythology | L197: Logical | M197: =IF(COUNTIF($A$2:A227, A197)>1, "Dublet", "OK") -> OK
A198: 1dhf9h2 | B198: Sabrina | C198: Done | D198: Donald Trump saying electric boats are heavy and will sink. You either get electrocuted by the battery or face a shark. | E198: There are not sharks everywhere in the ocean, so acting like the only options are “safe water” or “shark attack” is way too dramatic. | F198: A meme shows two politicians sitting on a couch, with one laughing while the other bends forward. Text above them says, “So there’s a boat, A battery and a shark 10 yards away.” | G198: It shows Hillary and Obama secretly plotting together to get rid of Trump. | H198: A meme shows two politicians sitting on a couch, with one laughing while the other bends forward. Text above them says, “So there’s a boat, A battery and a shark 10 yards away.” | I198: Surprise | J198: Comparison | K198: politics | L198: Social conventions | M198: =IF(COUNTIF($A$2:A198, A198)>1, "Dublet", "OK") -> OK
A199: 1c01lei | B199: Sabrina | C199: Done | D199: A British prime minister who the IRA tried to blow up. | E199: It looks like they are planning to bomb the non-binary person, which makes the situation feel way darker and more absurd than expected. | F199: Even when people travel back in time to warn them that the bomb will not kill Thatcher, they still do not seem to take it seriously. They are so focused on the plan that the warning barely matters to them. | G199: A time-machine meme compares girls, boys, and a non-binary person using a time machine. Each section shows a character giving advice to a group of masked men, with the group responding that they will do better. | H199: A time-machine meme compares girls, boys, and a non-binary person using a time machine. Each section shows a character giving advice to a group of masked men, with the group responding that they will do better. | I199: Dark Humor | J199: Exaggeration | K199: politics | L199: Logical | M199: =IF(COUNTIF($A$2:A199, A199)>1, "Dublet", "OK") -> OK
A200: 1d7u657 | B200: Sabrina | C200: Done | D200: To Kill a Mockingbird Story: In 1932 Alabama, a widowed lawyer with two small children defends a black man accused of raping a white woman. | E200: The image combines a social media post about believing rape victims with a black-and-white courtroom scene from an old film. Two men are seated in court while people watch from the background. | F200: The situation is wild because the widowed lawyer is still helping the man accused of rape, even though that same man is also connected to the death of his wife. It makes the scene feel morally twisted, since he is defending someone who has caused him personal harm. | G200: The point is that people often treat male victims with way more doubt, especially in cases involving sexual assault. The reaction becomes uncomfortable because it suggests that being taken seriously depends on gender rather than the actual situation. | H200: The image combines a social media post about believing rape victims with a black-and-white courtroom scene from an old film. Two men are seated in court while people watch from the background. | I200: Sarcasm/Irony | J200: Comparison | K200: politics | L200: Hobby | M200: =IF(COUNTIF($A$2:A200, A200)>1, "Dublet", "OK") -> OK
A201: 1dv83hh | B201: Sabrina | C201: Done | D201: It’s a stereotype that black peoples favorite alcoholic beverage is Hennessy, and if they didn’t ask or didn’t know his taste beforehand, this definitely comes off as racist but it doesn’t look like he’s complaining too terribly | E201: He is overreacting to the cake being chocolate, because he connects the brown color of the cake to his own skin color. In his mind, the choice of flavor feels way too targeted, even though it is probably just a normal cake. | F201: A tweet says the person’s job called them a slur “with the hardest ER.” Below the tweet is a photo of a chocolate cake topped with a bottle of Hennessy and a large blue bow. | G201: The image leans on an association between chocolate and dark skin. Because the cake is chocolate, he reads it as if his workplace is making a weird comment about him rather than simply giving him a dessert. | H201: A tweet says the person’s job called them a slur “with the hardest ER.” Below the tweet is a photo of a chocolate cake topped with a bottle of Hennessy and a large blue bow. | I201: Dark Humor | J201: Situational | K201: politics | L201: Social conventions | M201: =IF(COUNTIF($A$2:A201, A201)>1, "Dublet", "OK") -> OK
A202: 1cdufsh | B202: Sabrina | C202: Done | D202: Pot of greed was a bit broken simply because it was an automatic “draw 2 cards” without a downside. So lets say you start a game and have pot of greed, now you start with 6 cards instead of 5, if you had more pots of greed you could just continuously pull more cards to force the deck into giving you very strong cards/plays. There are some clips of people playing with no restrictions to show how broken the game could be, and you were essentially able to abuse pot of greed and other cards to win on round 1. | E202: This is clearly a troll version of the original image, where the child was holding a Kinder Egg. Here, it has been swapped out for a game card, which makes the message feel even more exaggerated and ridiculous. | F202: The image points out how strange it is to treat a game card as more dangerous than a gun. Playing games is obviously not on the same level as holding a firearm, which makes the comparison feel absurd. | G202: Two children are standing in a classroom. One child is holding a trading card, while the other is holding a large rifle. Text above them says that one child is holding something banned in America to protect them. | H202: Two children are standing in a classroom. One child is holding a trading card, while the other is holding a large rifle. Text above them says that one child is holding something banned in America to protect them. | I202: Sarcasm/Irony | J202: Comparison | K202: politics | L202: Hobby | M202: =IF(COUNTIF($A$2:A202, A202)>1, "Dublet", "OK") -> OK
A203: 13ibrc1 | B203: Sabrina | C203: Done | D203: Let’s start with the comic. The two shallow and wide glasses hold the same amount of liquid. The next panels you see the transfer of the liquid to the taller thin glass. The volume and quantity of the liquid remains the same. The third panel the child points to the taller glass. This whole set up is a standard test for the developmental level of a child. The goal is to tell which glass holds the most liquid. It’s commonly for young children to look at the glass and see that it’s taller and say that has the most liquid, simply because they lack the understanding to consider the width of the glass. This occurs even if you pour it right in front of them. So the comment from Lara Trump follows a similar logic. The red portion of the map outlines Republican districts, the blue outlines Democratic districts. She is implying that because the red covers the majority of the map, most of the country is Republican and therefor would be unable to impeach them. The comic is pointing out that although the red map covers more land than blue, it does not accurately convey the number of voters, because the blue districts hold the same or more of the population due to population density. | E203: A Reddit screenshot shows a tweet with a red-and-blue map of the United States and the text “Try to impeach this.” Under it, another user replies with a three-panel image of a child pouring liquid between containers. | F203: Trump’s daughter appears to be trolling people online by posting a map that makes it look like far more people voted for her dad. It comes across as a deliberately provocative post meant to annoy or bait people on X. | G203: She seems to have edited or presented the voting map in a way that makes it look much redder than it actually is. The image gives the impression that the results are being manipulated visually to support her point. | H203: A Reddit screenshot shows a tweet with a red-and-blue map of the United States and the text “Try to impeach this.” Under it, another user replies with a three-panel image of a child pouring liquid between containers. | I203: Comparison | J203: Sarcasm/Irony | K203: Logical | L203: politics | M203: =IF(COUNTIF($A$2:A203, A203)>1, "Dublet", "OK") -> OK
A204: 1m56k4v | B204: Sabrina | C204: Done | D204: Actually I don’t believe it is at all. People who take too much Benadryl sometimes report seeing a black figure with a hat that people call the “hat man.” It’s a frequent enough phenomena that I think there’s some medical studies or articles about him. | E204: A tweet says “Couples costume idea” above a photo of a smiling woman in a pink Benadryl shirt. Behind her, a person dressed entirely in black with a wide-brimmed hat is standing with their arms around her. | F204: Taking too much Benadryl is known for making people hallucinate, so the dark figure behind her is meant to look like something she would start seeing after using it. | G204: They are dressed like a couple’s costume, with her as Benadryl and the person behind her looking like Sherlock Holmes or some mysterious shadowy boyfriend. | H204: A tweet says “Couples costume idea” above a photo of a smiling woman in a pink Benadryl shirt. Behind her, a person dressed entirely in black with a wide-brimmed hat is standing with their arms around her. | I204: Surprise | J204: Incongruity | K204: Technical | L204: General knowledge | M204: =IF(COUNTIF($A$2:A204, A204)>1, "Dublet", "OK") -> OK
A205: 1mbrsfx | B205: Sabrina | C205: Done | D205: A guy retweeted this photo saying « I’m sorry for what United States did at Pearl Harbor ». The joke is that she’s looking good and the dude was a simp | E205: A photo shows a woman in a grey suit holding a black folder while standing indoors. The caption above says that seeing the picture as a man feels like getting hit in the chest with a sledgehammer. | F205: The guy first seems interested because he finds her attractive, but then he realizes she is trans and suddenly changes his mind | G205: He thinks she looks good at first, but then finds out she is his friend’s ex. That makes the whole thing awkward, because being into your homie’s ex is usually seen as crossing a line. | H205: A photo shows a woman in a grey suit holding a black folder while standing indoors. The caption above says that seeing the picture as a man feels like getting hit in the chest with a sledgehammer. | I205: Surprise | J205: Sarcasm/Irony | K205: meme | L205: Social conventions | M205: =IF(COUNTIF($A$2:A205, A205)>1, "Dublet", "OK") -> OK
A206: 1lnme9d | B206: Sabrina | C206: Done | D206: Diogenes is the most Philosopher ahead of his time, he literally didn't care about anyone or anything, and he proves his points in a very... creative ways once, he won an entire debate with some guy by just farting Poter out | E206: Socrates is usually seen as calm and patient, so his lack of reaction makes the scene even better. Something completely absurd is happening in front of him, but he just sits there as if this is a normal philosophical moment. | F206: The meme shows a close-up selfie of a bearded man sitting in a car. The text above says, “Socrates watching Diogenes piss himself to prove a point.” | G206: Socrates does not even want to argue with Diogenes because he has more important philosophy stuff to deal with. Diogenes is doing something ridiculous to prove a point, and Socrates basically looks like he has no time or energy for that kind of chaos. | H206: The meme shows a close-up selfie of a bearded man sitting in a car. The text above says, “Socrates watching Diogenes piss himself to prove a point.” | I206: Surprise | J206: Incongruity | K206: History/Mythology | L206: Social conventions | M206: =IF(COUNTIF($A$2:A206, A206)>1, "Dublet", "OK") -> OK
A207: 1lhnwl4 | B207: Sabrina | C207: Done | D207: The original was about a man working despite being armless while the begger got both arms but still refuse to do the harder work. The twist is that the begger is working as an undercover spy, so technically he is working. | E207: He is apparently a Russian spy, which makes the scene even more ridiculous. He is sitting there looking like he is begging, but then acts like it is all part of some secret mission. | F207: A cartoon shows a man sitting on the ground with a bowl, appearing to beg. Another man with no arms walks past carrying bricks and bags, with the text “Work bro, don’t beg...” The seated man replies, “I’m a spy, you fool!” | G207: He only says he is a spy to save his dignity. Instead of admitting that he is begging, he tries to make the situation sound intentional and mysterious. | H207: A cartoon shows a man sitting on the ground with a bowl, appearing to beg. Another man with no arms walks past carrying bricks and bags, with the text “Work bro, don’t beg...” The seated man replies, “I’m a spy, you fool!” | I207: Incongruity | J207: Surprise | K207: politics | L207: Logical | M207: =IF(COUNTIF($A$2:A207, A207)>1, "Dublet", "OK") -> OK
A208: 1lcutci | B208: Sabrina | C208: Done | D208: Americans' taxes are funding the ammunition of Iran and Israel, who are currently blaming and hurling explosives at each other | E208: People are crying because a war seems like it is about to break out. The situation feels tense, and everyone is reacting as if something terrible is coming. | F208: The population is scared because they think the bombs might hit them. They are basically stuck under the threat of violence, not knowing whether they are going to be next. | G208: The image shows missiles flying over a city at night. Text labels the missiles as “my tax dollars” and “somehow also my tax dollars,” while the bottom shows a man underwater with the caption “Americans.” | H208: The image shows missiles flying over a city at night. Text labels the missiles as “my tax dollars” and “somehow also my tax dollars,” while the bottom shows a man underwater with the caption “Americans.” | I208: Comparison | J208: Exaggeration | K208: politics | L208: Logical | M208: =IF(COUNTIF($A$2:A208, A208)>1, "Dublet", "OK") -> OK
A209: 1lmltqs | B209: Sabrina | C209: Done | D209: Think I found the original meme. It's the barcode of the Oreo and the person who decided to get this tattoo is half-black and half-white. It makes some sense I guess. | E209: It is silly to imagine that a barcode tattoo would actually scan like a real product. He puts his hand under the scanner as if the tattoo can be read and priced by the machine. | F209: A tweet says, “My brother wanted to show me his new tattoo.....” Below it, a hand is shown inside an orange store scanner, and the scanner screen displays the number “2.54.” | G209: It has that typical kid logic where children half-believe they can be sold because parents sometimes jokingly threaten them with it. The scanner showing a price makes it look like the brother is actually being treated as something for sale. | H209: A tweet says, “My brother wanted to show me his new tattoo.....” Below it, a hand is shown inside an orange store scanner, and the scanner screen displays the number “2.54.” | I209: Surprise | J209: Incongruity | K209: meme | L209: Logical | M209: =IF(COUNTIF($A$2:A209, A209)>1, "Dublet", "OK") -> OK
... A267: 1m0b8uv | B267: Sabrina | C267: Done | D267: The joke is that the people on the bottom are coming for the people on the top as if they're the enemy. But it's not a very good joke as it doesn't really make sense in terms of Squid Games. | E267: It is funny because this could honestly work as a Squid Game plot. | F267: It shows an upside-down world where the less fortunate finally get to eat the rich. | G267: A meme combines two images. The top image shows formally dressed people wearing gold animal masks, with labels such as “working class immigrants,” “teachers,” “consent laws including age,” and “the unemployed.” The bottom image shows a group of people in green tracksuits from a game-like setting, with labels including “Israel,” “venture capitalists,” “AI artists,” “Elon Musk,” and “Donald Trump.” | H267: A meme combines two images. The top image shows formally dressed people wearing gold animal masks, with labels such as “working class immigrants,” “teachers,” “consent laws including age,” and “the unemployed.” The bottom image shows a group of people in green tracksuits from a game-like setting, with labels including “Israel,” “venture capitalists,” “AI artists,” “Elon Musk,” and “Donald Trump.” | I267: Incongruity | J267: Comparison | K267: politics | L267: Pop culture | M267: =IF(COUNTIF($A$2:A267, A267)>1, "Dublet", "OK") -> OK
A268: 19994ey | B268: Sabrina | C268: Done | D268: I'm assuming the idea that someone would think it's a gunshot in that neighborhood is absurd. Edit: I think the idea is absurd *to OP*. I'm not making a judgement one way or another. | E268: It is a cannibalism joke implying that they always get “chicken” after the dad has killed someone. | F268: Pizza had not been invented yet, which is why the situation does not really make sense historically. | G268: A four-panel comic shows a man in a helmet and formal clothing on a battlefield. He returns home holding a cooked chicken and tells his children that he brought dinner. The children complain that they are having chicken again and ask why he does not bring pizza next time, while the man looks upset. | H268: A four-panel comic shows a man in a helmet and formal clothing on a battlefield. He returns home holding a cooked chicken and tells his children that he brought dinner. The children complain that they are having chicken again and ask why he does not bring pizza next time, while the man looks upset. | I268: Exaggeration | J268: Dark Humor | K268: politics | L268: General knowledge
A269: 18dba0l | B269: Sabrina | C269: Done | D269: The character is from the video game PUBG. After killing everyone else in the game you see a message saying “winner winner chicken dinner” | E269: It is funny because shotguns are treated as completely normal in the U.S. | F269: Since fireworks are illegal after New Year’s, it is obviously supposed to be gunshots. | G269: A meme shows a large suburban house with the caption, “Idk if those were gunshots or fireworks.” The image implies that the uncertainty is associated with this kind of neighborhood or setting. | H269: A meme shows a large suburban house with the caption, “Idk if those were gunshots or fireworks.” The image implies that the uncertainty is associated with this kind of neighborhood or setting. | I269: Wordplay | J269: Situational | K269: Hobby | L269: Logical | M269: =IF(COUNTIF($A$2:A269, A269)>1, "Dublet", "OK") -> OK
A270: 1lppcyj | B270: Naomi | C270: Done | D270: The kid is playing games on the school computer on coolmathgames.com, which has nothing to do with math. The teacher found out, approached the student and asked him to log out. The student knows he is in trouble. | E270: It is funny because you dont need to be logged into a account to play cool math games. | F270: Its funny because cool math games doesnt exist anymore. | G270: A high-contrast black-and-white image of a distorted, eerie humanoid face with a long neck and dark hollow eyes, captioned "When you're playing coolmathgames, then feel a hand on your shoulder and hear: 'Yeah, go ahead and log out for me, please.'" | H270: A high-contrast black-and-white image of a distorted, eerie humanoid face with a long neck and dark hollow eyes, captioned "When you're playing coolmathgames, then feel a hand on your shoulder and hear: 'Yeah, go ahead and log out for me, please.'" | I270: Situational | K270: General knowledge | M270: =IF(COUNTIF($A$2:A270, A270)>1, "Dublet", "OK") -> OK
A271: 1h066h6 | B271: Naomi | C271: Done | D271: It’s a honeypot cryptocurrency shitcoin. Basically the developers of the coin locked anyone from selling but themselves so it’s impossible for him to sell. | E271: A screenshot of a tweet from "Tony" (@0xRacist) captioned "Who's gonna tell him?" showing a candlestick chart with a steep upward trend in green, followed by text messages reading "Holy fuck bro I'm up like 10x already and it keeps going up" and "When do I sell?" | F271: Its because he actually isnt a net positive. | G271: IFirst-time trader discovers the y-axis. | H271: A screenshot of a tweet from "Tony" (@0xRacist) captioned "Who's gonna tell him?" showing a candlestick chart with a steep upward trend in green, followed by text messages reading "Holy fuck bro I'm up like 10x already and it keeps going up" and "When do I sell?" | I271: Situational | K271: Technical | M271: =IF(COUNTIF($A$2:A271, A271)>1, "Dublet", "OK") -> OK
A272: 1kjzy1y | B272: Naomi | C272: Done | D272: It's a play on words being names Me: Kill ogram\ Ogram: No, Pls, don't do it\ Pls: i was never going to\ i: It's True\ True: Yo, Gurt\ Gurt: Yo" | E272: A six-panel cartoon featuring characters with shirts labeled "Me," "pls," "ogram," "i," "true," and "gurt." In the first panel "Me" says "Kilogram" to "pls"; in the second "ogram" tells "pls" "No pls don't do it"; in the third "ogram" says "i was never going to" to "pls"; in the fourth "i" tells "true" "it's true"; in the fifth "true" says "yogurt" to "gurt"; in the sixth "gurt" says "yo" to "true." | F272: Word-association support group spirals out of control. | G272: A person is threatening his friend in a joking manner. | H272: A six-panel cartoon featuring characters with shirts labeled "Me," "pls," "ogram," "i," "true," and "gurt." In the first panel "Me" says "Kilogram" to "pls"; in the second "ogram" tells "pls" "No pls don't do it"; in the third "ogram" says "i was never going to" to "pls"; in the fourth "i" tells "true" "it's true"; in the fifth "true" says "yogurt" to "gurt"; in the sixth "gurt" says "yo" to "true." | I272: Wordplay | K272: General knowledge | M272: =IF(COUNTIF($A$2:A272, A272)>1, "Dublet", "OK") -> OK
A273: 1c341d5 | B273: Naomi | C273: Done | D273: Because it has no texture. | E273: It is the famous british dish checker pie. | F273: Photoshop's transparency layer, served piping hot. | G273: An image captioned "British cuisine. Best in the world." showing a pot with a wooden spoon, where the contents inside the pot have been replaced with a transparent checkerboard pattern. | H273: An image captioned "British cuisine. Best in the world." showing a pot with a wooden spoon, where the contents inside the pot have been replaced with a transparent checkerboard pattern. | I273: Exaggeration | K273: General knowledge | M273: =IF(COUNTIF($A$2:A273, A273)>1, "Dublet", "OK") -> OK
A274: 17930bw | B274: Naomi | C274: Done | D274: Je M‘appelle“ is french for „My name is“ Introducing herself she would say: „Bonjour Je M‘appelle Gemma Pell“ Which would sound like „Hello my name is my name is | E274: A screenshot of a Facebook profile for "Gemma Pell" featuring a profile picture of a woman with dark bobbed hair in a kitchen and a rocky landscape cover photo, captioned "Imagine the trouble she has trying to introduce herself in France" with a laughing-crying emoji. | F274: A meme about a terrible haircut. | G274: Parents who didn't think about phonetics before filing the birth certificate. | H274: Parents who didn't think about phonetics before filing the birth certificate. | I274: Wordplay | K274: General knowledge | M274: =IF(COUNTIF($A$2:A274, A274)>1, "Dublet", "OK") -> OK
A275: 1lfe3gp | B275: Naomi | C275: Done | D275: I think you typically see "the best of Japan" on social media but it's not as glamorous as it seems to live there. | E275: Everyone knows japan is the best country. | F275: Expat forums in a nutshell. | G275: A two-panel meme using the Tom and Jerry "angry Tom reading a book" template, with the top panel showing an open book reading "Japan is not a good country to live in," and the bottom panel showing Tom with a red, furious face holding the book, labeled "People who are not Japanese." | H275: A two-panel meme using the Tom and Jerry "angry Tom reading a book" template, with the top panel showing an open book reading "Japan is not a good country to live in," and the bottom panel showing Tom with a red, furious face holding the book, labeled "People who are not Japanese." | I275: Exaggeration | K275: politics | M275: =IF(COUNTIF($A$2:A275, A275)>1, "Dublet", "OK") -> OK
A276: 19dbf08 | B276: Naomi | C276: Done | D276: It’s a zen expression. Before enlightenment, chop wood, carry water. After enlightenment, chop wood, carry water. Here’s a good explanation from the internet: Before Enlightenment, you hate your life. You chop wood and carry water, but secretly wish to get out of it all. You bear with these activities through habit and out of hopelessness, but you really wish you could do something else. In a way, you are a victim, a slave - the wood chops you and the water carries you, and there is no way to escape. This could go for eternity, it is like living in eternal hell. After Enlightenment, you are in harmony with the universe. You realized the emptiness of it all, so you see that there is nothing more important than chopping wood and carrying water. All activities are equalized, there is no preference, no discrimination. Because there is no "you", no ego, no personality, no being, no separate individuality - there is no conflict. No need to escape. No other bank to be reached, no Nirvana to seek. But also, because you have mastered your mind, you are not chopped by the wood and carried by the water anymore. You can flip your perspective at will. It is your choice to chop wood and carry water, and you live it in complete suchness and spontaneity. You are beyond the beyond. And even beyond "beyond the beyond". | E276: Chop wood, carry water — the only thing that changed was the beard. | F276: A two-panel meme labeled "Before Enlightenment" and "After Enlightenment." Both panels contain the same thought bubble showing an illustration of a man chopping wood and a photo of a man carrying water buckets on a shoulder pole. The top panel shows a crying, distressed wojak in the shower; the bottom panel shows a calm, bearded wojak in the shower. | G276: No matter what you do life is still is the same. | H276: A two-panel meme labeled "Before Enlightenment" and "After Enlightenment." Both panels contain the same thought bubble showing an illustration of a man chopping wood and a photo of a man carrying water buckets on a shoulder pole. The top panel shows a crying, distressed wojak in the shower; the bottom panel shows a calm, bearded wojak in the shower. | I276: Sarcasm/Irony | K276: History/Mythology | M276: =IF(COUNTIF($A$2:A276, A276)>1, "Dublet", "OK") -> OK
A277: 1ly2yui | B277: Naomi | C277: Done | D277: Anything to the 0 power is 1 | E277: Evryone knows 20 is a made up age. | F277: A screenshot of a tweet from "Rubix" (@candy380) reading "I turn 20, my daughter turns 1 today / Look what my dad did:" above a photo of gold balloons shaped as "2" and "0" with the "0" smaller and floating higher to read as "2¹". Below is text "THE DAD:" followed by an image of a biblically-accurate angel with many eyes and outstretched arms surrounded by purple light. | G277: When grandpa moonlights as a math notation theologian. | H277: A screenshot of a tweet from "Rubix" (@candy380) reading "I turn 20, my daughter turns 1 today / Look what my dad did:" above a photo of gold balloons shaped as "2" and "0" with the "0" smaller and floating higher to read as "2¹". Below is text "THE DAD:" followed by an image of a biblically-accurate angel with many eyes and outstretched arms surrounded by purple light. | I277: Incongruity | K277: Technical | M277: =IF(COUNTIF($A$2:A277, A277)>1, "Dublet", "OK") -> OK
A278: 1bnyn39 | B278: Naomi | C278: Done | D278: Ya see, we had a mad lad named Steve Irwin that was really into hanging with crocs. He loved dangerous animals so much, he made the world love em too. But crikey, one day the lad was swimming and a skate got him right in the ol’ pumper. Didn’t last long after that But knowing Irwin, he’d want us to forgive the lil critter, after all, it was just doing what animals do | E278: Men love animals more than women do. | F278: A two-part meme labeled "Women with a time machine" showing two female cartoon characters where one says "I am your granddaughter" and the other responds "Really?", and "Men with a time machine" showing a bearded male cartoon character gently petting a stingray with the caption "It's okay buddy, he'd want us to forgive you." | G278: Gender differences in temporal priorities, illustrated. | H278: A two-part meme labeled "Women with a time machine" showing two female cartoon characters where one says "I am your granddaughter" and the other responds "Really?", and "Men with a time machine" showing a bearded male cartoon character gently petting a stingray with the caption "It's okay buddy, he'd want us to forgive you." | I278: Sarcasm/Irony | K278: Pop culture | M278: =IF(COUNTIF($A$2:A278, A278)>1, "Dublet", "OK") -> OK
A279: 1jczpuc | B279: Naomi | C279: Done | D279: Earlier this year a Chef posted a charcuterie board on r/KitchenConfidential that they had billed the customer $700 for. It was a bunch of basic raw vegetables, but featured a ramp and “carrot jacuzzi” where a lone olive reclined on top a sea of carrot pieces. The guy got laughed out of the sub and has become a meme. The board above was posted today asking how much they should charge for it. This is leagues better than the $700 board. Here’s today’s thread with links inside to the $700 board. ://www.reddit.com/r/KitchenConfidential/s/3kHdGIpxTf Edit: direct link to the $700 board | E279: A two-panel image. The top shows a large wooden charcuterie board piled with cheeses, cured meats, crackers, grapes, strawberries, dips, and jams on a dark table with wine glasses and breadsticks nearby. The bottom shows the "sweating Black man" reaction shot from the Key & Peele sketch, labeled "OP asking for business advice." | F279: The food us so dlecious is difficult to resist eating it. | G279: When the "side hustle starter pack" costs more than the side hustle earns. | H279: A two-panel image. The top shows a large wooden charcuterie board piled with cheeses, cured meats, crackers, grapes, strawberries, dips, and jams on a dark table with wine glasses and breadsticks nearby. The bottom shows the "sweating Black man" reaction shot from the Key & Peele sketch, labeled "OP asking for business advice." | I279: Sarcasm/Irony | K279: Hobby | M279: =IF(COUNTIF($A$2:A279, A279)>1, "Dublet", "OK") -> OK
A280: 1hy2gti | B280: Naomi | C280: Done | D280: That's thermal paste on his hand. He's building a PC, and using thermal paste is part of it. The graphics card in the background has a picture of Asuka from Neon Genesis Evangelion. There is an infamous frame from End of Evangelion where Shinji >!has semen on his hand after masturbating to Asuka.!<The framing of this image resembles this scene. | E280: He's trying to tell you the GPU is cooked, in interpretive sculpture. | F280: A screenshot of a tweet from "Maririn" (@TopGyaru) reading "Repair guy sent me this. What does it mean?" with an image of a hand holding up its palm, fingers covered in gray thermal paste, in front of a red GeForce RTX graphics card with an anime girl decal. | G280: Thermal paste hieroglyphics — translation pending. | H280: A screenshot of a tweet from "Maririn" (@TopGyaru) reading "Repair guy sent me this. What does it mean?" with an image of a hand holding up its palm, fingers covered in gray thermal paste, in front of a red GeForce RTX graphics card with an anime girl decal. | I280: Situational | K280: Hobby | M280: =IF(COUNTIF($A$2:A280, A280)>1, "Dublet", "OK") -> OK
A281: 1h53lb4 | B281: Naomi | C281: Done | D281: There's a joke about A freakishly strong, skinny, and tall individual called SCP-096 who doesn't like to be looked at, the joke is that he is shown in this photo (A whole 4 pixels) and after noticing said individual they will attempt to kill you. | E281: A screenshot of a Twitter post by Liv (@Liv_Agar) reading "Fun fact: there are four pixels in the background of this photo that will do something really cool when you notice them," quote-tweeting an earlier post captioned "Look before you leap!" with a photo of a smiling person in ski goggles, a helmet, and a black "Tsunami Hazard Zone" hoodie on a snowy mountain, with a small "Notice: Look Before You Leap" sign visible in the background. | F281: Internet sleuths assembling for the most underwhelming Where's Waldo of all time. | G281: Bait so transparent it qualifies as performance art. | H281: A screenshot of a Twitter post by Liv (@Liv_Agar) reading "Fun fact: there are four pixels in the background of this photo that will do something really cool when you notice them," quote-tweeting an earlier post captioned "Look before you leap!" with a photo of a smiling person in ski goggles, a helmet, and a black "Tsunami Hazard Zone" hoodie on a snowy mountain, with a small "Notice: Look Before You Leap" sign visible in the background. | I281: Dark Humor | K281: meme | M281: =IF(COUNTIF($A$2:A281, A281)>1, "Dublet", "OK") -> OK
... A318: 1iu9i31 | B318: Naomi | C318: Done | D318: A dude (i don't remember where) injected a moth into his vains and died in hospital Edit: it happened in Brazil, and it was a butterfly, not a moth | E318: Teenage curiosity, butterfly edition — with significantly worse consequences. | F318: "Is This a Pigeon?" anime meme showing a young man with glasses gesturing at a yellow butterfly. The man is labeled "14 year old boy," the butterfly is unlabeled, and the bottom caption reads "Is this INJECTABLE." | G318: That age where every unfamiliar object is one Google search from becoming a syringe trial. | H318: "Is This a Pigeon?" anime meme showing a young man with glasses gesturing at a yellow butterfly. The man is labeled "14 year old boy," the butterfly is unlabeled, and the bottom caption reads "Is this INJECTABLE." | I318: Dark Humor | K318: meme | M318: =IF(COUNTIF($A$2:A318, A318)>1, "Dublet", "OK") -> OK
A319: 1ftdy3c | B319: Sabrina | C319: Done | D319: "It's missing the punchline. The other muffin screams 'Oh my god, a talking muffin!'" | E319: The muffin is screaming because theyre in a hot oven | F319: Theyre screamin in the oven because theyre coming alive | G319: A photo shows a person holding a wrapped object or package with printed text on it. The visible text says, “Two muffins were sitting in an oven. One says ‘Geez, it’s hot in here.’ The other screams.” Above the photo, there is a caption that says, “what kind of joke is this.” | H319: A photo shows a person holding a wrapped object or package with printed text on it. The visible text says, “Two muffins were sitting in an oven. One says ‘Geez, it’s hot in here.’ The other screams.” Above the photo, there is a caption that says, “what kind of joke is this.” | I319: Surprise | J319: Sarcasm/Irony | K319: Logical | L319: Social conventions | M319: =IF(COUNTIF($A$2:A319, A319)>1, "Dublet", "OK") -> OK
A320: 1lt2euq | B320: Sabrina | C320: Done | D320: "Presumably it's referencing the stereotype that Americans are stupid and ignorant about even basic geography, so naming three countries would be enough of a challenge for them to eliminate a huge chunk of contestants." | E320: A screenshot shows a post stating that David Fincher’s American “Squid Game” series will reportedly begin filming in December in Los Angeles. Below the text, there is an image of two people standing in an urban setting. Under the image, another user comments, “First Game: Name three countries.” | F320: It would be too easy to name 3 countries, so there wouldn't be a challenge, and everyone wpuld win the game | G320: This is the first challenge in the TV show squid games. | H320: A screenshot shows a post stating that David Fincher’s American “Squid Game” series will reportedly begin filming in December in Los Angeles. Below the text, there is an image of two people standing in an urban setting. Under the image, another user comments, “First Game: Name three countries.” | I320: Exaggeration | J320: Sarcasm/Irony | K320: Pop culture | L320: Social conventions | M320: =IF(COUNTIF($A$2:A320, A320)>1, "Dublet", "OK") -> OK
A321: 1gp5i8t | B321: Sabrina | C321: Done | D321: "Its a joke about different workplace cultures in tech. Dell laptops would be a standard run of the mill company, MacBooks would be a start-up, thus if funding doesn't work out you'll get laid off, and a Thinkpad would be a sign of a large behemoth where you can comfortably exist for your whole career" | E321: It's based on the fact that most companies with MacBooks doesn't have a lot of money and the only reason they can afford to give their employees that, is because there aren't many employed. | F321: A screenshot of a post lists different laptop brands and what they supposedly imply about a new tech job. It says that receiving a Dell laptop means the employee has three warnings before being fired, receiving a MacBook means the job depends on the next funding round, and receiving a Lenovo ThinkPad means the employee will probably stay there for 28 years. | G321: It is based on a joke from friends where Ross has to buy a new computer | H321: A screenshot of a post lists different laptop brands and what they supposedly imply about a new tech job. It says that receiving a Dell laptop means the employee has three warnings before being fired, receiving a MacBook means the job depends on the next funding round, and receiving a Lenovo ThinkPad means the employee will probably stay there for 28 years. | I321: Exaggeration | J321: Sarcasm/Irony | K321: General knowledge | L321: Social conventions | M321: =IF(COUNTIF($A$2:A321, A321)>1, "Dublet", "OK") -> OK
A322: 1j6bl5f | B322: Sabrina | C322: Done | D322: "A lot of metal bands have logos that look like that." | E322: The image is a famous album cover | F322: It is a picture of a couch | G322: A meme says that metal fans describe this as their favorite band. Below the text, there is an image of cracked or peeling material on a wall or surface, forming shapes that resemble an unreadable extreme-metal band logo. | H322: A meme says that metal fans describe this as their favorite band. Below the text, there is an image of cracked or peeling material on a wall or surface, forming shapes that resemble an unreadable extreme-metal band logo. | I322: Comparison | J322: Exaggeration | K322: Hobby | L322: Pop culture | M322: =IF(COUNTIF($A$2:A322, A322)>1, "Dublet", "OK") -> OK
A323: 1iz5ool | B323: Sabrina | C323: Done | D323: He’s gonna die (and you with him in the plane crash) because some company or government agency doesn’t want that getting out. | E323: It is a new interesting innovation, so it is an honour to sit next to this person on the plane | F323: The man would be too rich to sit on the plane with you, so it is confusing | G323: A meme shows a man sitting on an airplane. The caption says that, as the plane took off, the person sitting to his left said they had created a car engine that runs on water instead of fuel. | H323: A meme shows a man sitting on an airplane. The caption says that, as the plane took off, the person sitting to his left said they had created a car engine that runs on water instead of fuel. | I323: Dark Humor | J323: Situational | K323: politics | L323: Technical | M323: =IF(COUNTIF($A$2:A323, A323)>1, "Dublet", "OK") -> OK
A324: 1kfloer | B324: Sabrina | C324: Done | D324: Dude stumbled upon a secret military installation. | E324: He is digging for wifi | F324: A screenshot of a post shows someone inside a cave with a phone displaying very fast internet speed. The text says they are lost in a cave after hiking for an hour, but the Wi-Fi is amazing. | G324: None of the above | H324: A screenshot of a post shows someone inside a cave with a phone displaying very fast internet speed. The text says they are lost in a cave after hiking for an hour, but the Wi-Fi is amazing. | I324: Surprise | J324: Incongruity | K324: Logical | L324: General knowledge | M324: =IF(COUNTIF($A$2:A324, A324)>1, "Dublet", "OK") -> OK
A325: 1l3sh3k | B325: Sabrina | C325: Done | D325: Leonardo is known for only dating women under the age of 25, so the joke is that his character in titanic would rather die than date a 25 year old | E325: Rose is too old to be a child in the Titanic movie, and can therefore not be saven in the childrens boat | F325: A meme says that it now makes sense that there was room for Jack on the door, but there was another problem. Below the text, a search result shows the age of the female character from Titanic as 26 years old. | G325: Titatic sunk in 1912 so she would be 100 years old | H325: A meme says that it now makes sense that there was room for Jack on the door, but there was another problem. Below the text, a search result shows the age of the female character from Titanic as 26 years old. | I325: Situational | J325: Sarcasm/Irony | K325: Pop culture | L325: Social conventions | M325: =IF(COUNTIF($A$2:A325, A325)>1, "Dublet", "OK") -> OK
A326: 1kbvz8k | B326: Sabrina | C326: Done | D326: There's an ongoing meme about throwing car batteries into the ocean (to charge the electric eels, of course) because AutoZone said you shouldn't. In this meme, he is training not to impress a woman, but rather to do the heavy task of throwing car batteries into the ocean for his grandma. | E326: Its a reference to a movie where a grandma goes crazy and make people throw batteries in the ocean. Th man is training to help the grandma with her plan | F326: A comic-style image shows a muscular man lifting a heavy weight while a woman asks whether he is training hard to impress her. He says no. In the lower panel, he tells an elderly woman that he will throw her old car battery in the ocean, and she responds affectionately. | G326: It is funny because it is illegal to throw car batteries in the ocean | H326: A comic-style image shows a muscular man lifting a heavy weight while a woman asks whether he is training hard to impress her. He says no. In the lower panel, he tells an elderly woman that he will throw her old car battery in the ocean, and she responds affectionately. | I326: Situational | J326: Incongruity | K326: General knowledge | L326: Social conventions | M326: =IF(COUNTIF($A$2:A326, A326)>1, "Dublet", "OK") -> OK
A327: 1llqmsk | B327: Sabrina | C327: Done | D327: "Time traveller, to the WWI Soldier: "Judging by the uniform, you're clearly a soldier from World War 1." The Soldier: "*What do you mean, **ONE**?!*"" | E327: "Time traveller, to the WWI Soldier: "Judging by the uniform, you're clearly a soldier from World War 1." The Soldier: "*What do you mean, **ONE**?!*"" | F327: The timetraveler failed to go back in time, and does not realize it, and therefore thinks the area has always gone by the same name. | G327: The joke is that it was never called that | H327: A screenshot of a post describes someone traveling 4000 years back in time and asking where they are. A person replies that they are in the Indus Valley Civilization. The time traveler then remarks that it is interesting that they call it that too. | I327: Surprise | J327: Sarcasm/Irony | K327: History/Mythology | L327: General knowledge | M327: =IF(COUNTIF($A$2:A327, A327)>1, "Dublet", "OK") -> OK
A328: 1i5ptep | B328: Sabrina | C328: Done | D328: Boys stereotypically find it cool when things break or are smashed. Therefore when the wife wasnt intereted he knew other men would like it. | E328: It is a commentary on marriage, when the wife doesnt understand his hobbies, he prefers to hang out with other men | F328: A post describes someone accidentally dropping a plate and being excited that it broke perfectly in half. Below the text, there is a photo of a round white plate split into two clean, symmetrical halves. | G328: The wife is annoyed because the man clearly broke the plate, but he wont tell her | H328: A post describes someone accidentally dropping a plate and being excited that it broke perfectly in half. Below the text, there is a photo of a round white plate split into two clean, symmetrical halves. | I328: Situational | J328: Comparison | K328: Social conventions | L328: General knowledge | M328: =IF(COUNTIF($A$2:A328, A328)>1, "Dublet", "OK") -> OK
A329: 1jwed8c | B329: Sabrina | C329: Done | D329: That image is the source of all of the doge memes | E329: A screenshot of a text post tells a short fictional story about a Japanese woman in 2010 taking photos of her Shiba Inu dog for her blog. A man from a time portal stops her and says he cannot let her do it because it is too stupid to explain. | F329: The joke doesnt refer to anything that has happened in real life, since the time traveler has stopped it from happening. | G329: Doge is a shiba inu dog | H329: A screenshot of a text post tells a short fictional story about a Japanese woman in 2010 taking photos of her Shiba Inu dog for her blog. A man from a time portal stops her and says he cannot let her do it because it is too stupid to explain. | I329: Surprise | J329: Situational | K329: meme | L329: Pop culture | M329: =IF(COUNTIF($A$2:A329, A329)>1, "Dublet", "OK") -> OK
A330: 1lavhpu | B330: Sabrina | C330: Done | D330: "Instant friendship unlocked: These countries get excited when they meet a foreigner who is trying to speak their language. Nice try.... but why bother: These countries languages are pretty difficult with their grammar and pronunciations, so it's like, we appreciate the effort, but it'll be easier for us to just speak in a language you already know how to speak. Cute but let's switch to English: Kind of the same as the last one with a bit of a sarcastic eye roll at hearing your attempt. No reaction: They're English speaking countries, you speak English. You already speak the same language as them so there's no reaction. PLEASE DON'T: France has a stereotype of being condescending and elitist, scoffing at foreigners who try to adopt their culture, and would try to shut down anyone trying to speak French and doing so poorly. Now, I don't know how true these are, but I'm just explaining the joke, not speaking on how accurate it is." | E330: The map shows how people of different countried stereotypically react when you speak their language, scandinavian people are known for stricly enforcing grammar rules, even for beginners, so they would prefer if you dont butcher the language, while the germans are known for their friendliness | F330: A map is depicted in different colors, indicating which languages are spoken there | G330: A map of Europe is titled “How people react when you try to speak their language.” Different countries are colored according to a legend with reactions such as “Instant friendship unlocked,” “Nice try... but why bother?”, “Cute but let’s switch to English,” “No reaction,” and “PLEASE DON’T.” | H330: A map of Europe is titled “How people react when you try to speak their language.” Different countries are colored according to a legend with reactions such as “Instant friendship unlocked,” “Nice try... but why bother?”, “Cute but let’s switch to English,” “No reaction,” and “PLEASE DON’T.” | I330: Exaggeration | J330: Comparison | K330: History/Mythology | L330: Social conventions | M330: =IF(COUNTIF($A$2:A330, A330)>1, "Dublet", "OK") -> OK
... A364: 1duiywi | B364: Sabrina | C364: Done | D364: This joke has two big parts the first part is the child doesn't understand the assignment, she misunderstands the comment about dividing X by 2, and she produces the variable C because of her handwriting. In some higher level mathematics such as calculus the variable C represents a range of numbers the exact one of which is unknown. This range includes the number 1 the answer for the specific problem. That leads us to the second part of the joke which is the child writing something that is mathematically well beyond her level (at graduate lever) and the teacher assessing it as the child being exceptionally intelligent and ready for graduation. It is a humorous juxtaposition of simple and profound and the results there of. | E364: She is graduating even though she still does not understand basic math rules. | F364: A four-panel comic shows a student working on a math problem involving the expression “If x = 2, x/2 =”. In the first panel, the student writes an incorrect answer, and the paper says, “No, we’re dividing x by 2. Try again.” In the second panel, the student erases part of the answer and writes again. In the lower-left panel, a teacher stands beside the student while the student continues writing at a desk. In the final panel, the student is shown as a very small child wearing a graduation cap and gown at a graduation ceremony. | G364: She is ready to graduate because there is apparently no point in keeping her in school if she still cannot divide properly. | H364: A four-panel comic shows a student working on a math problem involving the expression “If x = 2, x/2 =”. In the first panel, the student writes an incorrect answer, and the paper says, “No, we’re dividing x by 2. Try again.” In the second panel, the student erases part of the answer and writes again. In the lower-left panel, a teacher stands beside the student while the student continues writing at a desk. In the final panel, the student is shown as a very small child wearing a graduation cap and gown at a graduation ceremony. | I364: Incongruity | J364: Incongruity | K364: Technical | L364: Logical | M364: =IF(COUNTIF($A$2:A364, A364)>1, "Dublet", "OK") -> OK
A365: 1jzk0f2 | B365: Naomi | C365: Done | D365: The social media account managers for two brands are having a fake spat for publicity. Then a third unrelated brand joins in and ruins the artifice. | E365: The social media account managers for two horror franchises are having a staged argument to entertain fans, and then a third brand joins in as part of the same coordinated joke. | F365: The image shows real monsters arguing on Twitter, until an iced tea company interrupts their conversation by accident. | G365: None of the above | H365: The image shows real monsters arguing on Twitter, until an iced tea company interrupts their conversation by accident. | I365: Situational | K365: Pop culture | M365: =IF(COUNTIF($A$2:A365, A365)>1, "Dublet", "OK") -> OK
A366: 1l6ov5y | B366: Naomi | C366: Done | D366: "He resembles Zeke Yaeger. A character in Attack on Titan anime. Basically, if you drink his spinal fluid and he screams, you turn into a titan (monster in that anime). In the last season his spinal fluid was mixed with wine and people drank it unknowingly. Bad things happened after that" | E366: The joke comes from the man looking like a generic anime villain, with the caption exaggerating him as someone dangerous even though he is just an ordinary cashier. | F366: He resembles a character from Attack on Titan, and the joke is that drinking wine connected to him gives people supernatural powers, referencing how characters in the anime gain abilities through special substances. | G366: He is a famous chef who likes to give freebees | H366: He is a famous chef who likes to give freebees | I366: Situational | K366: Hobby | M366: =IF(COUNTIF($A$2:A366, A366)>1, "Dublet", "OK") -> OK
A367: 1d5bxcu | B367: Naomi | C367: Done | D367: "It's an old Reddit copy pasta that someone lived an entire fulfilling and successful life with a wife, kids, and house, until one day he realizes the perspective of his lamp is off. He later realizes the lamp is fake and his entire life is fake because he got tackled by a football player. The lamp grows and takes up the entire room before he wakes up on the pavement surrounded by people, EMS, and cops" | E367: Its a reference to the Truman show movie. The lamp probably broke and was replaced by the crew | F367: His wife has very bad taste in lamps, and he is only noticing it now | G367: Its a refernce to the youtube show Dont hug me im scared | H367: His wife has very bad taste in lamps, and he is only noticing it now | I367: Dark Humor | K367: meme | M367: =IF(COUNTIF($A$2:A367, A367)>1, "Dublet", "OK") -> OK
A368: 1fvg71d | B368: Naomi | C368: Done | D368: "First image is Villa Savoye built in 1931 in Poissy, France. A modern style building using that all the rage material reinforced concrete. Second image is Palais Garnier, an opera house built in 1875 in Paris France at the behest of Emperor Napoleon III the style is literally called Napoleon III. OOP likes the older style better and feels that newer buildings are appreciated for their advanced construction but are unable to capture the beauty of early styles." | E368: The image shows that ancient people literally invented modern buildings first, and todayï¿½s architects are stealing their exact designs and claiming them as new. | F368: The humor comes from a generational disagreement where older people simply dislike modern styles out of nostalgia, regardless of whether new designs are actually better. | G368: The Joke is that the old house was actually build first | H368: The image shows that ancient people literally invented modern buildings first, and todayï¿½s architects are stealing their exact designs and claiming them as new. | I368: Comparison | K368: History/Mythology | M368: =IF(COUNTIF($A$2:A368, A368)>1, "Dublet", "OK") -> OK
A369: 1j25t67 | B369: Naomi | C369: Done | D369: "He turned heel last night. Aka became a bad guy in wresting" | E369: Some new alligations towards John Cena came out | F369: Theres a common joke that John Cena doesnt like christmas | G369: The account is a parody | H369: The account is a parody | I369: Wordplay | K369: meme | M369: =IF(COUNTIF($A$2:A369, A369)>1, "Dublet", "OK") -> OK
A370: 1jipmfo | B370: Naomi | C370: Done | D370: The man dies later in the game | E370: The joke is that only experienced Pokï¿½mon players recognize this line as inefficient gameplay advice, since low-level Pokï¿½mon are harder to train and not worth taking care of. | F370: The humor comes from casual players not understanding Pokï¿½mon level systems, while veteran players overthink a harmless line of dialogue. | G370: The old man will steal the pokemon and become a villian | H370: The old man will steal the pokemon and become a villian | I370: Surprise | K370: Hobby | M370: =IF(COUNTIF($A$2:A370, A370)>1, "Dublet", "OK") -> OK
A371: 1fl51f0 | B371: Naomi | C371: Done | D371: "It signals that the car is driven by a gay couple looking for a big, hairy threesome partner" | E371: Its generally a bad idea to have custom made license plates | F371: The lady driving in from of OP, is presumably bad at driving and has caused an accident | G371: Its funny because its hard to read the license plate | H371: The lady driving in from of OP, is presumably bad at driving and has caused an accident | I371: Surprise | K371: Social conventions | M371: =IF(COUNTIF($A$2:A371, A371)>1, "Dublet", "OK") -> OK
A372: 1kxmxbf | B372: Naomi | C372: Done | D372: "Kamdyn is saying the person holding the photo is visible on the phone screen and is also comparing their stature to a tank. As to what tank she most resembles is up for our individual interpretation. I myself like the World War Two M4 Sherman tank." | E372: The joke is that the list exaggerates traditional dating expectations, and the comment points out that these standards are still obvious even when people try to disguise them as jokes. | F372: The humor comes from people arguing online about masculinity, with the comment mocking how seriously some users take a casual social media post. | G372: The image is about military tanks being visible in fog, and the list on the phone is unrelated background information. | H372: The image is about military tanks being visible in fog, and the list on the phone is unrelated background information. | I372: Exaggeration | K372: History/Mythology | M372: =IF(COUNTIF($A$2:A372, A372)>1, "Dublet", "OK") -> OK
A373: 1kpsba8 | B373: Naomi | C373: Done | D373: "Car salesman pretending to speak with his manager to get a better deal for the customer.. common salesman practice." | E373: The joke is that car dealerships have inefficient management structures, forcing salesmen to constantly check in with their managers before making decisions. | F373: The humor comes from mocking corporate office culture, where employees exaggerate how busy they are by pretending to make important phone calls. | G373: The image shows a man who cannot reach his manager on the phone and must try calling seven times in a row. | H373: The image shows a man who cannot reach his manager on the phone and must try calling seven times in a row. | I373: Situational | K373: Social conventions | M373: =IF(COUNTIF($A$2:A373, A373)>1, "Dublet", "OK") -> OK
A374: 1klgmos | B374: Naomi | C374: Done | D374: "Nothing wrong. It's just showing that the ISO 216 international standard for paper sizes, followed by most countries around the world, has a logic to it: Each format is built by halving the longer side of the format above. Take half of A0 and you get A1, halve it to get A2, halve it again to get A3, etc. The "joke" is that North America doesn't use these standards, and instead use a seemingly arbitrary list: and that perhaps they get offended when people point that out." | E374: Americans often hate european standards | F374: The image shows paper sizes | G374: Nothing is wrong | H374: The image shows paper sizes | I374: Exaggeration | K374: General knowledge | M374: =IF(COUNTIF($A$2:A374, A374)>1, "Dublet", "OK") -> OK
A375: 1jk2lgw | B375: Naomi | C375: Done | D375: His name is (East) Indian. I grew up with a ton of Indians. Whenever we had to answer what do you want to be when you grow up in school, all these kids had a) detailed answers, and b) straight, emotionless faces when answering. I don't think a single one of them got to choose their own adventure. | E375: The poster shared a weird an unique event that happened to them, the story went viral for being so weid | F375: The poster is talking about family and how theyre often very controlling | G375: Its about feeding your kids answers. | H375: The poster is talking about family and how theyre often very controlling | I375: Sarcasm/Irony | K375: meme | M375: =IF(COUNTIF($A$2:A375, A375)>1, "Dublet", "OK") -> OK
A376: 1jpmmd9 | B376: Naomi | C376: Done | D376: "They thought they were setting their alarm but it's their calculator." | E376: OP spent a lot of money on a night out, and is therefore very hung over, so they didnt wake up | F376: It shows someone being very bad at math and having to rely on a calculator to calcualte something very easy, thus showing they are not qualified for work | G376: OP accidentally set their alarm to 630 | H376: OP accidentally set their alarm to 630 | I376: Wordplay | K376: Social conventions | M376: =IF(COUNTIF($A$2:A376, A376)>1, "Dublet", "OK") -> OK
... A503: 1ijv4xn | B503: Naomi | C503: Done | D503: Beaver sees water Beaver hates the sound of running water Beaver says oh, absolutely not" with the rage of a thousand suns burning in his soul Beaver goes to build dam to stop the running water" | E503: A two-panel comic by @AbelBryanMedia titled "A Beaver's Instinct." The first panel shows a beaver looking at a flowing stream with a question mark above its head. The second panel zooms in on the beaver's face as it firmly declares, "Oh, absolutely not." | F503: Nature's busiest engineer rejecting a project before it has begun. | G503: A beaver consulting its blueprint and deciding the river fails inspection. | H503: A two-panel comic by @AbelBryanMedia titled "A Beaver's Instinct." The first panel shows a beaver looking at a flowing stream with a question mark above its head. The second panel zooms in on the beaver's face as it firmly declares, "Oh, absolutely not." | I503: Wordplay | K503: General knowledge | M503: =IF(COUNTIF($A$2:A503, A503)>1, "Dublet", "OK") -> OK

Sheet Lists
A1: Assigned | B1: Status | D1: Humor (Primary) | E1: Count Humor | F1: Mangler | G1: Mål | I1: Context (Primary) | J1: Count context | K1: Mangler | L1: Mål | N1: farvekode | O1: Antal billeder for style | P1: Antal billeder for context | R1: Picture annotations | S1: Name | T1: status | U1: Progress | V1: Mål
A2: Sabrina | B2: Not started | D2: Wordplay | E2: =COUNTIFS(Annotations!I:I,D2,Annotations!C:C,"Done") -> 62 | F2: =MAX(0,$G2-E2) -> 1 | G2: 63 | I2: Pop culture | J2: =COUNTIFS(Annotations!K:K,I2,Annotations!C:C,"Done") -> 64 | K2: =MAX(0,$L2-J2) -> 0 | L2: 56 | N2: 0-30% | O2: 0-21 | P2: 0-16 | S2: Sabrina | T2: Done | U2: =COUNTIFS(Annotations!B:B,A2,Annotations!C:C,"Done") -> 251 | V2: 250
A3: Naomi | B3: In progress | D3: Situational | E3: =COUNTIFS(Annotations!I:I,D3,Annotations!C:C,"Done") -> 63 | F3: =MAX(0,$G3-E3) -> 0 | G3: 63 | I3: meme | J3: =COUNTIFS(Annotations!K:K,I3,Annotations!C:C,"Done") -> 42 | K3: =MAX(0,$L3-J3) -> 14 | L3: 56 | N3: 31-74% | O3: 22-53 | P3: 17-40 | S3: Naomi | T3: Done | U3: =COUNTIFS(Annotations!B:B,A3,Annotations!C:C,"Done") -> 251 | V3: 250
B4: Done | D4: Comparison | E4: =COUNTIFS(Annotations!I:I,D4,Annotations!C:C,"Done") -> 65 | F4: =MAX(0,$G4-E4) -> 0 | G4: 63 | I4: Social conventions | J4: =COUNTIFS(Annotations!K:K,I4,Annotations!C:C,"Done") -> 65 | K4: =MAX(0,$L4-J4) -> 0 | L4: 56 | N4: 75%-100% | O4: 54-72 | P4: 41-56
D5: Exaggeration | E5: =COUNTIFS(Annotations!I:I,D5,Annotations!C:C,"Done") -> 63 | F5: =MAX(0,$G5-E5) -> 0 | G5: 63 | I5: Technical | J5: =COUNTIFS(Annotations!K:K,I5,Annotations!C:C,"Done") -> 57 | K5: =MAX(0,$L5-J5) -> 0 | L5: 56 | R5: Partner Annotations | S5: Name | T5: status | U5: Progress | V5: Mål
D6: Sarcasm/Irony | E6: =COUNTIFS(Annotations!I:I,D6,Annotations!C:C,"Done") -> 64 | F6: =MAX(0,$G6-E6) -> 0 | G6: 63 | I6: Hobby | J6: =COUNTIFS(Annotations!K:K,I6,Annotations!C:C,"Done") -> 58 | K6: =MAX(0,$L6-J6) -> 0 | L6: 56 | S6: Sabrina | T6: Done | U6: =COUNTIFS(PAnnotations!J:J,A2,PAnnotations!K:K,"Done") -> 0 | V6: 25
D7: Surprise | E7: =COUNTIFS(Annotations!I:I,D7,Annotations!C:C,"Done") -> 55 | F7: =MAX(0,$G7-E7) -> 8 | G7: 63 | I7: Logical | J7: =COUNTIFS(Annotations!K:K,I7,Annotations!C:C,"Done") -> 50 | K7: =MAX(0,$L7-J7) -> 6 | L7: 56 | S7: Naomi | T7: Done | U7: =COUNTIFS(PAnnotations!J:J,A3,PAnnotations!K:K,"Done") -> 25 | V7: 25
D8: Incongruity | E8: =COUNTIFS(Annotations!I:I,D8,Annotations!C:C,"Done") -> 59 | F8: =MAX(0,$G8-E8) -> 4 | G8: 63 | I8: General knowledge | J8: =COUNTIFS(Annotations!K:K,I8,Annotations!C:C,"Done") -> 55 | K8: =MAX(0,$L8-J8) -> 1 | L8: 56
D9: Dark Humor | E9: =COUNTIFS(Annotations!I:I,D9,Annotations!C:C,"Done") -> 71 | F9: =MAX(0,$G9-E9) -> 0 | G9: 63 | I9: politics | J9: =COUNTIFS(Annotations!K:K,I9,Annotations!C:C,"Done") -> 56 | K9: =MAX(0,$L9-J9) -> 0 | L9: 56 | R9: Secondary tags | S9: Name | T9: status | U9: Progress | V9: Mål
I10: History/Mythology | J10: =COUNTIFS(Annotations!K:K,I10,Annotations!C:C,"Done") -> 55 | K10: =MAX(0,$L10-J10) -> 1 | L10: 56 | S10: Sabrina | T10: Done | U10: =COUNTIFS(Annotations!$B$2:$B$505,"Sabrina",Annotations!$J$2:$J$505,"<>",Annotations!$L$2:$L$505,"<>") -> 251 | V10: 250
D11: I alt | E11: =SUM(E2:E9) -> 502 | F11: =500-E11 -> -2 | G11: =SUM(G2:G9) -> 504 | I11: I alt | J11: =SUM(J2:J10) -> 502 | K11: =500-J11 -> -2 | L11: =SUM(L2:L10) -> 504 | S11: Naomi | T11: Done | U11: =COUNTIFS(Annotations!$B$2:$B$505,"Naomi",Annotations!$J$2:$J$505,"<>",Annotations!$L$2:$L$505,"<>") -> 41 | V11: 250
C14: Fokusområde: | H14: Fokusområde:
C15: Wordplay, Sarcasm and Dark humor | H15: meme, politics, historie og hobby

Sheet Notes
A1: AI to use: look for performace gap i disse modeller | B1: Duplicates: slettet fra vores annotation ark | C1: inden vi analysere med AI | D1: Lektie til næste gang | E1: Spørgsmål
A2: GPT5 | B2: 1jfy6ms | C2: Når vi har ramt 500 billeder skal vi sørge for alt teksten er ensartet, dvs. enten punktum på alle eller ingen, fjerne indrykning, fjerne citationstegn, stort bogstav for alle sætninger etc. | D2: Find akademiske kilder 3-4 hver, kilderne skal være nuanceret (artikler, bøger m.m.) | E2: skal vi lave en komparativ analyse? Dvs. Skal vi sammenligne Fridas resultater med vores? Fx om vi kan sige om accuracy m.m.
A3: Claude 4.6 | B3: 1gz2i0o | C3: når man omdanner cvs til excel bliver nogle tegn underlige, det skal rettes | D3: Lav en kode som gør teksten ren i annotations
A4: Gemini 3 | B4: 1d6ho4f | C4: vi skal randomisere rækkefølgen af svarmulighederne | D4: En kode der randomisere svarene
A5: Open weight models | B5: 1gqh1c5 | C5: for literal: hvis det er none of the above så lav en ny og ellers så tag den der tættest på | D5: Have en klar outline
A6: Gemma 4 | B6: 1mfr9vy | D6: Skrive analyse delen
A7: Qwen3.5 | B7: 1j983b2
C8: Lav en sekundær tag til billederne | D8: Naomi: finish csv file and adjust frida code to run experiment
D9: Outline: Naomi (2 related work) Sabrina (3 data)
D10: Lav 25 partner annotations til hinandens random
D11: Skriv til desmond
D12: Sabrina: Lav secondary tags til billederne
D13: Sabrina: Lav progress for partner annotation

Sheet Definitions
A1: Context definitions | B1: How to use them correctly | C1: Examples | D1: Humor style definitions | E1: How to use them correctly | F1: Examples
A2: popculture | B2: Requires knowledge of widely known media, celebrities, movies, music, or mainstream entertainment. | C2: This is me waiting like Harry Potter for my letter
A3: Meme | B3: Requires familiarity with a specific internet meme format or template. | C3: “This is fine.” (dog sitting in a burning room)
A4: Social conventions | B4: Requires understanding of social norms, roles, or expected behavior between people. | C4: Saying ‘you too’ to the waiter when they say enjoy your meal.
A5: Technical | B5: Requires specialized or domain-specific knowledge (e.g. programming, science, psychology). | C5: Fixing a bug by commenting out the code.
A6: Hobby | B6: Requires insider knowledge of a niche interest or community (e.g. Warhammer, fishing). | C6: Only Warhammer players know this pain…
A7: Logical | B7: Requires understanding of reasoning, logic, or a flawed/absurd conclusion. | C7: If tomatoes are fruit, then ketchup is a smoothie.
A8: General knowledge | B8: Requires broad, common knowledge about the world that most people are expected to know. | C8: Nokia phones never break
A9: Politics | B9: Requires knowledge of political systems, conflicts, ideologies, or current affairs. | C9: Russia taking land like my neighbor taking my parking spot.
A10: History/Mythology | B10: Requires knowledge of historical events, figures, or mythological stories. | C10: Medusa turning men to stone
A13: sarcasm/Irony
A14: Wordplay/rhymes
A15: Social/Cultural Norms.

Sheet PAnnotations
A1: File | B1: Assigned_to | C1: Status | D1: Correct answer | E1: Literal_Description | F1: Humor Style | G1: Humor style secondary | H1: Contextual Knowledge | I1: Contextual Knowledge secondary | J1: Partner name | K1: Status | L1: Partner: Humor Style | M1: Partner: Humor style secondary | N1: Partner: Contextual Knowledge | O1: Partner: Contextual Knowledge secondary | P1: Duplicate check
A2: 1actpx8 | B2: Sabrina | C2: Done | D2: the meme refers to cloudy and a chance of meatballs (movie): the main character is a scientist and sprayed on shoes when he was a kid, which he could never remove | E2: a snapchat picture showing a person holding a can of Flex Seal and their foot covered in a black substance, with the text ‘Flex seal shoe’ with the text underneath: "did the tales of falling meatballs not weigh on thine conscious". | F2: Sarcasm/Irony | H2: Hobby | J2: Naomi | K2: Done | L2: Sarcasm/Irony | M2: Situational | N2: Hobby | O2: Pop culture | P2: =IF(COUNTIF($A$2:A2, A2)>1, "Dublet", "OK") -> OK
A3: 1af8odu | B3: Sabrina | C3: Done | D3: A teller is a person who works at the front desk of a bank. Teller is also a person's name; that person is one half of the magician duo Penn & Teller. On stage, Teller doesn't speak. Penn is the one who explains everything/talks to the crowd. The joke is that you expect the robber to be speaking to a bank teller. But he's actually speaking to the magician Teller who doesn't talk. That's why Penn comes in at the end to explain what's going on. | E3: A tweet-style image shows a fictional dialogue where a bank robber repeatedly asks a teller where the safe is. The teller gives no visible response, and the robber becomes confused. The final line says, “PENN: He always does this,” implying the teller is the magician Teller, who is known for staying silent. | F3: Wordplay | H3: Pop culture | J3: Naomi | P3: =IF(COUNTIF($A$2:A3, A3)>1, "Dublet", "OK") -> OK
A4: 1ajzxfm | B4: Sabrina | C4: Done | D4: It’s kind of a weird joke that doesn’t make perfect sense, but here’s the intended meaning: 1. Many people might see something like 50/50 odds leading to 20 successes in a row and think the next one is more likely to be a failed surgery. Like how many people could flip a coin and get heads twice in a row, and be more likely to guess the next coinflip would be tails. Hence the nervous face. 2. A statistician would know that the success rate of each surgery is independent of all the other ones, so they wouldn’t be especially nervous theirs would go wrong. 3. A scientist might see 20 successes in a row for a surgery with a 50% survival rate and think “wow, this doctor must be really good at doing surgeries” | E4: A meme with text describing a doctor stating that a surgery has a 50% survival rate and that the last 20 patients survived. Below the text are three panels labeled ‘Normal people’, ‘Mathematician’, and ‘Scientist’, each showing a different face reacting to the statement. | F4: Comparison | H4: Logical | J4: Naomi | P4: =IF(COUNTIF($A$2:A4, A4)>1, "Dublet", "OK") -> OK
A5: 1amtoff | B5: Sabrina | C5: Done | D5: Amazon does not hire 12 year olds, and 12 year olds cannot drive. The potential panic this may cause whomever at Amazon, is hilarious. | E5: A screenshot of a social media thread where a user says that Amazon hired their 12-year-old son, followed by a response from an Amazon customer service account asking for clarification, and a subsequent reply stating that the son is one of their drivers | F5: Incongruity | H5: General knowledge | J5: Naomi | K5: Done | L5: Incongruity | M5: Sarcasm/Irony | N5: General knowledge | O5: politics | P5: =IF(COUNTIF($A$2:A5, A5)>1, "Dublet", "OK") -> OK
A6: 1aoxsw3 | B6: Sabrina | C6: Done | D6: Deer run in circles as a defense mechanism against predators ants run in circles because an ant has to turn around & left a pheromone trail in a circle, so the ants will die. it’s very sad. | E6: “A meme with the caption ‘Animals running in circles is so cool’ at the top, followed by two images of animals arranged in circular formations. Below the images are two panels with illustrated faces, labeled ‘Deers’ on the left and ‘Ants’ on the right, each showing a different facial expression.” | F6: Situational | H6: Technical | J6: Naomi | P6: =IF(COUNTIF($A$2:A6, A6)>1, "Dublet", "OK") -> OK
A7: 1asrnb3 | B7: Sabrina | C7: Done | D7: The black car is the Impala (aka “Metallicar”/“Baby”) from *Supernatural*, a show about two brothers who hunt down paranormal phenomena like ghosts, demons, etc. The Mystery Machine, of course, is Scooby Doo and the Scooby Gang, who hunt down ghosts and other various monsters. If they’re both in the same place, some haunted stuff is going down. | E7: A meme with the text “oh this place is HAUNTED haunted” at the top, showing a black car parked in front of a colorful van resembling the Scooby-Doo “Mystery Machine” in a parking lot. | F7: Incongruity | H7: Pop culture | J7: Naomi | P7: =IF(COUNTIF($A$2:A7, A7)>1, "Dublet", "OK") -> OK
A8: 1aya611 | B8: Sabrina | C8: Done | D8: Alabama ruled that frozen embryos count as live children, so this couple is claiming their 3 live children and 5 frozen embryos as 8 total children for tax purposes | E8: A meme showing a couple sitting in an office labeled “Tax Services,” speaking to a man behind a desk. One person says “We’re claiming 8 kids…” and the other adds “3 at home and 5 in the lab.” | F8: Sarcasm/Irony | H8: Social conventions | J8: Naomi | P8: =IF(COUNTIF($A$2:A8, A8)>1, "Dublet", "OK") -> OK
A9: 1b03bqv | B9: Sabrina | C9: Done | D9: we's making up states to mess em up badly | E9: A map of the United States showing state borders, with one state highlighted in yellow and a caption asking viewers to identify it. | F9: Incongruity | H9: politics | J9: Naomi | P9: =IF(COUNTIF($A$2:A9, A9)>1, "Dublet", "OK") -> OK
A10: 1b7unh0 | B10: Sabrina | C10: Done | D10: He would probably also be confused why they had built a second Memphis | E10: A meme divided into two sections labeled “Women with a time machine” and “Men with a time machine.” The top shows a woman pointing a gun at Henry Ford. The bottom shows a man speaking to an ancient Egyptian figure in front of a pyramid, with text about a modern glass pyramid in Memphis containing a Bass Pro Shop. | F10: Comparison | H10: Logical | J10: Naomi | K10: Done | L10: Comparison | M10: Exaggeration | N10: Logical | O10: History/Mythology | P10: =IF(COUNTIF($A$2:A10, A10)>1, "Dublet", "OK") -> OK
A11: 1be8p2s | B11: Sabrina | C11: Done | D11: It's a football thing Hosted in Brazil, best international team historically and huge favourites to win, they crashed out the tournament to Germany with a 7-1 loss. One of the most shocking results in football. Brazilian fans did not take the loss well. | E11: A meme with text at the top reading “Teacher: what is 7-1? Me: 6 My Brazilian classmates:” followed by an image of people wearing yellow shirts reacting emotionally in what appears to be a stadium setting. | F11: Incongruity | H11: Pop culture | J11: Naomi | P11: =IF(COUNTIF($A$2:A11, A11)>1, "Dublet", "OK") -> OK
A12: 1bikyy1 | B12: Sabrina | C12: Done | D12: The math is a little off, but the gist of it is that the grand canyon took a long *long* time to get to its current state, but, at some point in the very distant past, it would've started out as a small stream, as depicted in the meme. So, the joke is that the Flintstones were around a long time ago when the Grand Canyon was still just a little stream. | E12: A meme with the text “So that's the Grand Canyon, huh?” followed by “– The Flintstones,” showing a cartoon scene of characters standing near a narrow canyon with a small stream running through it. | F12: Incongruity | H12: Hobby | J12: Naomi | K12: Done | L12: Incongruity | M12: Surprise | N12: Hobby | O12: Technical | P12: =IF(COUNTIF($A$2:A12, A12)>1, "Dublet", "OK") -> OK
A13: 1bl3eve | B13: Sabrina | C13: Done | D13: Been a while since I read the books but basically, phones attract monsters for some reason, so Demigods don’t carry them around. | E13: A screenshot of a social media post referencing Percy Jackson using an iPod to fight Medusa, accompanied by two images: one of a character holding a device and another showing Medusa’s reflection in the device. Below, a reply comments that it is funny because they did not have phones. | F13: Incongruity | H13: Hobby | J13: Naomi | P13: =IF(COUNTIF($A$2:A13, A13)>1, "Dublet", "OK") -> OK
A14: 1bmtc5u | B14: Sabrina | C14: Done | D14: He likes big butts and he cannot lie. | E14: A black-and-white cartoon of a courtroom scene where a judge asks a witness to swear to tell the truth. The witness, a woman standing at the stand, responds that it will not be necessary. Several people are seated in the courtroom observing the exchange. | F14: Incongruity | H14: Social conventions | J14: Naomi | K14: Done | L14: Situational | M14: Incongruity | N14: Pop culture | O14: Social conventions | P14: =IF(COUNTIF($A$2:A14, A14)>1, "Dublet", "OK") -> OK
A15: 1bsdc0l | B15: Sabrina | C15: Done | D15: The Romans did not like the Germanic Tribes at all. It was in fact the Germanic Tribes that were an important factor in the downfall of the empire Edit: What I have just said is basically a CliffNotes explanation of what really happened. Was obviously more complicated than this but this is the gist of it | E15: A meme titled “Bringing Romans forward in time,” divided into two sections labeled “Expectation” and “Reality.” The top section shows a Roman figure reacting to a modern helicopter alongside a modern character making a dismissive comment. The bottom section shows a Roman figure speaking, with text referencing Germans. | F15: Comparison | H15: History/Mythology | J15: Naomi | P15: =IF(COUNTIF($A$2:A15, A15)>1, "Dublet", "OK") -> OK
A16: 1bw9tb7 | B16: Sabrina | C16: Done | D16: Labs test lipsticks and other cosmetics on mice before opening them to the human market. The process probably involves autopsying the mice to see if any toxic chemicals from the product have entered the liver. | E16: A four-panel comic showing mice in a cage. In the first panels the mice ask where they are being taken and speculate that they are going to a laboratory to test lipstick, expressing excitement. In the final panel, a person in a lab coat is shown carrying the cage in a laboratory setting. | F16: Comparison | H16: General knowledge | J16: Naomi | P16: =IF(COUNTIF($A$2:A16, A16)>1, "Dublet", "OK") -> OK
A17: 1c1tpnf | B17: Sabrina | C17: Done | D17: It's a meme from r/anarchychess, where "Google En Passant" comes from. They're acting as if this is a way to cheat at chess, because it lets you see the other player's pieces. In a lot of card games like Poker this would be a genuine advantage, but I'm Chess the point is you can see the other player's pieces. The joke is OOP pretending not to get that. The two people are big famous competitive chess players. The brick is a reference to the joke on r/anarchychess that the move "En Passant" is forced. If you decline En Passant, that is if you could have taken the move but didn't, you are punished by your pipi being bricked, aka your penis being crushed by a brick. | E17: A simple drawing showing two stick figures labeled Magnus Carlsen and Hans Niemann sitting at a table playing chess. Above them is a mirror on the ceiling, with dashed lines indicating a line of sight from the mirror to the player. | F17: Incongruity | H17: Logical | J17: Naomi | P17: =IF(COUNTIF($A$2:A17, A17)>1, "Dublet", "OK") -> OK
A18: 1c6zoan | B18: Sabrina | C18: Done | D18: That's a (slightly edited) picture of Todd Howard, the director, executive producer, and public spokesperson for Bethesda Games. He lead development on all the Elder Scrolls games (Skyrim), Starfield, and Fallout 3, 4, and 76. Recently the Fallout TV series was released and it featured an event that happened in one of the endings of "Fallout New Vegas," a game published but *not developed* by Bethesda. But the event in question happens in different years in each of New Vegas and the TV show. Because of this Todd was asked recently whether New Vegas or the TV show is canon to the series at large, and if New Vegas is, which ending. His response was "all of Fallout is canon." Which doesn't really answer any questions or make sense. | E18: A screenshot of a social media post showing a dialogue about inconsistencies in a fictional storyline, mentioning “Todd” and “New Vegas,” followed by a repeated response stating “All of it.” Below the text is an image of Todd. | F18: Incongruity | H18: Pop culture | J18: Naomi | K18: Done | L18: Incongruity | M18: Situational | N18: Pop culture | O18: Hobby | P18: =IF(COUNTIF($A$2:A18, A18)>1, "Dublet", "OK") -> OK
A19: 1c22s8b | B19: Sabrina | C19: Done | D19: Joji is filthy frank (the guy in the left) made content on YouTube that was very unusual. I highly suggest watching it cause a lot of memes came from him. Now he makes chill music and all ties to the character are cut. Miss papa franku | E19: A screenshot of a social media post showing text at the top referencing going back in time, followed by a repost of an older post by H3h3productions. The post includes a photo of four people posing in a kitchen, with one person crouching in front and the others standing behind. | F19: Incongruity | H19: Pop culture | J19: Naomi | P19: =IF(COUNTIF($A$2:A19, A19)>1, "Dublet", "OK") -> OK
A20: 1c175gf | B20: Sabrina | C20: Done | D20: It's basically about how nuclear energy is almost universally despised by environmentalists despite it being extremely clean and reliable source of energy. | E20: A four-panel comic showing characters engaged in a tug-of-war. The first panel shows a character labeled “Pro Nuclear” pulling a rope. In the second panel, a character labeled “Climate Change Deniers” joins on the same side. In the third panel, characters labeled “Climate Change Activists” and “Oil & Coal Companies” appear on the opposite side. In the final panel, the “Pro Nuclear” character looks confused and says “Huh?” | F20: Sarcasm/Irony | H20: Logical | J20: Naomi | P20: =IF(COUNTIF($A$2:A20, A20)>1, "Dublet", "OK") -> OK
A21: 1ccfha2 | B21: Sabrina | C21: Done | D21: The man in the top picture admitted in court that he pointed a gun at another person | E21: A meme showing two courtroom images. The top image shows a man in a suit speaking in a courtroom setting, while the bottom image shows another man sitting and covering his face with his hand. The caption reads: “My attorney, after hearing me turn my jaywalking charge into a death penalty case.” | F21: Incongruity | H21: politics | J21: Sabrina | P21: =IF(COUNTIF($A$2:A21, A21)>1, "Dublet", "OK") -> OK
A22: 1cehmmt | B22: Naomi | C22: Done | D22: He looks very much like Hugh Laurie. | E22: It is a screeshot of an internet article with the title of "Russian Plumber Doesn't Know Why People Stare At Him On The Street" the phot below the caption shows a middle aged caucasian male with a tired expression. | F22: Situational | H22: Pop culture | J22: Sabrina | P22: =IF(COUNTIF($A$2:A22, A22)>1, "Dublet", "OK") -> OK
A23: 1cgcw31 | B23: Naomi | C23: Done | D23: Its a reference to a trend on TikTok where people will ask women if they would feel safer being alone in the woods with a bear or a random man and they almost always choose the bear. Basically the idea is that the bear will be pretty much harmless if you leave it alone vs a man could have nefarious intent with no provocation. | E23: It shows a man speaking with the caption "if you don't understand why women are choosing the bear... you are probably part of the reason they are choosing the bear"and the llama reacting with a gaping sigh. | F23: Exaggeration | H23: Pop culture | J23: Sabrina | P23: =IF(COUNTIF($A$2:A23, A23)>1, "Dublet", "OK") -> OK
A24: 1jfy6ms | B24: Naomi | C24: Done | D24: Whitney Houston had a song called "Im every woman" | E24: A screenshot of a twitter interaction between a woman and a man with the LGBTQ flag in his profile having a cinversation about feminism | F24: Wordplay | H24: Pop culture | J24: Sabrina | P24: =IF(COUNTIF($A$2:A24, A24)>1, "Dublet", "OK") -> OK
A25: 1eae89f | B25: Naomi | C25: Done | D25: In one possible ending of Bloodborne, the protagonist becomes an eldritch squid creature. | E25: It shows a line of somber men walking in a single file line into a an upside cover of the game Bloodborne and leaving the other side of the cover is a line of squids. | F25: Exaggeration | H25: Hobby | J25: Sabrina | P25: =IF(COUNTIF($A$2:A25, A25)>1, "Dublet", "OK") -> OK
A26: 1iw42ka | B26: Naomi | C26: Done | D26: Grimes met Elon Musk at Met gala 2018 , leading to their relationship . Many people believe things would have been better if Grimes and Musk had never met . | E26: It is a screeenshot of a tweet showing a meme with the top portion titled "Boys with the time Machine" and one male face saying "im your grandson" and he other one replies "wow" the lower portion of the meme is titled "Girls with the time machine" and a group of females speaking to a photo of Grimes with the caption "do not go to the 2018 Met Gala" | F26: Exaggeration | H26: Pop culture | J26: Sabrina | P26: =IF(COUNTIF($A$2:A26, A26)>1, "Dublet", "OK") -> OK
A27: 1k4fjdr | B27: Naomi | C27: Done | D27: Wish #1 is to wish the genie does the opposite of what he asks in wish #2 Wish #2 is to not grant wish #3 (which since Wish #1 was do the opposite, it means the genie must grant wish #2 as 'do grant wish #3). Wish #3 is cancel wish #1, which is to do the opposite of wish #2, which as established is to make the genie grant wish #3, which causes wish #2 to not be opposite, which means that genie can't grant wish #3, which means wish #1 can't be cancelled, which means, genie needs to do the opposite of "don't do wish #3", which means, the genie must cancel wish #1, which means wish #2 becomes "don't grant wish #3", thus stopping "cancel wish #1" from happening, which means wish #2 won't grant wish #3, which means wish #1 gets cancelled, which means, wish #2 must cancel wish #3, which means wish #1 doesn't get cancelled... | E27: A four-panel comic followed by an image of a mushroom cloud, depicting a man using his three wishes from a genie to create a logical paradox by asking for the opposite of the second wish, the denial of the third wish, and the cancellation of the first. | F27: Wordplay | H27: Logical | J27: Sabrina | P27: =IF(COUNTIF($A$2:A27, A27)>1, "Dublet", "OK") -> OK
A28: 1l4mpmj | B28: Naomi | C28: Done | D28: "He liked her body so much he did not realise where he was walking" | E28: A screenshot of a social media thread where a user shares a photo of a woman with a highly exaggerated curvy silhouette asking if men "really like this," followed by a quote-post from another user claiming he once walked into a rack of stuffed animals after seeing someone with that build. | F28: Situational | H28: Social conventions | J28: Sabrina | P28: =IF(COUNTIF($A$2:A28, A28)>1, "Dublet", "OK") -> OK
A29: 1k0el7w | B29: Naomi | C29: Done | D29: "In one of Metal Gear Solid games there was a boss called Psychomantis which messed up with your consol and one of the things the boss does is disabling your first pad port. Since the pad is connected to port 2 the person is fighting with Psychomantis" | E29: A meme featuring text about "gamers" being able to identify a specific video game boss by looking at a console, paired with a photo of a PlayStation 1 with its controller plugged into the second port | F29: Situational | H29: Hobby | J29: Sabrina | P29: =IF(COUNTIF($A$2:A29, A29)>1, "Dublet", "OK") -> OK
A30: 15h4szq | B30: Naomi | C30: Done | D30: In Platos republic, Plato argues that the best society is one in which a astiorcratic elite who have spent their whole lives training and learning the art of statecraft should be the rulers. The idea is that if someone has been trained in the art of statecraft and philosophy from birth they will be the idea ruler or "philosopher king" who seeks council from other who are skilled in their professions. Super simplified, in an ideal world, people would fulfil a specific role and be happy about it. In Barbie, each of the Barbies holds a specific role they were created for, their ruler rules and does so well, because they were created to rule. The Barbies are happy about it. You could argue it looks like Platos ideal republic | E30: A two-panel meme that humorously labels the 2023 Barbie movie poster as "the anime" and the cover of Plato's The Republic as "the manga," satirizing the common gatekeeping trope that one cannot appreciate an adaptation without reading its "source material." | F30: Comparison | H30: History/Mythology | J30: Sabrina | P30: =IF(COUNTIF($A$2:A30, A30)>1, "Dublet", "OK") -> OK
... A44: 1cwrltm | B44: Sabrina | C44: Done | D44: Cuz if a person is in danger and wants to call 911 but they don't want the person they are with to know they are calling 911, presumably because that person *is* the danger, they can pretend they are ordering a pizza and the 911 dispatcher will know to send police. The dispatcher can ask yes or no questions and the caller can answer while still pretending they are ordering a pizza. That is a picture of moistcritikal. | E44: A screenshot of a social media post with the headline “POV: I’m telling my wife what I want on the pizza she’s ordering but I hear her only dial 3 numbers” at the top, followed by an image of a man with long hair sitting indoors looking unamused. | F44: Incongruity | H44: Pop culture | J44: Naomi | P44: =IF(COUNTIF($A$2:A44, A44)>1, "Dublet", "OK") -> OK
A45: 1cym2ue | B45: Sabrina | C45: Done | D45: There are already many great answers here, but I’d like to add an interesting example involving Deadmau5. He bought a Ferrari 458 Spider and heavily modified it, even replacing the Ferrari emblem with a “Purrari” logo. This led to Ferrari suing him over the modifications. Interestingly, Lamborghini later offered him a Huracan with a Nyan Cat wrap as a playful response to the situation! | E45: A meme with the text “Ferrari’s lawyers on their way to sue someone for modifying the car that they bought with their own money:” at the top, followed by an image of several men in suits walking out of a large building entrance. | F45: Exaggeration | H45: Pop culture | J45: Naomi | K45: Done | L45: Exaggeration | M45: Situational | N45: Pop culture | O45: Hobby | P45: =IF(COUNTIF($A$2:A45, A45)>1, "Dublet", "OK") -> OK
A46: 1d2jxbw | B46: Sabrina | C46: Done | D46: Dasani is highly regarded as one of the worst bottled water brands for its supposedly horrible taste | E46: A multi-panel comic showing a man stranded in a desert, crawling and asking for water. He finds a bottle labeled “Dasani,” expresses relief, then looks disappointed and throws the bottle away. | F46: Incongruity | H46: General knowledge | J46: Naomi | P46: =IF(COUNTIF($A$2:A46, A46)>1, "Dublet", "OK") -> OK
A47: 1d6ho4f | B47: Sabrina | C47: Done | D47: When you push your nail against a mosquito bite it stops it from itching for a bit | E47: A meme with the text “Do you need some anti itch cream?” followed by “Me: nah I’m good bro,” above an image of a hand with visible redness and irritation. | F47: Sarcasm/Irony | H47: General knowledge | J47: Naomi | P47: =IF(COUNTIF($A$2:A47, A47)>1, "Dublet", "OK") -> OK
A48: 1d8sg9b | B48: Sabrina | C48: Done | D48: Lots of anecdotal stories about how if you film at Chipotle you get larger portions. | E48: A meme with the text “going to chipotle ya’ll need anything” at the top, followed by an image of a man wearing a body-mounted camera rig with a large professional camera attached. | F48: Exaggeration | H48: Logical | J48: Naomi | P48: =IF(COUNTIF($A$2:A48, A48)>1, "Dublet", "OK") -> OK
A49: 1d98tf9 | B49: Sabrina | C49: Done | D49: Guy took out his town’s city hall, a former mayor’s house, and some other buildings, in a tank-like modified bulldozer, over a dispute with the city. He also committed suicide at the end of it. Lookup Killdozer. | E49: A meme with the text “Sometimes reasonable men must do unreasonable things” displayed above and below an image of a bulldozer-like machine. | F49: Dark Humor | H49: General knowledge | J49: Naomi | P49: =IF(COUNTIF($A$2:A49, A49)>1, "Dublet", "OK") -> OK
A50: 1dbipgs | B50: Sabrina | C50: Done | D50: The muscles and tendons in the ring finger are highly interconnected with, and partially dependent on, the pinky and middle finger. It's also very difficult to place all your fingers on a table and only lift up the ring finger, but lifting it with the ring or pinkly finger is easy. OP, you are a "mutant" in that you're part of the small percent of the population that can move their ring finger independently. It can become a learned ability, but that requires active training with the fingers, being able to do it naturally is very unique. It's why some people struggle to do the Vulcan hand sign form Star Trek. To add more info, in general, the muscles in our fingers are deeply connected to the forearm muscles. lay down one hand, put the other hand on your forearm, and just wiggle your fingers. You should feel your forearm tense and flex in different spots with each finger movement. The musculatory system is highly complex! | E50: A meme with the text “Only 1% of humans can do this” at the top, showing a hand with fingers positioned in an unusual way. At the bottom, the text reads “If you think is easy, re-check where the pinky is.” | F50: Exaggeration | H50: Logical | J50: Naomi | P50: =IF(COUNTIF($A$2:A50, A50)>1, "Dublet", "OK") -> OK
A51: 1dfrh37 | B51: Sabrina | C51: Done | D51: Because the king can't safely move, the match is a stalemate | E51: A multi-panel comic showing a queen confronting a king in a castle. The queen threatens the king with a sword, while the king warns her not to move to a certain space. In the next panel, the king appears in a different location unharmed, while the queen stands in the previous position. The final panel shows many fallen characters outside the castle and others reacting with frustration. | F51: Incongruity | H51: Logical | J51: Naomi | P51: =IF(COUNTIF($A$2:A51, A51)>1, "Dublet", "OK") -> OK
A52: 1di1z94 | B52: Sabrina | C52: Done | D52: This was posted yesterday on Chuck Shumer's Twitter. He made a post about grilling for Father's Day but had placed the cheese on a completely raw burger which no one would do indicating it was a staged photo or just another example of government incompetence. | E52: A meme with the text “I’m from the government and I’m here to help.” at the top, followed by an image of a burger patty on a grill with a slice of cheese placed directly on top. | F52: Exaggeration | H52: Social conventions | J52: Naomi | K52: Done | L52: Sarcasm/Irony | M52: Situational | N52: politics | O52: Social conventions | P52: =IF(COUNTIF($A$2:A52, A52)>1, "Dublet", "OK") -> OK
A53: 1dk6kds | B53: Sabrina | C53: Done | D53: In this episode of Tom & Jerry, Tom arrives at the gates of Heaven together with a group of other cats who recently died. These kittens are inside of a soaked sack, implying that they were drowned. The gatekeeper even says this has happened a lot. | E53: A meme comparing two stages of watching Tom and Jerry. The top shows a child watching a scene without understanding it, alongside a neutral facial expression. The bottom shows the same scene labeled “14 years later,” paired with a more serious facial expression. | F53: Incongruity | H53: Pop culture | J53: Naomi | P53: =IF(COUNTIF($A$2:A53, A53)>1, "Dublet", "OK") -> OK
A54: 1dlzvsx | B54: Sabrina | C54: Done | D54: The boots seems to be more detailed, so took more time to draw... That's all | E54: A screenshot of a social media post comparing drawings labeled “1978” and “2011,” showing a simpler sketch in the earlier year and a more detailed drawing of boots in the later year. | F54: Comparison | H54: Logical | J54: Naomi | K54: Done | L54: Comparison | M54: Situational | N54: Logical | O54: General knowledge | P54: =IF(COUNTIF($A$2:A54, A54)>1, "Dublet", "OK") -> OK
A55: 1do7yvv | B55: Sabrina | C55: Done | D55: His wife thinks he was protecting her from hitting her head on the table, but really he was keeping his secret stash of money from being discovered. | E55: A multi-panel comic showing a woman handling a wet cloth near a window. She attempts to dry or manage the cloth, while a man approaches and interacts with her. In a later panel, the woman kisses the man, and in the final panel, money is shown being placed on a surface near the window. | F55: Incongruity | H55: Logical | J55: Naomi | P55: =IF(COUNTIF($A$2:A55, A55)>1, "Dublet", "OK") -> OK
A56: 1dr9jg6 | B56: Sabrina | C56: Done | D56: He plays music in that background while holding his finger up and a caption rolling such as “ Song X is like/sampled/copied from Song Y” - all the while staring blankly at the camera. | E56: A two-panel meme showing a school bus on train tracks with a train approaching. The top panel includes text describing small creators trying to get views. The bottom panel shows the train colliding with the bus, with additional text and an image of a man inserted over the train. | F56: Situational | H56: Pop culture | J56: Naomi | P56: =IF(COUNTIF($A$2:A56, A56)>1, "Dublet", "OK") -> OK
A57: 1dtmedg | B57: Sabrina | C57: Done | D57: The man is either presenting a puzzle ("find x") or making an assertion ("7 + x is the same thing as 7 \* x"), and either way, the woman isn't having it. | E57: A two-panel comic showing a man lying on a couch looking at his phone with a speech bubble containing the equation “7 + x = 7x.” In the second panel, a woman next to him looks down and says, “I think we should see other people.” | F57: Situational | H57: Logical | J57: Naomi | K57: Done | L57: Situational | M57: Exaggeration | N57: Technical | O57: General knowledge | P57: =IF(COUNTIF($A$2:A57, A57)>1, "Dublet", "OK") -> OK
A58: 1dwa7tj | B58: Sabrina | C58: Done | D58: There was a practice back then to create Castrati, essentially choir boys castrated before puberty in order to maintain a high pitched singing voice. | E58: A four-panel comic showing a boy and a priest in a church talking about singing, followed by a final panel of an adult sitting by a fireplace with text about losing his balls. | F58: Incongruity | H58: General knowledge | J58: Naomi | P58: =IF(COUNTIF($A$2:A58, A58)>1, "Dublet", "OK") -> OK
A59: 1e0k66e | B59: Sabrina | C59: Done | D59: Its a coding joke. You ask for 0 wishes, and that in itself is a wish, so you ends up with -1 wishes. But old computing systems can't take negative integers, so it gets set to 255, which is the 8-bit integer limit. edit: wording edit2: Any system *can* take negative numbers if you program it to, but this particular problem is mostly exists on old systems due to either technological limits/budget or was never intended to account for them. | E59: A meme with text at the top showing a dialogue: “Genie: You have three wishes,” “Me: Make it 0,” and “Genie: Ok, you now have 255.” Below the text is an image of a blue cartoon genie sitting and thinking. | F59: Wordplay | H59: Technical | J59: Naomi | P59: =IF(COUNTIF($A$2:A59, A59)>1, "Dublet", "OK") -> OK
A60: 1e2qvt9 | B60: Sabrina | C60: Done | D60: There's a common phrase in the atheist community. "Read parts of the bible and you become a Christian, read the whole bible and you become an atheist." As an atheist that used to be christian I can agree with the sentiment even though it's a bit oversimplified. | E60: A meme with the text “Just read the Bible for yourself and you’ll see why I’m right” at the top. Below are two images labeled “People who don’t know” and “People who know,” showing a normal-looking character on the left and a darker, unsettling face on the right | F60: Exaggeration | H60: Social conventions | J60: Naomi | P60: =IF(COUNTIF($A$2:A60, A60)>1, "Dublet", "OK") -> OK
A61: 1e6m88u | B61: Sabrina | C61: Done | D61: The bottom is Stevie Nicks and Lindsey Buckingham of Fleetwood Mac. They were a couple when they joined the band in the 70s. By the time of their classic album Rumours, they had broken up very acrimoniously. They started writing basically diss songs about each other for the album. Also, basically every member of the band beside Mick Fleetwood and John Mcvie (edit to make this more clear, the only members not sleeping with each other) sleeping together. There was also a lot of cocaine. They made a masterpiece. | E61: A two-panel meme showing a woman at the top with text about writing songs about her exes, and a couple at the bottom with the text “That’s cute.” | F61: Comparison | H61: Pop culture | J61: Naomi | P61: =IF(COUNTIF($A$2:A61, A61)>1, "Dublet", "OK") -> OK
A62: 1ea5yhw | B62: Sabrina | C62: Done | D62: It's less professional than a navy, gray, or black one. Certain Obama opponents tried to blow it up into a scandal. This post is poking fun at those people for losing their mind over what is in the and a perfectly acceptable suit. | E62: A screenshot of a post asking about Obama wearing a tan suit, with an image of Barack Obama standing outside in a tan suit. | F62: Sarcasm/Irony | H62: Pop culture | J62: Naomi | P62: =IF(COUNTIF($A$2:A62, A62)>1, "Dublet", "OK") -> OK
A63: 1eeayas | B63: Sabrina | C63: Done | D63: One participant’s name is listed as J Christ. That is very much like Jesus Christ, a famed religious figure that reputedly walked on water. Being able to walk on water would be an unfair advantage. | E63: A post with text about unfair advantage in water, showing two rowers in a boat during a competition. | F63: Sarcasm/Irony | H63: History/Mythology | J63: Naomi | P63: =IF(COUNTIF($A$2:A63, A63)>1, "Dublet", "OK") -> OK
A64: 1efs65o | B64: Sabrina | C64: Done | D64: The commenter is referring to the fact it could also look like the one star dragonball from a show called dragonball. | E64: An image of a hand holding an orange with a red star shape on it, with text above and below referencing “A Soviet Orange.” | F64: Comparison | H64: Hobby | J64: Naomi | P64: =IF(COUNTIF($A$2:A64, A64)>1, "Dublet", "OK") -> OK
A65: 1eko6xo | B65: Sabrina | C65: Done | D65: I believe it was revealed some time ago that BetterHelp's service is actually very lackluster. | E65: A two-panel meme showing a man sweating at the top and another man reacting below, with text about a video being sponsored. | F65: Comparison | H65: Pop culture | J65: Naomi | P65: =IF(COUNTIF($A$2:A65, A65)>1, "Dublet", "OK") -> OK
A66: 1elhse8 | B66: Sabrina | C66: Done | D66: The joke is that the modern ballpoint pen is a perfectly designed technology that would be unaffected by the butterfly effect. The design has survived long enough that not even time travel could stop its use. | E66: A meme with the text “Time traveller: moves a chair” and “Timeline:” above four images of identical blue pens labeled 1955, 1985, 2015, and 2021 | F66: Comparison | H66: Technical | J66: Naomi | P66: =IF(COUNTIF($A$2:A66, A66)>1, "Dublet", "OK") -> OK
A67: 1eq297i | B67: Sabrina | C67: Done | D67: These were sold in vending machine inside break rooms, usually at manufacturing plants. They were usually in the vending machine that rotates. You have to open the little door and pull it out. Edit: These were a great choice at 7 am, first thing In the morning, because you didn’t get home from the bars before 3:30 am. | E67: A screenshot of a tweet stating “if you’ve never eaten one of these i don’t want to hear your opinion on labor rights” above an image of a packaged “Big AZ Cheeseburger” and a cheeseburger. | F67: Comparison | H67: General knowledge | J67: Naomi | P67: =IF(COUNTIF($A$2:A67, A67)>1, "Dublet", "OK") -> OK
A68: 1et8l0q | B68: Sabrina | C68: Done | D68: I think the joke is that they typed in their calculator app by accident rather than setting their alarm clock. | E68: A screenshot of a text conversation labeled “Boss” asking “Why are you late to work??” with a reply showing a calculator displaying “630,” followed by “Understandable, have a nice day.” | F68: Situational | H68: Logical | J68: Naomi | P68: =IF(COUNTIF($A$2:A68, A68)>1, "Dublet", "OK") -> OK
A69: 1ex1lej | B69: Sabrina | C69: Done | D69: They’re out of business, so someone could use it as resume fluff | E69: A meme with the text “Remember, no one can prove you weren’t a regional manager for RadioShack or Toys’R’Us” above an image of a man staring intensely. | F69: Exaggeration | H69: General knowledge | J69: Naomi | P69: =IF(COUNTIF($A$2:A69, A69)>1, "Dublet", "OK") -> OK
... A72: 1f16w9p | B72: Sabrina | C72: Done | D72: it's a prank device that give you a small shock when you try to take the gum | E72: A meme with the text “this is where my trust issues started” above three packs of chewing gum labeled “PULL HERE,” each partially opened with a strip visible. | F72: Situational | H72: General knowledge | J72: Naomi | P72: =IF(COUNTIF($A$2:A72, A72)>1, "Dublet", "OK") -> OK
B73: Sabrina | C73: Done | D73: Grave of the Fireflies, it's a grade A tear jerker. | E73: An image of a boy carrying a child in front of a burning building, with text below showing a conversation where one person asks “Show?” and another replies “no this is for your own good.” | F73: Sarcasm/Irony | H73: Pop culture | J73: Naomi | P73: =IF(COUNTIF($A$2:A73, A73)>1, "Dublet", "OK") -> OK
A74: 1fbym0h | B74: Sabrina | C74: Done | D74: One likes to eat, one goes to the gym, and one survives off energy drinks and snicker bars. Probably. | E74: A meme with the text “Average male friend group:” above an image of three items on a store shelf: a yellow Heinz mustard bottle placed upside down, a green Prime drink bottle, and a pink Alani energy drink can. | F74: Comparison | H74: Social conventions | J74: Naomi | P74: =IF(COUNTIF($A$2:A74, A74)>1, "Dublet", "OK") -> OK
A75: 1fdg0i5 | B75: Sabrina | C75: Done | D75: Alan Turing was gay and was pretty brutally persecuted for it by the UK government. He's the guy who kind of invented modern computing and did things like help crack the German Enigma code. Despite his accolades he ended up taking his life because of mistreatment by the country he helped survive. | E75: A screenshot of a tweet reading “The British government the second ww2 was over” above an image of a woman speaking, with overlaid text “you’re telling me a queer coded this.” | F75: Dark Humor | H75: politics | J75: Naomi | P75: =IF(COUNTIF($A$2:A75, A75)>1, "Dublet", "OK") -> OK
A76: 1fg38dp | B76: Sabrina | C76: Done | D76: The word they’re looking for is homage | E76: A screenshot of a tweet saying “Open the schools” quoting another tweet about Megan Thee Stallion paying mortgage to Beyoncé, with two side-by-side images of the two artists wearing similar outfits. | F76: Comparison | H76: Logical | J76: Naomi | P76: =IF(COUNTIF($A$2:A76, A76)>1, "Dublet", "OK") -> OK
A77: 1fm0tjo | B77: Sabrina | C77: Done | D77: Someone feels old because they remembered Y2K was a thing. | E77: A meme showing a sticker reading “REMEMBER Turn your computer off before midnight on 12/31/99” above an image of a man with the caption “I was there. 3,000 years ago…” | F77: Exaggeration | H77: Logical | J77: Naomi | K77: Done | L77: Exaggeration | M77: Situational | N77: Logical | O77: General knowledge | P77: =IF(COUNTIF($A$2:A77, A77)>1, "Dublet", "OK") -> OK
A78: 1fs6ndo | B78: Sabrina | C78: Done | D78: Tyranids avoid two things , demon and necron. Tbf thé latter are probably a better news than the nids | E78: A three-panel meme showing a soldier in armor with text: “A Tyranid fleet is approaching the system,” followed by two panels both stating “It ignores your planet,” with the soldier’s facial expression changing. | F78: Comparison | H78: Hobby | J78: Naomi | P78: =IF(COUNTIF($A$2:A78, A78)>1, "Dublet", "OK") -> OK
A79: 1fo91u1 | B79: Sabrina | C79: Done | D79: The Logo designer normally charges 350$ But the person asking for the logo has a budget of 800$ 800$ is more dollars than the 350$, this is an important fact which can be easily overlooked. So just about as the logo desinger was to send their message they see this. And after doing a bit of math and self refelection they think to themselves. "hmm, I could also charge 800$ as that is more than 350$" Which will allow the logo desinger to buy more peanuts. Peanuts are tasty. Also shrek is there for the 'hold on a moment' thing and obviously for the sex appeal. | E79: A screenshot of a chat where a person asks for a logo price, states a budget of $800, and a reply is typed “Logo design price is $350,” followed by an image of Shrek smiling. | F79: Situational | H79: Logical | J79: Naomi | K79: Done | L79: Situational | M79: Surprise | N79: General knowledge | O79: Logical | P79: =IF(COUNTIF($A$2:A79, A79)>1, "Dublet", "OK") -> OK
A80: 1fst6nb | B80: Sabrina | C80: Done | D80: Yeah its a political joke, the neighbours have taken a part of the other person's garden just like Russia has taken parts of Ukraine. Hopefully that helps. | E80: Drawing of a man standing by a fence talking to two neighbors inside a yard; a speech bubble says: “No, we’ve never had Russian neighbours. You are the first.” | F80: Comparison | H80: politics | J80: Naomi | P80: =IF(COUNTIF($A$2:A80, A80)>1, "Dublet", "OK") -> OK
A81: 1fu3pp1 | B81: Sabrina | C81: Done | D81: that is way too good for a school computer. it's clearly for gaming | E81: Four-panel meme: top text shows a mother asking for a PC for school and a son listing high-end specs; bottom panels show Shrek smiling. | F81: Incongruity | H81: Technical | J81: Naomi | P81: =IF(COUNTIF($A$2:A81, A81)>1, "Dublet", "OK") -> OK
A82: 1fuxrbx | B82: Sabrina | C82: Done | D82: The numbers when pressed will correlate to different letters. For example, pressing 2 will give you A, but pressing 22 will give you B, 222 giving you C, and so on. This pattern of numbers spells, "It was me Dio!" Which is a reference to the anime Jojo's Bizarre Adventure. The line is said by the main antagonist, named Dio Brando. | E82: Image of an old mobile phone keypad with numbers and letters; below it is the sequence: “4448 927777 633 3444666”. | F82: Surprise | H82: Hobby | J82: Naomi | P82: =IF(COUNTIF($A$2:A82, A82)>1, "Dublet", "OK") -> OK
A83: 1fwbzz9 | B83: Sabrina | C83: Done | D83: A small county sent out an emergency alert to the entire state, setting off everyone’s phone with a loud alarm at 4:53 am. It was to be on alert for a white guy in a blue shirt and pants who shot a cop. Texas is a huge state so people literally 10 hours away got alerted and woken up. Everyone is pissed off, and it’s against the rules of the emergency alert to use it during those hours, and we don’t know if it was by accident or just negligence. Let me clarify a point: it’s only Amber and Blue Alerts that aren’t supposed to be sent between 11pm and 6am, other emergencies can go off any time. These are also internal rules, not laws. | E83: Text “all of texas at 4:53 am” above a photo of a man lying in bed looking tired and confused while holding a phone. | F83: Situational | H83: General knowledge | J83: Naomi | P83: =IF(COUNTIF($A$2:A83, A83)>1, "Dublet", "OK") -> OK
A84: 1fxqzyt | B84: Sabrina | C84: Done | D84: She is meaning to say, “aww, thank you so much”. He apparently has autism and doesn’t realize she was texting an acronym so he read it as a misspelling of autism, aww-tysm. | E84: Four-panel comic: a person receives “You’re cute”, replies “Aww tysm”, then misreads it as “Awwtism?”, and lies in bed holding a phone. | F84: Wordplay | H84: Social conventions | J84: Naomi | P84: =IF(COUNTIF($A$2:A84, A84)>1, "Dublet", "OK") -> OK
A85: 1g02nzf | B85: Sabrina | C85: Done | D85: There was a copper merchant named Ea-Nasir who lived around 1750 BC. Archeologists have discovered several clay tablets complaining about this guy by name (saying that he sold them substandard copper, was very slow on deliveries, etc). This is interesting because these are the oldest recorded customer complaints. Ea-Nasir has become kind of a meme on some parts of the internet, so this sticker is a joke about him. | E85: Screenshot of a post showing an object with the text: “WELL BEHAVED COPPER INGOT MERCHANTS RARELY MAKE HISTORY”. | F85: Situational | H85: History/Mythology | J85: Naomi | P85: =IF(COUNTIF($A$2:A85, A85)>1, "Dublet", "OK") -> OK
A86: 1g7yhzc | B86: Sabrina | C86: Done | D86: The OP is trying to say that certain people, especially trans women over a certain age who use the internet, type in a very distinct, tumblr-esque, "chronically online" style. The person who replies is trans (as you can tell by the flag in their username) and uses a lot of abbreviations and certain punctuation that is seemingly the exact style of writing the OP was describing. The joke is that, ironically, the person in that category doesn't seem to realise there is a distinctive style of writing, despite the fact they themselves are using it (although this may be satire/intentional) Edit: In addition, as many of the replies suggested, there's a bit of another layer: they are most likely (like 99% chance) overexaggerating the unique typing to join in on the joke - sarcastically saying "I have noooo idea what you could mean by that", basically :) | E86: Screenshot of a tweet mentioning a “28+ year old trans girlfriend and how they type”; below, a reply says: “hey rq i’m just Really Curious what u mean by that,,,,”. | F86: Exaggeration | H86: Social conventions | J86: Naomi | P86: =IF(COUNTIF($A$2:A86, A86)>1, "Dublet", "OK") -> OK
A87: 1g4657e | B87: Sabrina | C87: Done | D87: Not Floridian but isn't the north of Florida bordering with some "southern" US-states, culturally speaking? (Florida being rather hispanic/caribbean, the more south you go) | E87: Meme with text about Florida: “the more North you go, the farther South you’re in”; below is Captain America with the caption “Ancient Egyptians: I understood that!” | F87: Exaggeration | H87: History/Mythology | J87: Naomi | P87: =IF(COUNTIF($A$2:A87, A87)>1, "Dublet", "OK") -> OK
A88: 1gazv8u | B88: Sabrina | C88: Done | D88: Saddam hussein hiding spot | E88: Comic showing an ape asking for a “pattern-seeking brain”, an image of DNA, and a final panel with an object on the ground. | F88: Dark Humor | H88: politics | J88: Naomi | P88: =IF(COUNTIF($A$2:A88, A88)>1, "Dublet", "OK") -> OK
A89: 1gidb47 | B89: Sabrina | C89: Done | D89: In real life, most hackers are scammers who rely on exploiting people’s trust to obtain passwords rather than bypassing them. | E89: Two-part meme: top shows a person with a laptop and text “writes a few lines of code ‘I’m in.’”; bottom shows another person at a computer with text about asking for passwords. | F89: Situational | H89: Technical | J89: Naomi | P89: =IF(COUNTIF($A$2:A89, A89)>1, "Dublet", "OK") -> OK
A90: 1gop1dk | B90: Sabrina | C90: Done | D90: The Joke is, when a small Child sleeps at this time of the day, it will BE awake all night and you dont want that to happen as a parent. | E90: Tweet with text about trying to entertain someone so they don’t take a long nap; below is a yellow emoji holding a bat. | F90: Exaggeration | H90: General knowledge | J90: Naomi | P90: =IF(COUNTIF($A$2:A90, A90)>1, "Dublet", "OK") -> OK
A91: 1gqh1c5 | B91: Sabrina | C91: Done | D91: This person used to work in a kitchen, where you ABSOLUTELY need to inform people when you’re near them. Otherwise you get stabbed or cause an accident. The joke is they’re still using that mindset even in a relaxed office break room. Edit: may also be because they watched the bear and are acting it out, as some comments have nicely, and not so nicely pointed out lol. | E91: Tweet text: “shouting ‘corner!’ and ‘behind!’ while heating up cup noodles in the office break room”. | F91: Situational | H91: Social conventions | J91: Naomi | P91: =IF(COUNTIF($A$2:A91, A91)>1, "Dublet", "OK") -> OK
... A94: 1gx0pu0 | B94: Sabrina | C94: Done | D94: So basically Pikachu(yellow one) is a normal Pokémon while Mew (white one) is an extremely rare Pokémon with phenomenal powers and basically considered a god in the Pokémon universe. But it is kinda a childish Pokémon who enjoys nature and loves to play. | E94: Image from Pokémon: Mew and Pikachu are standing on grass; Pikachu is holding a spinning top-like object; below is a Tumblr-style caption beginning with “aspidelaps:” and text about meeting Jesus. | F94: Comparison | H94: Pop culture | J94: Naomi | P94: =IF(COUNTIF($A$2:A94, A94)>1, "Dublet", "OK") -> OK
A95: 1gz2i0o | B95: Sabrina | C95: Done | D95: I believe it’s Plymouth Rock. Something about being where the pilgrims first landed in America. So a big deal historically, but a pretty boring rock in reality | E95: Photo of a stone on a sandy ground near water behind a metal fence; text over the image reads: “You’ll never disappoint your mom as much as this stone disappoints tourists.” | F95: Exaggeration | H95: History/Mythology | J95: Naomi | K95: Done | L95: Comparison | M95: Exaggeration | N95: History/Mythology | O95: General knowledge | P95: =IF(COUNTIF($A$2:A95, A95)>1, "Dublet", "OK") -> OK
A96: 1gzkbbi | B96: Sabrina | C96: Done | D96: Colin Kapernik was kneeling during the national anthem to protest the killings of unarmed black men by police officers alongside BLM, the bottom image is NFL guys celebrating with the Trump dance (because they're like supporting him and his stances) | E96: Meme with text “WE WENT FROM THIS” above an image of three African American football players kneeling; below are images of other football players standing, followed by “TO THIS...”. | F96: Comparison | H96: Hobby | J96: Naomi | P96: =IF(COUNTIF($A$2:A96, A96)>1, "Dublet", "OK") -> OK
A97: 1h5a44z | B97: Sabrina | C97: Done | D97: According to reverse image search, that is the Master Debater guy. He became a meme when he was the "Both" guy in the conversation at the bottom of the text. So, he would disarm the stupid fucking shit Jigsaw says and just refuse the trial until he gets let go LGBTQ rights or economic stability? - Why can't you have both? - You need to pick one. - Refuse the question. - LGBTQ rights or economic stability? - Why can't you have both? - You need to pick one. - Refuse the question. - You can't refuse the question. - I do. - But you can't. - But I did. - But you need to pick one. - No, I don't. - I just said you did. - Hahaha, so what? - Can you pick one? - No, because they're both doable. - No, only one. - I don't have to pick one because we can have both. - But the answer is that both is not an answer. It's not a valid answer. - I reject your question. - You can't reject it. - Just did. - Can you pick one? - I don't have to. - Why? - Because they're both completely doable. - So LGBTQ rights or economic stability? - Both. - That's not an answer. - Yes it is. - LGBTQ rights or economic stability. - Both. - Are you trying to troll me. - No. - I'm just wondering which one you like more. - I like them both, - You can't have both. - Yes you can. - Not in this question. - Haha, too bad. - Why are you trolling me right now? - Because I don't have to choose. - Well, if I had to ask you gender inclusivity or economic stability? - You can have both. - You can't. - Why make this so difficult? I'm trying to pass my final. - Too bad. - Which one do you pick? - I pick them both. - Uhm, that's not a vaild answer. - Too bad. - Okay. [Shaking hands] - Thank you. -Thank you. | E97: Screenshot of a tweet asking: “what are two characters you’d wanna put in a room together just to see what happens”; above are two images, one of a man in a jacket outdoors and one of a puppet-like face on a screen. | F97: Comparison | H97: Pop culture | J97: Naomi | K97: Done | L97: Comparison | M97: Situational | N97: Pop culture | O97: meme | P97: =IF(COUNTIF($A$2:A97, A97)>1, "Dublet", "OK") -> OK
A98: 1h7di4x | B98: Sabrina | C98: Done | D98: he wants to shape the world according to his own liking. | E98: Text at the top says: “How I look at bro after we get superpowers and he says ‘let’s fix the world’ instead of ‘save’”; below is a close-up of a man looking sideways with a serious expression. | F98: Wordplay | H98: Logical | J98: Naomi | P98: =IF(COUNTIF($A$2:A98, A98)>1, "Dublet", "OK") -> OK
A99: 1h8d39n | B99: Sabrina | C99: Done | D99: (deep breath) Here we go, in Zootopia, Disney made several significant changes to the plot before its release, altering the film's tone and themes. Originally, all predators were supposed to wear control collars that shocked them when they felt strong emotions, symbolizing societal oppression, but this concept was deemed too dark for a family movie. The initial story also presented a bleaker view of discrimination, with prey animals as the oppressors of predators, which was shifted to focus on cooperation and understanding instead. The main villain was Initially going to be Mayor Swinton, a pig representing societal control, but was changed to Bellwether, a sheep whose betrayal added a surprising twist. Nick Wilde's backstory was originally darker, emphasizing his childhood trauma from prejudice, but this was toned down for a lighter narrative. The first draft included a storyline where Nick dealt with a virus causing savage behavior but managed to control it, this was simplified in the final version to highlight themes of acceptance. (Sigh of relief) | E99: Split image with text on the left: “The zootopia plot Disney gave us” and below “The original Zootopia plot Disney denied”; on the right are two images of a man in a suit, one smiling and one serious. | F99: Comparison | H99: Hobby | J99: Naomi | P99: =IF(COUNTIF($A$2:A99, A99)>1, "Dublet", "OK") -> OK
A100: 1h52vkf | B100: Sabrina | C100: Done | D100: People have been reporting that when you give ChatGPT a prompt that involves David Mayer it breaks the session. Nobody seems to know why yet, some are saying it is because he had his info pulled, but because he is a Rothschild people are coming up with all sorts of conspiracy theories. | E100: Text at the top says: “What’s the next test?” followed by: “ChatGPT watching everyone asking it to write ‘David Mayer’ after it just learnt that strawberry has 3 r’s”; below is an image of a humanoid robot with a neutral expression. | F100: Comparison | H100: General knowledge | J100: Naomi | P100: =IF(COUNTIF($A$2:A100, A100)>1, "Dublet", "OK") -> OK
A101: 1hfggtz | B101: Sabrina | C101: Done | D101: Drywall vs WALL | E101: Two-panel image with text on the left: “When Americans punch their wall” above an anime character punching a wall; below: “When Europeans punch their wall” above the same character holding their head in pain. | F101: Comparison | H101: Technical | J101: Naomi | P101: =IF(COUNTIF($A$2:A101, A101)>1, "Dublet", "OK") -> OK
A102: 1hmbnol | B102: Sabrina | C102: Done | D102: That command line, “sudo rm -fr /\*” is a command to remove the french language pack from your computer… *Technically* It does this by completely wiping your entire system, including the OS. Basically bricking your computer and forcing you to do a full reinstall of the operating system. | E102: Screenshot with text: “ Linux tips 1. Always remove the french language pack: sudo rm -fr /*”; below are two faces labeled “PEOPLE WHO DON’T KNOW” and “PEOPLE WHO KNOW…”. | F102: Comparison | H102: Technical | J102: Naomi | P102: =IF(COUNTIF($A$2:A102, A102)>1, "Dublet", "OK") -> OK
A103: 1hqtnop | B103: Sabrina | C103: Done | D103: An infamous advertisement in Britain saying that the government will be providing for the needs of homeless people, but it reads like they will mutilate them instead: "We plan to cut homeless people in half in 2025. | E103: Text at the top: “Homeless people on December 31st 2024:” above a photo of a sweating man looking sideways with a serious expression. | F103: Wordplay | H103: politics | J103: Naomi | P103: =IF(COUNTIF($A$2:A103, A103)>1, "Dublet", "OK") -> OK
A104: 1huqauz | B104: Sabrina | C104: Done | D104: Absolutely every single human with a pulse calls the it the "X" button regardless of console. PlayStation insists that it's actually called "cross" on theirs for some reason and is politely corrected with a Futurama meme. | E104: Screenshot of a PlayStation UK post listing “Triangle, Circle, Cross, Square” and asking: “If Cross is called X (it’s not), then what are you calling Circle?”; below is a Futurama scene with a PlayStation logo over one character and text “WRONG AGAIN IDIOT”. | F104: Incongruity | H104: General knowledge | J104: Naomi | K104: Done | L104: Incongruity | M104: Comparison | N104: Hobby | O104: General knowledge | P104: =IF(COUNTIF($A$2:A104, A104)>1, "Dublet", "OK") -> OK
A105: 1i5ve1j | B105: Sabrina | C105: Done | D105: There were protests in China, Tiananmen Square, in 1989, ended up with lots of casualties. And TS stands for Taylor Swift, born in 1989 | E105: wo stacked panels: top shows Fry holding money with the label “Swifties” and text “Shut up and take my money!”; bottom shows Fry with a skeptical expression labeled “Historians”; to the right are two identical black hoodies with “T.S. 1989” printed on them. | F105: Comparison | H105: History/Mythology | J105: Naomi | P105: =IF(COUNTIF($A$2:A105, A105)>1, "Dublet", "OK") -> OK
A106: 1iad0kh | B106: Sabrina | C106: Done | D106: Freud had ideas about how our relationships are always coloured by the first relationship we had with a person of the other sex, our father or our mother. | E106: Text at the top: “Every time you call your boyfriend ‘Daddy’, Sigmund Freud’s ghost becomes a little stronger.”; below is a black-and-white portrait of Sigmund Freud. | F106: Incongruity | H106: Technical | J106: Naomi | P106: =IF(COUNTIF($A$2:A106, A106)>1, "Dublet", "OK") -> OK
A107: 1ibz4bh | B107: Sabrina | C107: Done | D107: A brute force will go through every password once, this code means the first time you get it right it will return a wrong password so you have to enter it twice. Hence a brute force will only try once and then skip the correct password. I probably worded this horribly | E107: Multi-panel comic: several office workers react with shocked expressions while one spills coffee; final panel shows code on a screen reading: “// brute-force attack protection if isPasswordCorrect && isFirstLoginAttempt { Error(‘Wrong login or password’) }”. | F107: Incongruity | H107: Technical | J107: Naomi | P107: =IF(COUNTIF($A$2:A107, A107)>1, "Dublet", "OK") -> OK
A108: 1ig7lnf | B108: Sabrina | C108: Done | D108: Your brain on drugs | E108: Text at the top: “If you watched TV in the 80s you know this isn’t an egg”; below is a frying pan with a fried egg being cooked on a stove. | F108: Incongruity | H108: Pop culture | J108: Naomi | P108: =IF(COUNTIF($A$2:A108, A108)>1, "Dublet", "OK") -> OK
A109: 1inxmb2 | B109: Sabrina | C109: Done | D109: picture of a guy, top text, bottom text. therefore, meme | E109: Screenshot of a tweet: “little brother told me ‘money is the oldest meme’ and proceeded to describe this image”; below is a one-dollar bill labeled “FEDERAL RESERVE NOTE ONE DOLLAR”. | F109: Comparison | H109: Logical | J109: Naomi | P109: =IF(COUNTIF($A$2:A109, A109)>1, "Dublet", "OK") -> OK
A110: 1iri57s | B110: Sabrina | C110: Done | D110: It's the year 2025. Everyone who was born in 19XX is at least 25 years old, well above the legal age for drinking. | E110: Text conversation: “cashier checks my ID in half a second Me: ‘That was fast.’ Cashier: ‘Yeah, I saw the 19.’ Me:” followed by an image of a woman with a surprised expression. | F110: Surprise | H110: Social conventions | J110: Naomi | P110: =IF(COUNTIF($A$2:A110, A110)>1, "Dublet", "OK") -> OK
A111: 1iv0i8s | B111: Sabrina | C111: Done | D111: He puts a yellow cap on his black sharpie so nobody steals it. Nobody wants a yellow sharpie. | E111: Two-panel image: top text says “Why no one takes my sharpie” above a Sharpie marker with a yellow cap; bottom shows the same marker with the cap removed, revealing black ink. | F111: Situational | H111: Logical | J111: Naomi | P111: =IF(COUNTIF($A$2:A111, A111)>1, "Dublet", "OK") -> OK
A112: 1h626bt | B112: Sabrina | C112: Done | D112: His grades went down in history. "Rudolph the Red-Nosed Reindeer, you'll go down in history" are the lyrics | E112: A cartoon reindeer with a red nose is sitting at a desk holding a report card. The card shows grades for subjects like math, science, English, history, art, and gym, with mixed grades (e.g., B-, A, B, D, A-). Other reindeer students are visible in the background holding similar papers. | F112: Wordplay | H112: Hobby | J112: Naomi | P112: =IF(COUNTIF($A$2:A112, A112)>1, "Dublet", "OK") -> OK
A113: 1hcpvbz | B113: Sabrina | C113: Done | D113: One of my fav episodes :D Peppa spends the whole episode being envious that others can whistle and tries do it as well. And it finishes like that. The expression and the timing kill me every time. And i'm a 32 yo dude :D (with 2 daughters) | E113: A screenshot of a tweet showing Peppa Pig standing indoors next to a wall-mounted telephone, pressing a button. Below the image, another user comments: “anyway can yall whistle ?”. The interface shows likes, retweets, and replies. | F113: Situational | H113: Pop culture | J113: Naomi | K113: Done | L113: Situational | M113: Comparison | N113: Pop culture | O113: Hobby | P113: =IF(COUNTIF($A$2:A113, A113)>1, "Dublet", "OK") -> OK
A114: 1izj4eu | B114: Sabrina | C114: Done | D114: PETA is the People for the Ethical Treatment of Animals. their stated mission is to get rid of all animal testing and have people treat animals nicely. what they actually do is run high-kill shelters, kidnap and execute pets, destroy years of research by breaking into testing labs and releasing the test animals, target children with messages like "your daddy kills animals", attempt to link milk with autism, and so forth. they are not a friend to animals, despite the name | E114: Text at the top reads: “Me, after reading ‘approved by Peta’ on my shampoo bottle.” Below, a cartoon cat (Tom from Tom and Jerry) is sitting in a chair holding a newspaper, looking to the side with a suspicious and slightly displeased expression. | F114: Incongruity | H114: General knowledge | J114: Naomi | P114: =IF(COUNTIF($A$2:A114, A114)>1, "Dublet", "OK") -> OK
A115: 1j983b2 | B115: Sabrina | C115: Done | D115: Divorce. Both are removing their former significant-other from the social media profiles they present to others. | E115: Text reads: “When the wife starts posting selfies and the husband changes his profile pic to the kids.” Below are two identical images of a puppet-like character with red hair and a neutral, slightly uneasy facial expression, facing sideways. | F115: Comparison | H115: Social conventions | J115: Naomi | P115: =IF(COUNTIF($A$2:A115, A115)>1, "Dublet", "OK") -> OK
A116: 1jaysny | B116: Sabrina | C116: Done | D116: I think that the meme suggests people who don't know will think that the family set up the baby on fire making them weirdos, and people who know recognize that this is a family of Incredibles and the baby has superpowers so it's fine and dandy. | E116: Top image shows a happy family (two adults and two children) sitting around a campfire roasting marshmallows inside a glowing dome-like setting. Below are two versions of Mr. Incredible: one labeled “People who know” (normal face) and one labeled “People who don’t know” (dark, distorted face). | F116: Incongruity | H116: Pop culture | J116: Naomi | P116: =IF(COUNTIF($A$2:A116, A116)>1, "Dublet", "OK") -> OK
A117: 1jh5toe | B117: Sabrina | C117: Done | D117: It’s a meme that women find men unattractive if they display any emotion, especially negative emotions like fear or sadness | E117: A tweet by “Diego Lopez” reads: “My face during a plane crash so my wife doesn’t get the ick.” Below is a close-up image of a woman with red hair looking straight ahead with a serious, controlled facial expression. | F117: Exaggeration | H117: Social conventions | J117: Naomi | P117: =IF(COUNTIF($A$2:A117, A117)>1, "Dublet", "OK") -> OK
...
